Workbook
Name Slicer_Ability1: #N/A
Name Slicer_Ability2: #N/A
Name Slicer_HiddenAbility: #N/A

Sheet DUMP
A1: # See the documentation on the wiki to learn how to edit this file.
A2: #-------------------------------
A3: [KOFFING] | E3: =A3&","&A4&","&A5&","&A6&","&A7&","&A8&","&A9&","&A10&","&A11&","&A12&","&A13&","&A14&","&A15&","&A16&","&A17&","&A18&","&A19&","&A20&","&A21&","&A22&","&A23&","&A24&","&A25&","&A26&","&A27 -> [KOFFING],Name = Koffing,Types = FIRE,BaseStats = 60,50,45,35,65,85,GenderRatio = Female50Percent,GrowthRate = Medium,BaseExp = 68,EVs = SPECIAL_DEFENSE,1,CatchRate = 190,Happiness = 70,Abilities = LEVITATE,WHITESMOKE,HiddenAbilities = FILTER,Moves = 1,POISONGAS,1,DEFENSECURL,5,EMBER,9,SMOG,12,HAZE,16,INCINERATE,19,CLEARSMOG,22,GYROBALL,26,CORRODE,30,SUNNYDAY,34,LAVAPLUME,38,DESTINYBOND,42,CORROSIVEGAS,45,ACIDRAIN,49,MEMENTO,54,ERUPTION,TutorMoves = TOXIC,HIDDENPOWER,SUNNYDAY,PROTECT,FRUSTRATION,RETURN,REFLECT,SLUDGEWAVE,FLAMETHROWER,SLUDGEBOMB,FIREBLAST,FACADE,REST,ATTRACT,OVERHEAT,SCALD,INCINERATE,WILLOWISP,EXPLOSION,SUBSTITUTE,HEATWAVE,SLEEPTALK,WEATHERBALL,FIRESPIN,CHARGEBEAM,SOLARBEAM,SOLARBLADE,MUDSHACKLES,STEALTHROCK,BEATUP,ALLERGY,ACIDRAIN,GASTROACID,ACIDARMOR,HEX,CURSE,CONFUSERAY,OMINOUSWIND,METEORDRIVE,GAMMARAY,GRAVITY,ROUND,ECHOEDVOICE,SCHIZOPHRENIA,RAYOFLIGHT,SIGNALBEAM,BODYSLAM,BALANCERCHANGEREQUIRED,NASTYPLOT,GUNKSHOT,SHADOWBALL,GYROBALL,BEJEWELED,POWERGEM,BURNINGJEALOUSY,FIREPLEDGE,SHOCKWAVE,SCORCHINGSANDS,STEAMROLLER,ZENHEADBUTT,TWINBEAM,WORKUP,CORROSIVEGAS,VITALITYDRAIN,MEMENTO,GRUDGE,BODYPRESS,TIMEBOMB,DEFOG,WAIL,COUPDEGRACE,ANCIENTPOWER,GLISTEN,TOXICSPIKES,EggMoves = CURSE,HEATCRASH,SLUDGEBOMB,BALANCERCHANGEREQUIRED,SIZZLE,FIERYDANCE,EggGroups = Amorphous,HatchSteps = 5355,Height = 0.6,Weight = 1.0,Color = Red,Shape = Head,Category = Volcanic Gas,Pokedex = The result of unifying poisonous gas, steam and a superheated atmosphere. Highly volatile, these Koffing are capable of spewing fireballs.,Generation = 1,Evolutions = WEEZING,LevelDay,33
A4: Name = Koffing
A5: Types = FIRE
A6: BaseStats = 60,50,45,35,65,85
A7: GenderRatio = Female50Percent
A8: GrowthRate = Medium
A9: BaseExp = 68
A10: EVs = SPECIAL_DEFENSE,1
A11: CatchRate = 190
A12: Happiness = 70
A13: Abilities = LEVITATE,WHITESMOKE
A14: HiddenAbilities = FILTER
A15: Moves = 1,POISONGAS,1,DEFENSECURL,5,EMBER,9,SMOG,12,HAZE,16,INCINERATE,19,CLEARSMOG,22,GYROBALL,26,CORRODE,30,SUNNYDAY,34,LAVAPLUME,38,DESTINYBOND,42,CORROSIVEGAS,45,ACIDRAIN,49,MEMENTO,54,ERUPTION | E15: =A15&","&A16&","&A17&","&A18&","&A19&","&A20&","&A21&","&A22&","&A23&","&A24&","&A25&","&A26&","&A27 -> Moves = 1,POISONGAS,1,DEFENSECURL,5,EMBER,9,SMOG,12,HAZE,16,INCINERATE,19,CLEARSMOG,22,GYROBALL,26,CORRODE,30,SUNNYDAY,34,LAVAPLUME,38,DESTINYBOND,42,CORROSIVEGAS,45,ACIDRAIN,49,MEMENTO,54,ERUPTION,TutorMoves = TOXIC,HIDDENPOWER,SUNNYDAY,PROTECT,FRUSTRATION,RETURN,REFLECT,SLUDGEWAVE,FLAMETHROWER,SLUDGEBOMB,FIREBLAST,FACADE,REST,ATTRACT,OVERHEAT,SCALD,INCINERATE,WILLOWISP,EXPLOSION,SUBSTITUTE,HEATWAVE,SLEEPTALK,WEATHERBALL,FIRESPIN,CHARGEBEAM,SOLARBEAM,SOLARBLADE,MUDSHACKLES,STEALTHROCK,BEATUP,ALLERGY,ACIDRAIN,GASTROACID,ACIDARMOR,HEX,CURSE,CONFUSERAY,OMINOUSWIND,METEORDRIVE,GAMMARAY,GRAVITY,ROUND,ECHOEDVOICE,SCHIZOPHRENIA,RAYOFLIGHT,SIGNALBEAM,BODYSLAM,BALANCERCHANGEREQUIRED,NASTYPLOT,GUNKSHOT,SHADOWBALL,GYROBALL,BEJEWELED,POWERGEM,BURNINGJEALOUSY,FIREPLEDGE,SHOCKWAVE,SCORCHINGSANDS,STEAMROLLER,ZENHEADBUTT,TWINBEAM,WORKUP,CORROSIVEGAS,VITALITYDRAIN,MEMENTO,GRUDGE,BODYPRESS,TIMEBOMB,DEFOG,WAIL,COUPDEGRACE,ANCIENTPOWER,GLISTEN,TOXICSPIKES,EggMoves = CURSE,HEATCRASH,SLUDGEBOMB,BALANCERCHANGEREQUIRED,SIZZLE,FIERYDANCE,EggGroups = Amorphous,HatchSteps = 5355,Height = 0.6,Weight = 1.0,Color = Red,Shape = Head,Category = Volcanic Gas,Pokedex = The result of unifying poisonous gas, steam and a superheated atmosphere. Highly volatile, these Koffing are capable of spewing fireballs.,Generation = 1,Evolutions = WEEZING,LevelDay,33
A16: TutorMoves = TOXIC,HIDDENPOWER,SUNNYDAY,PROTECT,FRUSTRATION,RETURN,REFLECT,SLUDGEWAVE,FLAMETHROWER,SLUDGEBOMB,FIREBLAST,FACADE,REST,ATTRACT,OVERHEAT,SCALD,INCINERATE,WILLOWISP,EXPLOSION,SUBSTITUTE,HEATWAVE,SLEEPTALK,WEATHERBALL,FIRESPIN,CHARGEBEAM,SOLARBEAM,SOLARBLADE,MUDSHACKLES,STEALTHROCK,BEATUP,ALLERGY,ACIDRAIN,GASTROACID,ACIDARMOR,HEX,CURSE,CONFUSERAY,OMINOUSWIND,METEORDRIVE,GAMMARAY,GRAVITY,ROUND,ECHOEDVOICE,SCHIZOPHRENIA,RAYOFLIGHT,SIGNALBEAM,BODYSLAM,BALANCERCHANGEREQUIRED,NASTYPLOT,GUNKSHOT,SHADOWBALL,GYROBALL,BEJEWELED,POWERGEM,BURNINGJEALOUSY,FIREPLEDGE,SHOCKWAVE,SCORCHINGSANDS,STEAMROLLER,ZENHEADBUTT,TWINBEAM,WORKUP,CORROSIVEGAS,VITALITYDRAIN,MEMENTO,GRUDGE,BODYPRESS,TIMEBOMB,DEFOG,WAIL,COUPDEGRACE,ANCIENTPOWER,GLISTEN,TOXICSPIKES
A17: EggMoves = CURSE,HEATCRASH,SLUDGEBOMB,BALANCERCHANGEREQUIRED,SIZZLE,FIERYDANCE
A18: EggGroups = Amorphous
A19: HatchSteps = 5355
A20: Height = 0.6
A21: Weight = 1.0
A22: Color = Red
A23: Shape = Head
A24: Category = Volcanic Gas
A25: Pokedex = The result of unifying poisonous gas, steam and a superheated atmosphere. Highly volatile, these Koffing are capable of spewing fireballs.
A26: Generation = 1
A27: Evolutions = WEEZING,LevelDay,33
A28: #-------------------------------
A29: [WEEZING] | E29: =A29&","&A30&","&A31&","&A32&","&A33&","&A34&","&A35&","&A36&","&A37&","&A38&","&A39&","&A40&","&A41&","&A42&","&A43&","&A44&","&A45&","&A46&","&A47&","&A48&","&A49&","&A50&","&A51&","&A52&","&A53 -> [WEEZING],Name = Weezing,Types = FIRE,BaseStats = 85,70,70,60,95,110,GenderRatio = Female50Percent,GrowthRate = Medium,BaseExp = 172,EVs = SPECIAL_DEFENSE,2,CatchRate = 100,Happiness = 70,Abilities = LEVITATE,MAGMAARMOR,HiddenAbilities = FILTER,Moves = 0,WILLOWISP,1,WILLOWISP,1,RECOVER,1,POISONGAS,1,DEFENSECURL,5,EMBER,9,SMOG,12,HAZE,16,INCINERATE,19,CLEARSMOG,22,GYROBALL,26,CORRODE,30,SUNNYDAY,36,LAVAPLUME,40,DESTINYBOND,44,CORROSIVEGAS,49,ACIDRAIN,53,MEMENTO,57,ERUPTION,TutorMoves = TOXIC,HIDDENPOWER,SUNNYDAY,PROTECT,FRUSTRATION,RETURN,REFLECT,SLUDGEWAVE,FLAMETHROWER,SLUDGEBOMB,FIREBLAST,FACADE,REST,ATTRACT,OVERHEAT,SCALD,INCINERATE,WILLOWISP,EXPLOSION,SUBSTITUTE,HEATWAVE,SLEEPTALK,WEATHERBALL,FIRESPIN,CHARGEBEAM,SOLARBEAM,SOLARBLADE,MUDSHACKLES,STEALTHROCK,BEATUP,ALLERGY,ACIDRAIN,GASTROACID,ACIDARMOR,HEX,CURSE,CONFUSERAY,OMINOUSWIND,METEORDRIVE,GAMMARAY,GRAVITY,ROUND,ECHOEDVOICE,SCHIZOPHRENIA,RAYOFLIGHT,SIGNALBEAM,BODYSLAM,BALANCERCHANGEREQUIRED,NASTYPLOT,GUNKSHOT,SHADOWBALL,GYROBALL,BEJEWELED,POWERGEM,BURNINGJEALOUSY,FIREPLEDGE,SHOCKWAVE,SCORCHINGSANDS,STEAMROLLER,ZENHEADBUTT,TWINBEAM,WORKUP,CORROSIVEGAS,VITALITYDRAIN,MEMENTO,GRUDGE,BODYPRESS,TIMEBOMB,DEFOG,WAIL,COUPDEGRACE,ANCIENTPOWER,GLISTEN,HYPERBEAM,GIGAIMPACT,TOXICSPIKES,EggGroups = Amorphous,HatchSteps = 5355,Height = 1.2,Weight = 9.5,Color = Red,Shape = Head,Category = Volcanic Gas,Pokedex = The superheated atmosphere of a volcano makes their chemical composition far more unstable and likely to attract more gaseous tumours on its body.,Generation = 1,#-------------------------------,[SOLOSIS]
A30: Name = Weezing
A31: Types = FIRE
A32: BaseStats = 85,70,70,60,95,110
A33: GenderRatio = Female50Percent
A34: GrowthRate = Medium
A35: BaseExp = 172
A36: EVs = SPECIAL_DEFENSE,2
A37: CatchRate = 100
A38: Happiness = 70
A39: Abilities = LEVITATE,MAGMAARMOR
A40: HiddenAbilities = FILTER
A41: Moves = 0,WILLOWISP,1,WILLOWISP,1,RECOVER,1,POISONGAS,1,DEFENSECURL,5,EMBER,9,SMOG,12,HAZE,16,INCINERATE,19,CLEARSMOG,22,GYROBALL,26,CORRODE,30,SUNNYDAY,36,LAVAPLUME,40,DESTINYBOND,44,CORROSIVEGAS,49,ACIDRAIN,53,MEMENTO,57,ERUPTION | E41: =A41&","&A42&","&A43&","&A44&","&A45&","&A46&","&A47&","&A48&","&A49&","&A50&","&A51&","&A52&","&A53 -> Moves = 0,WILLOWISP,1,WILLOWISP,1,RECOVER,1,POISONGAS,1,DEFENSECURL,5,EMBER,9,SMOG,12,HAZE,16,INCINERATE,19,CLEARSMOG,22,GYROBALL,26,CORRODE,30,SUNNYDAY,36,LAVAPLUME,40,DESTINYBOND,44,CORROSIVEGAS,49,ACIDRAIN,53,MEMENTO,57,ERUPTION,TutorMoves = TOXIC,HIDDENPOWER,SUNNYDAY,PROTECT,FRUSTRATION,RETURN,REFLECT,SLUDGEWAVE,FLAMETHROWER,SLUDGEBOMB,FIREBLAST,FACADE,REST,ATTRACT,OVERHEAT,SCALD,INCINERATE,WILLOWISP,EXPLOSION,SUBSTITUTE,HEATWAVE,SLEEPTALK,WEATHERBALL,FIRESPIN,CHARGEBEAM,SOLARBEAM,SOLARBLADE,MUDSHACKLES,STEALTHROCK,BEATUP,ALLERGY,ACIDRAIN,GASTROACID,ACIDARMOR,HEX,CURSE,CONFUSERAY,OMINOUSWIND,METEORDRIVE,GAMMARAY,GRAVITY,ROUND,ECHOEDVOICE,SCHIZOPHRENIA,RAYOFLIGHT,SIGNALBEAM,BODYSLAM,BALANCERCHANGEREQUIRED,NASTYPLOT,GUNKSHOT,SHADOWBALL,GYROBALL,BEJEWELED,POWERGEM,BURNINGJEALOUSY,FIREPLEDGE,SHOCKWAVE,SCORCHINGSANDS,STEAMROLLER,ZENHEADBUTT,TWINBEAM,WORKUP,CORROSIVEGAS,VITALITYDRAIN,MEMENTO,GRUDGE,BODYPRESS,TIMEBOMB,DEFOG,WAIL,COUPDEGRACE,ANCIENTPOWER,GLISTEN,HYPERBEAM,GIGAIMPACT,TOXICSPIKES,EggGroups = Amorphous,HatchSteps = 5355,Height = 1.2,Weight = 9.5,Color = Red,Shape = Head,Category = Volcanic Gas,Pokedex = The superheated atmosphere of a volcano makes their chemical composition far more unstable and likely to attract more gaseous tumours on its body.,Generation = 1,#-------------------------------,[SOLOSIS]
A42: TutorMoves = TOXIC,HIDDENPOWER,SUNNYDAY,PROTECT,FRUSTRATION,RETURN,REFLECT,SLUDGEWAVE,FLAMETHROWER,SLUDGEBOMB,FIREBLAST,FACADE,REST,ATTRACT,OVERHEAT,SCALD,INCINERATE,WILLOWISP,EXPLOSION,SUBSTITUTE,HEATWAVE,SLEEPTALK,WEATHERBALL,FIRESPIN,CHARGEBEAM,SOLARBEAM,SOLARBLADE,MUDSHACKLES,STEALTHROCK,BEATUP,ALLERGY,ACIDRAIN,GASTROACID,ACIDARMOR,HEX,CURSE,CONFUSERAY,OMINOUSWIND,METEORDRIVE,GAMMARAY,GRAVITY,ROUND,ECHOEDVOICE,SCHIZOPHRENIA,RAYOFLIGHT,SIGNALBEAM,BODYSLAM,BALANCERCHANGEREQUIRED,NASTYPLOT,GUNKSHOT,SHADOWBALL,GYROBALL,BEJEWELED,POWERGEM,BURNINGJEALOUSY,FIREPLEDGE,SHOCKWAVE,SCORCHINGSANDS,STEAMROLLER,ZENHEADBUTT,TWINBEAM,WORKUP,CORROSIVEGAS,VITALITYDRAIN,MEMENTO,GRUDGE,BODYPRESS,TIMEBOMB,DEFOG,WAIL,COUPDEGRACE,ANCIENTPOWER,GLISTEN,HYPERBEAM,GIGAIMPACT,TOXICSPIKES
A43: EggGroups = Amorphous
A44: HatchSteps = 5355
A45: Height = 1.2
A46: Weight = 9.5
A47: Color = Red
A48: Shape = Head
A49: Category = Volcanic Gas
A50: Pokedex = The superheated atmosphere of a volcano makes their chemical composition far more unstable and likely to attract more gaseous tumours on its body.
A51: Generation = 1
A52: #-------------------------------
A53: [SOLOSIS] | E53: =A53&","&A54&","&A55&","&A56&","&A57&","&A58&","&A59&","&A60&","&A61&","&A62&","&A63&","&A64&","&A65&","&A66&","&A67&","&A68&","&A69&","&A70&","&A71&","&A72&","&A73&","&A74&","&A75&","&A76&","&A77 -> [SOLOSIS],Name = Solosis,Types = WATER,PSYCHIC,BaseStats = 45,20,60,20,85,60,GenderRatio = Female50Percent,GrowthRate = Parabolic,BaseExp = 58,EVs = SPECIAL_ATTACK,1,CatchRate = 200,Happiness = 70,Abilities = TORRENT,MAGICBOUNCE,HiddenAbilities = TECHNICIAN,Moves = 1,BUBBLE,1,WATERSPORT,5,CONFUSION,10,HEALBLOCK,14,ICYWIND,18,WATERPULSE,22,SOAK,25,PSYSHOCK,29,REFLECT,29,LIGHTSCREEN,34,RECOVER,38,FREEZEDRY,41,SCALD,45,PSYCHIC,48,TRICKROOM,52,HYDROPUMP,56,CHECKMATE,TutorMoves = PSYSHOCK,CALMMIND,TOXIC,HAIL,HIDDENPOWER,ICEBEAM,LIGHTSCREEN,PROTECT,RAINDANCE,SAFEGUARD,FRUSTRATION,RETURN,PSYCHIC,SHADOWBALL,REFLECT,FACADE,REST,ATTRACT,SCALD,GYROBALL,SUBSTITUTE,TRICKROOM,LIQUIDATION,COSMICPOWER,ICYWIND,MAGICROOM,SLEEPTALK,WATERPULSE,WONDERROOM,ZENHEADBUTT,TIDALWAVE,SUBMERGE,WEATHERBALL,ICICLESPEAR,BOUNCE,GRASSKNOT,MINDDRAIN,ARCANEENERGY,FAKETEARS,TAUNT,CHARM,WHIRLPOOL,BRINE,HYDROPUMP,SOAK,ACIDARMOR,HEX,CURSE,CONFUSERAY,SWIFT,WISH,GRAVITY,STARDUSTREVERIE,SIGNALBEAM,BODYSLAM,TRIATTACK,LIQUIDNITROGEN,BLOODRITUAL,NASTYPLOT,MYSTICPULSE,FAESBLESSING,BLACKHOLE,HYPOTHERMIA,EXPANDINGFORCE,TERRAINPULSE,TWINBEAM,WORKUP,WATERPLEDGE,WAIL,EggMoves = ACIDARMOR,GUARDSWAP,POWERSWAP,SPEEDSWAP,TRICK,STOREDPOWER,BUBBLEBEAM,HYPNOSIS,KARMASPELL,EggGroups = Amorphous,HatchSteps = 5355,Height = 0.3,Weight = 1.0,Color = Blue,Shape = Head,Category = Sea Amoeba,Pokedex = They do not like light and are found in dark waters. They use their remote psychic ability to find food to sustain itself.,Generation = 5,Evolutions = DUOSION,Level,27
A54: Name = Solosis
A55: Types = WATER,PSYCHIC
A56: BaseStats = 45,20,60,20,85,60
A57: GenderRatio = Female50Percent
A58: GrowthRate = Parabolic
A59: BaseExp = 58
A60: EVs = SPECIAL_ATTACK,1
A61: CatchRate = 200
A62: Happiness = 70
A63: Abilities = TORRENT,MAGICBOUNCE
A64: HiddenAbilities = TECHNICIAN
A65: Moves = 1,BUBBLE,1,WATERSPORT,5,CONFUSION,10,HEALBLOCK,14,ICYWIND,18,WATERPULSE,22,SOAK,25,PSYSHOCK,29,REFLECT,29,LIGHTSCREEN,34,RECOVER,38,FREEZEDRY,41,SCALD,45,PSYCHIC,48,TRICKROOM,52,HYDROPUMP,56,CHECKMATE | E65: =A65&","&A66&","&A67&","&A68&","&A69&","&A70&","&A71&","&A72&","&A73&","&A74&","&A75&","&A76&","&A77 -> Moves = 1,BUBBLE,1,WATERSPORT,5,CONFUSION,10,HEALBLOCK,14,ICYWIND,18,WATERPULSE,22,SOAK,25,PSYSHOCK,29,REFLECT,29,LIGHTSCREEN,34,RECOVER,38,FREEZEDRY,41,SCALD,45,PSYCHIC,48,TRICKROOM,52,HYDROPUMP,56,CHECKMATE,TutorMoves = PSYSHOCK,CALMMIND,TOXIC,HAIL,HIDDENPOWER,ICEBEAM,LIGHTSCREEN,PROTECT,RAINDANCE,SAFEGUARD,FRUSTRATION,RETURN,PSYCHIC,SHADOWBALL,REFLECT,FACADE,REST,ATTRACT,SCALD,GYROBALL,SUBSTITUTE,TRICKROOM,LIQUIDATION,COSMICPOWER,ICYWIND,MAGICROOM,SLEEPTALK,WATERPULSE,WONDERROOM,ZENHEADBUTT,TIDALWAVE,SUBMERGE,WEATHERBALL,ICICLESPEAR,BOUNCE,GRASSKNOT,MINDDRAIN,ARCANEENERGY,FAKETEARS,TAUNT,CHARM,WHIRLPOOL,BRINE,HYDROPUMP,SOAK,ACIDARMOR,HEX,CURSE,CONFUSERAY,SWIFT,WISH,GRAVITY,STARDUSTREVERIE,SIGNALBEAM,BODYSLAM,TRIATTACK,LIQUIDNITROGEN,BLOODRITUAL,NASTYPLOT,MYSTICPULSE,FAESBLESSING,BLACKHOLE,HYPOTHERMIA,EXPANDINGFORCE,TERRAINPULSE,TWINBEAM,WORKUP,WATERPLEDGE,WAIL,EggMoves = ACIDARMOR,GUARDSWAP,POWERSWAP,SPEEDSWAP,TRICK,STOREDPOWER,BUBBLEBEAM,HYPNOSIS,KARMASPELL,EggGroups = Amorphous,HatchSteps = 5355,Height = 0.3,Weight = 1.0,Color = Blue,Shape = Head,Category = Sea Amoeba,Pokedex = They do not like light and are found in dark waters. They use their remote psychic ability to find food to sustain itself.,Generation = 5,Evolutions = DUOSION,Level,27
A66: TutorMoves = PSYSHOCK,CALMMIND,TOXIC,HAIL,HIDDENPOWER,ICEBEAM,LIGHTSCREEN,PROTECT,RAINDANCE,SAFEGUARD,FRUSTRATION,RETURN,PSYCHIC,SHADOWBALL,REFLECT,FACADE,REST,ATTRACT,SCALD,GYROBALL,SUBSTITUTE,TRICKROOM,LIQUIDATION,COSMICPOWER,ICYWIND,MAGICROOM,SLEEPTALK,WATERPULSE,WONDERROOM,ZENHEADBUTT,TIDALWAVE,SUBMERGE,WEATHERBALL,ICICLESPEAR,BOUNCE,GRASSKNOT,MINDDRAIN,ARCANEENERGY,FAKETEARS,TAUNT,CHARM,WHIRLPOOL,BRINE,HYDROPUMP,SOAK,ACIDARMOR,HEX,CURSE,CONFUSERAY,SWIFT,WISH,GRAVITY,STARDUSTREVERIE,SIGNALBEAM,BODYSLAM,TRIATTACK,LIQUIDNITROGEN,BLOODRITUAL,NASTYPLOT,MYSTICPULSE,FAESBLESSING,BLACKHOLE,HYPOTHERMIA,EXPANDINGFORCE,TERRAINPULSE,TWINBEAM,WORKUP,WATERPLEDGE,WAIL
A67: EggMoves = ACIDARMOR,GUARDSWAP,POWERSWAP,SPEEDSWAP,TRICK,STOREDPOWER,BUBBLEBEAM,HYPNOSIS,KARMASPELL
A68: EggGroups = Amorphous
A69: HatchSteps = 5355
A70: Height = 0.3
A71: Weight = 1.0
A72: Color = Blue
A73: Shape = Head
A74: Category = Sea Amoeba
A75: Pokedex = They do not like light and are found in dark waters. They use their remote psychic ability to find food to sustain itself.
A76: Generation = 5
A77: Evolutions = DUOSION,Level,27
A78: #-------------------------------
A79: [DUOSION] | E79: =A79&","&A80&","&A81&","&A82&","&A83&","&A84&","&A85&","&A86&","&A87&","&A88&","&A89&","&A90&","&A91&","&A92&","&A93&","&A94&","&A95&","&A96&","&A97&","&A98&","&A99&","&A100&","&A101&","&A102&","&A103 -> [DUOSION],Name = Duosion,Types = WATER,PSYCHIC,BaseStats = 60,35,70,35,100,70,GenderRatio = Female50Percent,GrowthRate = Parabolic,BaseExp = 130,EVs = SPECIAL_ATTACK,2,CatchRate = 100,Happiness = 70,Abilities = TORRENT,MAGICBOUNCE,HiddenAbilities = TECHNICIAN,Moves = 1,BUBBLE,1,WATERSPORT,5,CONFUSION,10,HEALBLOCK,14,ICYWIND,18,WATERPULSE,22,SOAK,25,PSYSHOCK,29,REFLECT,29,LIGHTSCREEN,34,RECOVER,38,FREEZEDRY,41,SCALD,45,PSYCHIC,48,TRICKROOM,52,HYDROPUMP,56,CHECKMATE,TutorMoves = PSYSHOCK,CALMMIND,TOXIC,HAIL,HIDDENPOWER,ICEBEAM,LIGHTSCREEN,PROTECT,RAINDANCE,SAFEGUARD,FRUSTRATION,RETURN,PSYCHIC,SHADOWBALL,REFLECT,FACADE,REST,ATTRACT,SCALD,GYROBALL,SUBSTITUTE,TRICKROOM,LIQUIDATION,COSMICPOWER,ICYWIND,MAGICROOM,SLEEPTALK,WATERPULSE,WONDERROOM,ZENHEADBUTT,TIDALWAVE,SUBMERGE,WEATHERBALL,ICICLESPEAR,BOUNCE,GRASSKNOT,MINDDRAIN,ARCANEENERGY,FAKETEARS,TAUNT,CHARM,WHIRLPOOL,BRINE,HYDROPUMP,SOAK,ACIDARMOR,HEX,CURSE,CONFUSERAY,SWIFT,WISH,GRAVITY,STARDUSTREVERIE,SIGNALBEAM,BODYSLAM,TRIATTACK,LIQUIDNITROGEN,BLOODRITUAL,NASTYPLOT,MYSTICPULSE,FAESBLESSING,BLACKHOLE,HYPOTHERMIA,EXPANDINGFORCE,TERRAINPULSE,TWINBEAM,WORKUP,WATERPLEDGE,WAIL,AURASPHERE,EggGroups = Amorphous,HatchSteps = 5355,Height = 0.6,Weight = 8.0,Color = Blue,Shape = Head,Category = Mitochondria,Pokedex = It exhibited significant psychic potential when it was just a single-celled organism. Imagine the power it now possesses now that it has evolved.,Generation = 5,Evolutions = REUNICLUS,Level,44,#-------------------------------
A80: Name = Duosion
A81: Types = WATER,PSYCHIC
A82: BaseStats = 60,35,70,35,100,70
A83: GenderRatio = Female50Percent
A84: GrowthRate = Parabolic
A85: BaseExp = 130
A86: EVs = SPECIAL_ATTACK,2
A87: CatchRate = 100
A88: Happiness = 70
A89: Abilities = TORRENT,MAGICBOUNCE
A90: HiddenAbilities = TECHNICIAN
A91: Moves = 1,BUBBLE,1,WATERSPORT,5,CONFUSION,10,HEALBLOCK,14,ICYWIND,18,WATERPULSE,22,SOAK,25,PSYSHOCK,29,REFLECT,29,LIGHTSCREEN,34,RECOVER,38,FREEZEDRY,41,SCALD,45,PSYCHIC,48,TRICKROOM,52,HYDROPUMP,56,CHECKMATE
... A103: #-------------------------------
A104: [REUNICLUS] | E104: =A104&","&A105&","&A106&","&A107&","&A108&","&A109&","&A110&","&A111&","&A112&","&A113&","&A114&","&A115&","&A116&","&A117&","&A118&","&A119&","&A120&","&A121&","&A122&","&A123&","&A124&","&A125&","&A126&","&A127&","&A128 -> [REUNICLUS],Name = Reuniclus,Types = WATER,PSYCHIC,BaseStats = 70,45,95,55,130,95,GenderRatio = Female50Percent,GrowthRate = Parabolic,BaseExp = 221,EVs = SPECIAL_ATTACK,3,CatchRate = 100,Happiness = 70,Abilities = TORRENT,MAGICBOUNCE,HiddenAbilities = TECHNICIAN,Moves = 0,CALMMIND,1,CALMMIND,1,BUBBLE,1,WATERSPORT,5,CONFUSION,10,HEALBLOCK,14,ICYWIND,18,WATERPULSE,22,SOAK,25,PSYSHOCK,29,REFLECT,29,LIGHTSCREEN,34,RECOVER,38,FREEZEDRY,41,SCALD,45,PSYCHIC,48,TRICKROOM,52,HYDROPUMP,56,CHECKMATE,TutorMoves = PSYSHOCK,CALMMIND,TOXIC,HAIL,HIDDENPOWER,ICEBEAM,LIGHTSCREEN,PROTECT,RAINDANCE,SAFEGUARD,FRUSTRATION,RETURN,PSYCHIC,SHADOWBALL,REFLECT,FACADE,REST,ATTRACT,SCALD,GYROBALL,SUBSTITUTE,TRICKROOM,LIQUIDATION,COSMICPOWER,ICYWIND,MAGICROOM,SLEEPTALK,WATERPULSE,WONDERROOM,ZENHEADBUTT,TIDALWAVE,SUBMERGE,WEATHERBALL,ICICLESPEAR,BOUNCE,GRASSKNOT,MINDDRAIN,ARCANEENERGY,FAKETEARS,TAUNT,CHARM,WHIRLPOOL,BRINE,HYDROPUMP,SOAK,ACIDARMOR,HEX,CURSE,CONFUSERAY,SWIFT,WISH,GRAVITY,STARDUSTREVERIE,SIGNALBEAM,BODYSLAM,TRIATTACK,LIQUIDNITROGEN,BLOODRITUAL,NASTYPLOT,MYSTICPULSE,FAESBLESSING,BLACKHOLE,HYPOTHERMIA,EXPANDINGFORCE,TERRAINPULSE,TWINBEAM,WORKUP,WATERPLEDGE,WAIL,FOCUSBLAST,GIGAIMPACT,BLIZZARD,HYPERBEAM,AURASPHERE,EggGroups = Amorphous,HatchSteps = 5355,Height = 1.0,Weight = 20.1,Color = Blue,Shape = HeadArms,Category = Water Bender,Pokedex = These Pokemon are capable of bending water to its will and forming fantastic water sculptures with its mind.,Generation = 5,#-------------------------------,[GASTLY]
A105: Name = Reuniclus
A106: Types = WATER,PSYCHIC
A107: BaseStats = 70,45,95,55,130,95
A108: GenderRatio = Female50Percent
A109: GrowthRate = Parabolic
A110: BaseExp = 221
A111: EVs = SPECIAL_ATTACK,3
...

Sheet Worksheet
A1: ID | B1: Internal Name | C1: Name | D1: Type | E1: BST | F1: HP | G1: Attack | H1: Defense | I1: Speed | J1: SpAtk | K1: SpDef | L1: Gender Ratio | M1: Growth Rate | N1: Base Exp | O1: EVs
B2: [KOFFING],Name = Koffing,Types = FIRE,BaseStats = 60,50,45,35,65,85,GenderRatio = Female50Percent,GrowthRate = Medium,BaseExp = 68,EVs = SPECIAL_DEFENSE,1,CatchRate = 190,Happiness = 70,Abilities = LEVITATE,WHITESMOKE,HiddenAbilities = FILTER,Moves = 1,POISONGAS,1,DEFENSECURL,5,EMBER,9,SMOG,12,HAZE,16,INCINERATE,19,CLEARSMOG,22,GYROBALL,26,CORRODE,30,SUNNYDAY,34,LAVAPLUME,38,DESTINYBOND,42,CORROSIVEGAS,45,ACIDRAIN,49,MEMENTO,54,ERUPTION,TutorMoves = TOXIC,HIDDENPOWER,SUNNYDAY,PROTECT,FRUSTRATION,RETURN,REFLECT,SLUDGEWAVE,FLAMETHROWER,SLUDGEBOMB,FIREBLAST,FACADE,REST,ATTRACT,OVERHEAT,SCALD,INCINERATE,WILLOWISP,EXPLOSION,SUBSTITUTE,HEATWAVE,SLEEPTALK,WEATHERBALL,FIRESPIN,CHARGEBEAM,SOLARBEAM,SOLARBLADE,MUDSHACKLES,STEALTHROCK,BEATUP,ALLERGY,ACIDRAIN,GASTROACID,ACIDARMOR,HEX,CURSE,CONFUSERAY,OMINOUSWIND,METEORDRIVE,GAMMARAY,GRAVITY,ROUND,ECHOEDVOICE,SCHIZOPHRENIA,RAYOFLIGHT,SIGNALBEAM,BODYSLAM,BALANCERCHANGEREQUIRED,NASTYPLOT,GUNKSHOT,SHADOWBALL,GYROBALL,BEJEWELED,POWERGEM,BURNINGJEALOUSY,FIREPLEDGE,SHOCKWAVE,SCORCHINGSANDS,STEAMROLLER,ZENHEADBUTT,TWINBEAM,WORKUP,CORROSIVEGAS,VITALITYDRAIN,MEMENTO,GRUDGE,BODYPRESS,TIMEBOMB,DEFOG,WAIL,COUPDEGRACE,ANCIENTPOWER,GLISTEN,TOXICSPIKES,EggMoves = CURSE,HEATCRASH,SLUDGEBOMB,BALANCERCHANGEREQUIRED,SIZZLE,FIERYDANCE,EggGroups = Amorphous,HatchSteps = 5355,Height = 0.6,Weight = 1.0,Color = Red,Shape = Head,Category = Volcanic Gas,Pokedex = The result of unifying poisonous gas, steam and a superheated atmosphere. Highly volatile, these Koffing are capable of spewing fireballs.,Generation = 1,Evolutions = WEEZING,LevelDay,33
B3: [WEEZING],Name = Weezing,Types = FIRE,BaseStats = 85,70,70,60,95,110,GenderRatio = Female50Percent,GrowthRate = Medium,BaseExp = 172,EVs = SPECIAL_DEFENSE,2,CatchRate = 100,Happiness = 70,Abilities = LEVITATE,MAGMAARMOR,HiddenAbilities = FILTER,Moves = 0,WILLOWISP,1,WILLOWISP,1,RECOVER,1,POISONGAS,1,DEFENSECURL,5,EMBER,9,SMOG,12,HAZE,16,INCINERATE,19,CLEARSMOG,22,GYROBALL,26,CORRODE,30,SUNNYDAY,36,LAVAPLUME,40,DESTINYBOND,44,CORROSIVEGAS,49,ACIDRAIN,53,MEMENTO,57,ERUPTION,TutorMoves = TOXIC,HIDDENPOWER,SUNNYDAY,PROTECT,FRUSTRATION,RETURN,REFLECT,SLUDGEWAVE,FLAMETHROWER,SLUDGEBOMB,FIREBLAST,FACADE,REST,ATTRACT,OVERHEAT,SCALD,INCINERATE,WILLOWISP,EXPLOSION,SUBSTITUTE,HEATWAVE,SLEEPTALK,WEATHERBALL,FIRESPIN,CHARGEBEAM,SOLARBEAM,SOLARBLADE,MUDSHACKLES,STEALTHROCK,BEATUP,ALLERGY,ACIDRAIN,GASTROACID,ACIDARMOR,HEX,CURSE,CONFUSERAY,OMINOUSWIND,METEORDRIVE,GAMMARAY,GRAVITY,ROUND,ECHOEDVOICE,SCHIZOPHRENIA,RAYOFLIGHT,SIGNALBEAM,BODYSLAM,BALANCERCHANGEREQUIRED,NASTYPLOT,GUNKSHOT,SHADOWBALL,GYROBALL,BEJEWELED,POWERGEM,BURNINGJEALOUSY,FIREPLEDGE,SHOCKWAVE,SCORCHINGSANDS,STEAMROLLER,ZENHEADBUTT,TWINBEAM,WORKUP,CORROSIVEGAS,VITALITYDRAIN,MEMENTO,GRUDGE,BODYPRESS,TIMEBOMB,DEFOG,WAIL,COUPDEGRACE,ANCIENTPOWER,GLISTEN,HYPERBEAM,GIGAIMPACT,TOXICSPIKES,EggGroups = Amorphous,HatchSteps = 5355,Height = 1.2,Weight = 9.5,Color = Red,Shape = Head,Category = Volcanic Gas,Pokedex = The superheated atmosphere of a volcano makes their chemical composition far more unstable and likely to attract more gaseous tumours on its body.,Generation = 1,#-------------------------------,[SOLOSIS]
B4: [SOLOSIS],Name = Solosis,Types = WATER,PSYCHIC,BaseStats = 45,20,60,20,85,60,GenderRatio = Female50Percent,GrowthRate = Parabolic,BaseExp = 58,EVs = SPECIAL_ATTACK,1,CatchRate = 200,Happiness = 70,Abilities = TORRENT,MAGICBOUNCE,HiddenAbilities = TECHNICIAN,Moves = 1,BUBBLE,1,WATERSPORT,5,CONFUSION,10,HEALBLOCK,14,ICYWIND,18,WATERPULSE,22,SOAK,25,PSYSHOCK,29,REFLECT,29,LIGHTSCREEN,34,RECOVER,38,FREEZEDRY,41,SCALD,45,PSYCHIC,48,TRICKROOM,52,HYDROPUMP,56,CHECKMATE,TutorMoves = PSYSHOCK,CALMMIND,TOXIC,HAIL,HIDDENPOWER,ICEBEAM,LIGHTSCREEN,PROTECT,RAINDANCE,SAFEGUARD,FRUSTRATION,RETURN,PSYCHIC,SHADOWBALL,REFLECT,FACADE,REST,ATTRACT,SCALD,GYROBALL,SUBSTITUTE,TRICKROOM,LIQUIDATION,COSMICPOWER,ICYWIND,MAGICROOM,SLEEPTALK,WATERPULSE,WONDERROOM,ZENHEADBUTT,TIDALWAVE,SUBMERGE,WEATHERBALL,ICICLESPEAR,BOUNCE,GRASSKNOT,MINDDRAIN,ARCANEENERGY,FAKETEARS,TAUNT,CHARM,WHIRLPOOL,BRINE,HYDROPUMP,SOAK,ACIDARMOR,HEX,CURSE,CONFUSERAY,SWIFT,WISH,GRAVITY,STARDUSTREVERIE,SIGNALBEAM,BODYSLAM,TRIATTACK,LIQUIDNITROGEN,BLOODRITUAL,NASTYPLOT,MYSTICPULSE,FAESBLESSING,BLACKHOLE,HYPOTHERMIA,EXPANDINGFORCE,TERRAINPULSE,TWINBEAM,WORKUP,WATERPLEDGE,WAIL,EggMoves = ACIDARMOR,GUARDSWAP,POWERSWAP,SPEEDSWAP,TRICK,STOREDPOWER,BUBBLEBEAM,HYPNOSIS,KARMASPELL,EggGroups = Amorphous,HatchSteps = 5355,Height = 0.3,Weight = 1.0,Color = Blue,Shape = Head,Category = Sea Amoeba,Pokedex = They do not like light and are found in dark waters. They use their remote psychic ability to find food to sustain itself.,Generation = 5,Evolutions = DUOSION,Level,27
B5: [DUOSION],Name = Duosion,Types = WATER,PSYCHIC,BaseStats = 60,35,70,35,100,70,GenderRatio = Female50Percent,GrowthRate = Parabolic,BaseExp = 130,EVs = SPECIAL_ATTACK,2,CatchRate = 100,Happiness = 70,Abilities = TORRENT,MAGICBOUNCE,HiddenAbilities = TECHNICIAN,Moves = 1,BUBBLE,1,WATERSPORT,5,CONFUSION,10,HEALBLOCK,14,ICYWIND,18,WATERPULSE,22,SOAK,25,PSYSHOCK,29,REFLECT,29,LIGHTSCREEN,34,RECOVER,38,FREEZEDRY,41,SCALD,45,PSYCHIC,48,TRICKROOM,52,HYDROPUMP,56,CHECKMATE,TutorMoves = PSYSHOCK,CALMMIND,TOXIC,HAIL,HIDDENPOWER,ICEBEAM,LIGHTSCREEN,PROTECT,RAINDANCE,SAFEGUARD,FRUSTRATION,RETURN,PSYCHIC,SHADOWBALL,REFLECT,FACADE,REST,ATTRACT,SCALD,GYROBALL,SUBSTITUTE,TRICKROOM,LIQUIDATION,COSMICPOWER,ICYWIND,MAGICROOM,SLEEPTALK,WATERPULSE,WONDERROOM,ZENHEADBUTT,TIDALWAVE,SUBMERGE,WEATHERBALL,ICICLESPEAR,BOUNCE,GRASSKNOT,MINDDRAIN,ARCANEENERGY,FAKETEARS,TAUNT,CHARM,WHIRLPOOL,BRINE,HYDROPUMP,SOAK,ACIDARMOR,HEX,CURSE,CONFUSERAY,SWIFT,WISH,GRAVITY,STARDUSTREVERIE,SIGNALBEAM,BODYSLAM,TRIATTACK,LIQUIDNITROGEN,BLOODRITUAL,NASTYPLOT,MYSTICPULSE,FAESBLESSING,BLACKHOLE,HYPOTHERMIA,EXPANDINGFORCE,TERRAINPULSE,TWINBEAM,WORKUP,WATERPLEDGE,WAIL,AURASPHERE,EggGroups = Amorphous,HatchSteps = 5355,Height = 0.6,Weight = 8.0,Color = Blue,Shape = Head,Category = Mitochondria,Pokedex = It exhibited significant psychic potential when it was just a single-celled organism. Imagine the power it now possesses now that it has evolved.,Generation = 5,Evolutions = REUNICLUS,Level,44,#-------------------------------
B6: [REUNICLUS],Name = Reuniclus,Types = WATER,PSYCHIC,BaseStats = 70,45,95,55,130,95,GenderRatio = Female50Percent,GrowthRate = Parabolic,BaseExp = 221,EVs = SPECIAL_ATTACK,3,CatchRate = 100,Happiness = 70,Abilities = TORRENT,MAGICBOUNCE,HiddenAbilities = TECHNICIAN,Moves = 0,CALMMIND,1,CALMMIND,1,BUBBLE,1,WATERSPORT,5,CONFUSION,10,HEALBLOCK,14,ICYWIND,18,WATERPULSE,22,SOAK,25,PSYSHOCK,29,REFLECT,29,LIGHTSCREEN,34,RECOVER,38,FREEZEDRY,41,SCALD,45,PSYCHIC,48,TRICKROOM,52,HYDROPUMP,56,CHECKMATE,TutorMoves = PSYSHOCK,CALMMIND,TOXIC,HAIL,HIDDENPOWER,ICEBEAM,LIGHTSCREEN,PROTECT,RAINDANCE,SAFEGUARD,FRUSTRATION,RETURN,PSYCHIC,SHADOWBALL,REFLECT,FACADE,REST,ATTRACT,SCALD,GYROBALL,SUBSTITUTE,TRICKROOM,LIQUIDATION,COSMICPOWER,ICYWIND,MAGICROOM,SLEEPTALK,WATERPULSE,WONDERROOM,ZENHEADBUTT,TIDALWAVE,SUBMERGE,WEATHERBALL,ICICLESPEAR,BOUNCE,GRASSKNOT,MINDDRAIN,ARCANEENERGY,FAKETEARS,TAUNT,CHARM,WHIRLPOOL,BRINE,HYDROPUMP,SOAK,ACIDARMOR,HEX,CURSE,CONFUSERAY,SWIFT,WISH,GRAVITY,STARDUSTREVERIE,SIGNALBEAM,BODYSLAM,TRIATTACK,LIQUIDNITROGEN,BLOODRITUAL,NASTYPLOT,MYSTICPULSE,FAESBLESSING,BLACKHOLE,HYPOTHERMIA,EXPANDINGFORCE,TERRAINPULSE,TWINBEAM,WORKUP,WATERPLEDGE,WAIL,FOCUSBLAST,GIGAIMPACT,BLIZZARD,HYPERBEAM,AURASPHERE,EggGroups = Amorphous,HatchSteps = 5355,Height = 1.0,Weight = 20.1,Color = Blue,Shape = HeadArms,Category = Water Bender,Pokedex = These Pokemon are capable of bending water to its will and forming fantastic water sculptures with its mind.,Generation = 5,#-------------------------------,[GASTLY]
B7: [GASTLY],Name = Gastly,Types = ICE,FLYING,BaseStats = 30,30,30,85,100,35,GenderRatio = Female50Percent,GrowthRate = Parabolic,BaseExp = 62,EVs = SPECIAL_ATTACK,1,CatchRate = 190,Happiness = 70,Abilities = FILTER,CLOUDNINE,HiddenAbilities = SNOWWARNING,Moves = 1,POWDERSNOW,5,GUST,9,HAIL,14,ICYWIND,20,TURBULENCE,26,FROSTBREATH,31,DEFOG,36,EROSION,41,AIRSLASH,45,ICEBEAM,49,STARDUSTREVERIE,53,TAILWIND,58,BOREASBREATH,62,BLIZZARD,TutorMoves = TOXIC,HAIL,HIDDENPOWER,ICEBEAM,BLIZZARD,LIGHTSCREEN,PROTECT,RAINDANCE,SAFEGUARD,FRUSTRATION,THUNDERBOLT,RETURN,REFLECT,FACADE,REST,ATTRACT,SUBSTITUTE,AURORAVEIL,HURRICANE,DEFOG,ICYWIND,OMINOUSWIND,SLEEPTALK,TAILWIND,ICICLECRASH,WEATHERBALL,ICYWIND,ICICLESPEAR,AVALANCHE,FROZENHEART,CHARGEBEAM,EERIEIMPULSE,FLY,AIRSLASH,TURBULENCE,DEATHVORTEX,TRICK,WONDERROOM,MAGICROOM,MINDDRAIN,TAUNT,SOAK,ACIDRAIN,HEX,CURSE,CONFUSERAY,MEANLOOK,COSMICPOWER,GRAVITY,STARDUSTREVERIE,SCHIZOPHRENIA,RAYOFLIGHT,TRIATTACK,LIQUIDNITROGEN,CALMMIND,BLOODRITUAL,NASTYPLOT,GYROBALL,BOREASBREATH,HURRICANE,TORNADO,ICECOMET,HYPOTHERMIA,SHOCKWAVE,WORKUP,WATERPULSE,WATERPLEDGE,EggMoves = AURORAVEIL,HURRICANE,RAINDANCE,TRIATTACK,FROZENHEART,LIQUIDNITROGEN,ICEVORTEX,CHECKMATE,TORNADO,FREEZEDRY,EggGroups = Amorphous,HatchSteps = 5355,Height = 1.3,Weight = 0.1,Color = Blue,Shape = Head,Category = Mist,Pokedex = Whenever hail falls, you can likely credit a Gastly as being responsible for starting it.,Generation = 1,Evolutions = HAUNTER,Level,25
B8: [HAUNTER],Name = Haunter,Types = ICE,FLYING,BaseStats = 50,45,45,95,115,55,GenderRatio = Female50Percent,GrowthRate = Parabolic,BaseExp = 142,EVs = SPECIAL_ATTACK,2,CatchRate = 100,Happiness = 70,Abilities = FILTER,CLOUDNINE,HiddenAbilities = SNOWWARNING,Moves = 0,WEATHERBALL,1,WEATHERBALL,1,POWDERSNOW,5,GUST,9,HAIL,14,ICYWIND,20,TURBULENCE,26,FROSTBREATH,31,DEFOG,36,EROSION,41,AIRSLASH,45,ICEBEAM,49,STARDUSTREVERIE,53,TAILWIND,58,BOREASBREATH,62,BLIZZARD,TutorMoves = TOXIC,HAIL,HIDDENPOWER,ICEBEAM,BLIZZARD,LIGHTSCREEN,PROTECT,RAINDANCE,SAFEGUARD,FRUSTRATION,THUNDERBOLT,RETURN,REFLECT,FACADE,REST,ATTRACT,SUBSTITUTE,AURORAVEIL,HURRICANE,DEFOG,ICYWIND,OMINOUSWIND,SLEEPTALK,TAILWIND,ICICLECRASH,WEATHERBALL,ICYWIND,ICICLESPEAR,AVALANCHE,FROZENHEART,CHARGEBEAM,EERIEIMPULSE,FLY,AIRSLASH,TURBULENCE,DEATHVORTEX,TRICK,WONDERROOM,MAGICROOM,MINDDRAIN,TAUNT,SOAK,ACIDRAIN,HEX,CURSE,CONFUSERAY,MEANLOOK,COSMICPOWER,GRAVITY,STARDUSTREVERIE,SCHIZOPHRENIA,RAYOFLIGHT,TRIATTACK,LIQUIDNITROGEN,CALMMIND,BLOODRITUAL,NASTYPLOT,GYROBALL,BOREASBREATH,HURRICANE,TORNADO,ICECOMET,HYPOTHERMIA,SHOCKWAVE,WORKUP,WATERPULSE,WATERPLEDGE,THUNDER,ICEPUNCH,MEMENTO,EggGroups = Amorphous,HatchSteps = 5355,Height = 1.6,Weight = 0.1,Color = Blue,Shape = HeadArms,Category = Freezing Rain,Pokedex = Haunters are mischievous creatures. Their command of ice allows them to set up icy traps for unsuspecting passerbys.,Generation = 1,Evolutions = GENGAR,Item,WINDSTONE,#-------------------------------
B9: [GENGAR],Name = Gengar,Types = ICE,FLYING,BaseStats = 65,60,60,115,130,70,GenderRatio = Female50Percent,GrowthRate = Parabolic,BaseExp = 225,EVs = SPECIAL_ATTACK,3,CatchRate = 100,Happiness = 70,Abilities = FILTER,CLOUDNINE,HiddenAbilities = SNOWWARNING,Moves = 0,MEMENTO,1,MEMENTO,1,WEATHERBALL,1,POWDERSNOW,5,GUST,9,HAIL,14,ICYWIND,20,TURBULENCE,26,FROSTBREATH,31,DEFOG,36,EROSION,41,AIRSLASH,45,ICEBEAM,49,STARDUSTREVERIE,53,TAILWIND,58,BOREASBREATH,62,BLIZZARD,TutorMoves = TOXIC,HAIL,HIDDENPOWER,ICEBEAM,BLIZZARD,LIGHTSCREEN,PROTECT,RAINDANCE,SAFEGUARD,FRUSTRATION,THUNDERBOLT,RETURN,REFLECT,FACADE,REST,ATTRACT,SUBSTITUTE,AURORAVEIL,HURRICANE,DEFOG,ICYWIND,OMINOUSWIND,SLEEPTALK,TAILWIND,ICICLECRASH,WEATHERBALL,ICYWIND,ICICLESPEAR,AVALANCHE,FROZENHEART,CHARGEBEAM,EERIEIMPULSE,FLY,AIRSLASH,TURBULENCE,DEATHVORTEX,TRICK,WONDERROOM,MAGICROOM,MINDDRAIN,TAUNT,SOAK,ACIDRAIN,HEX,CURSE,CONFUSERAY,MEANLOOK,COSMICPOWER,GRAVITY,STARDUSTREVERIE,SCHIZOPHRENIA,RAYOFLIGHT,TRIATTACK,LIQUIDNITROGEN,CALMMIND,BLOODRITUAL,NASTYPLOT,GYROBALL,BOREASBREATH,HURRICANE,TORNADO,ICECOMET,HYPOTHERMIA,SHOCKWAVE,WORKUP,WATERPULSE,WATERPLEDGE,THUNDER,ICEPUNCH,MEMENTO,EggGroups = Amorphous,HatchSteps = 5355,Height = 1.5,Weight = 40.5,Color = Blue,Shape = BipedalTail,Category = Nimbus,Pokedex = Due to its mastery of cloud systems, Gengars are capable of summoning powerful hailstorms and blizzards at will.,#-------------------------------,[DODUO],Name = Doduo
B10: [DODUO],Name = Doduo,Types = COSMIC,FLYING,BaseStats = 45,35,35,75,75,45,GenderRatio = Female50Percent,GrowthRate = Medium,BaseExp = 62,EVs = SPEED,1,CatchRate = 190,Happiness = 70,Abilities = EARLYBIRD,COMPETITIVE,HiddenAbilities = NAIVETY,Moves = 1,GUST,1,STARDUST,5,SWIFT,10,CONFUSION,14,BLACKOUT,19,TWINSTARS,23,TURBULENCE,28,HYPNOSIS,32,COSMICPOWER,37,AIRSLASH,40,PSYCHIC,44,MOONLIGHT,48,MOONBLAST,52,BOREASBREATH,56,METEORBEAM,TutorMoves = PSYSHOCK,CALMMIND,TOXIC,HIDDENPOWER,LIGHTSCREEN,PROTECT,RAINDANCE,SAFEGUARD,FRUSTRATION,RETURN,PSYCHIC,SHADOWBALL,REFLECT,FACADE,REST,ATTRACT,THIEF,ROUND,ECHOEDVOICE,STEELWING,UTURN,SUBSTITUTE,TRICKROOM,WORKUP,COSMICPOWER,BRAVEBIRD,HELPINGHAND,HYPERVOICE,KNOCKOFF,ROOST,WONDERROOM,MOONBLAST,SUNNYDAY,ICYWIND,HAIL,EERIEIMPULSE,CHARGEBEAM,FLY,BOUNCE,AIRSLASH,FEATHERDANCE,TURBULENCE,DEATHVORTEX,UTURN,FLUTTER,TRICKROOM,MAGICROOM,WONDERROOM,PSYCHICTERRAIN,TAUNT,SIRENSSONG,RAINDANCE,LOWSWEEP,LOWKICK,CURSE,CONFUSERAY,SWIFT,WISH,METEORDRIVE,GAMMARAY,GRAVITY,STARDUSTREVERIE,LULLABY,SIGNALBEAM,TRIPLEKICK,PSYCHIC,BLOODRITUAL,DARKPULSE,SHADOWBALL,NASTYPLOT,SWORDSDANCE,BOREASBREATH,HURRICANE,TORNADO,AURASPHERE,BLACKHOLE,HYPOTHERMIA,SHOCKWAVE,EXPANDINGFORCE,TERRAINPULSE,FOULPLAY,EggMoves = FEATHERDANCE,REFLECT,LIGHTSCREEN,STOREDPOWER,BRAVEBIRD,TAILWIND,WISH,EggGroups = Flying,HatchSteps = 5355,Height = 1.4,Weight = 39.2,Color = Blue,Shape = HeadLegs,Category = Galaxy,Pokedex = It can channel the power of the night sky into its attacks. It forgoes physical violence in favour of attacking from afar with its nascent mind.,Generation = 1,Evolutions = DODRIO,Item,MOONSTONE
B11: [DODRIO],Name = Dodrio,Types = COSMIC,FLYING,BaseStats = 70,60,60,105,100,75,GenderRatio = Female50Percent,GrowthRate = Medium,BaseExp = 161,EVs = SPEED,2,CatchRate = 100,Happiness = 70,Abilities = EARLYBIRD,COMPETITIVE,HiddenAbilities = NAIVETY,Moves = 0,STARSALIGNED,1,STARSALIGNED,1,TRIATTACK,1,GUST,1,STARDUST,5,SWIFT,10,CONFUSION,14,BLACKOUT,19,TWINSTARS,23,TURBULENCE,28,HYPNOSIS,32,COSMICPOWER,37,AIRSLASH,40,PSYCHIC,44,MOONLIGHT,48,MOONBLAST,52,BOREASBREATH,56,METEORBEAM,TutorMoves = PSYSHOCK,CALMMIND,TOXIC,HIDDENPOWER,LIGHTSCREEN,PROTECT,RAINDANCE,SAFEGUARD,FRUSTRATION,RETURN,PSYCHIC,SHADOWBALL,REFLECT,FACADE,REST,ATTRACT,THIEF,ROUND,ECHOEDVOICE,STEELWING,UTURN,SUBSTITUTE,TRICKROOM,WORKUP,COSMICPOWER,BRAVEBIRD,HELPINGHAND,HYPERVOICE,KNOCKOFF,ROOST,WONDERROOM,MOONBLAST,SUNNYDAY,ICYWIND,HAIL,EERIEIMPULSE,CHARGEBEAM,FLY,BOUNCE,AIRSLASH,FEATHERDANCE,TURBULENCE,DEATHVORTEX,UTURN,FLUTTER,TRICKROOM,MAGICROOM,WONDERROOM,PSYCHICTERRAIN,TAUNT,SIRENSSONG,RAINDANCE,LOWSWEEP,LOWKICK,CURSE,CONFUSERAY,SWIFT,WISH,METEORDRIVE,GAMMARAY,GRAVITY,STARDUSTREVERIE,LULLABY,SIGNALBEAM,TRIPLEKICK,PSYCHIC,BLOODRITUAL,DARKPULSE,SHADOWBALL,NASTYPLOT,SWORDSDANCE,BOREASBREATH,HURRICANE,TORNADO,AURASPHERE,BLACKHOLE,HYPOTHERMIA,SHOCKWAVE,EXPANDINGFORCE,TERRAINPULSE,FOULPLAY,EggGroups = Flying,HatchSteps = 5355,Height = 1.8,Weight = 85.2,Color = Blue,Shape = HeadLegs,Category = Galaxy,Pokedex = It is able to look into different universes to anticipate enemy attacks.,Generation = 1,#-------------------------------,[EKANS]
B12: [EKANS],Name = Ekans,Types = GROUND,POISON,BaseStats = 40,70,44,60,40,54,GenderRatio = Female50Percent,GrowthRate = Medium,BaseExp = 58,EVs = ATTACK,1,CatchRate = 255,Happiness = 70,Abilities = CORROSION,QUICKKILL,HiddenAbilities = BLOODTHIRST,Moves = 1,WRAP,1,LEER,5,POISONSTING,8,MEGAPHONE,12,SANDTOMB,16,BITE,20,POISONFANG,24,DIG,28,BATTLECRY,33,CRUNCH,37,TOXIC,41,COIL,44,POISONJAB,48,VENDETTA,52,CONTINENTALRIFT,56,GUNKSHOT,TutorMoves = TOXIC,ALLERGY,HIDDENPOWER,PROTECT,FRUSTRATION,RETURN,DIG,SLUDGEWAVE,SLUDGEBOMB,SANDSTORM,FACADE,REST,ATTRACT,THIEF,SCORESETTLER,BULLDOZE,POISONJAB,SUBSTITUTE,WORKUP,VENOMDRENCH,CRUNCH,FOULPLAY,GASTROACID,GUNKSHOT,SLEEPTALK,LEECHLIFE,SUNNYDAY,FIREFANG,ICEFANG,THUNDERFANG,PINMISSILE,UTURN,SANDTOMB,MUDSHACKLES,QUICKSAND,SPIKES,MUDSLIDE,GAIAPULSE,MINDDRAIN,ROCKSLIDE,ROCKTOMB,ROCKBLAST,STEALTHROCK,MINERALWAVE,ASSURANCE,SNARL,BRUTALSWING,TAUNT,VENDETTA,LOWSWEEP,CROSSPOISON,TOXICSPIKES,POISONFANG,ACIDARMOR,BREAKINGSWIPE,ANCIENTGLARE,CURSE,CONFUSERAY,MEANLOOK,EARTHPOWER,BLOODRITUAL,PSYCHICFANGS,OUTRAGE,DRAGONDANCE,THROATCHOP,SWORDSDANCE,BOOMBOX,CATAPULT,SCORCHINGSANDS,SPOIL,CORROSIVEGAS,SCALESHOT,DRAGONBREATH,ENDERSHOCK,LASHOUT,VITALITYDRAIN,GRUDGE,COUPDEGRACE,EXTREMESPEED,ANCIENTPOWER,EggMoves = SWORDSDANCE,DRAGONTAIL,NAGASKIN,KNOCKOFF,CLANGINGSCALES,QUICKSAND,BALANCERCHANGEREQUIRED,SCREECH,EggGroups = Field,Dragon,HatchSteps = 5355,Height = 2.0,Weight = 6.9,Color = Brown,Shape = Serpentine,Category = Rattlesnake,Pokedex = The rhythmic sound of an Ekans's tail is enough to put its foe to sleep when it can then move in to consume it whole.,Generation = 1,Evolutions = ARBOK,Level,30
B13: [ARBOK],Name = Arbok,Types = GROUND,POISON,BaseStats = 55,110,69,100,65,69,GenderRatio = Female50Percent,GrowthRate = Medium,BaseExp = 153,EVs = ATTACK,2,CatchRate = 100,Happiness = 70,Abilities = CORROSION,QUICKKILL,HiddenAbilities = BLOODTHIRST,Moves = 0,GLARE,1,GLARE,1,WRAP,1,LEER,5,POISONSTING,8,QUICKSAND,12,SANDTOMB,16,BITE,20,POISONFANG,24,DIG,31,BATTLECRY,35,CRUNCH,40,TOXIC,44,COIL,48,POISONJAB,52,VENDETTA,56,CONTINENTALRIFT,60,GUNKSHOT,TutorMoves = TOXIC,ALLERGY,HIDDENPOWER,PROTECT,FRUSTRATION,RETURN,DIG,SLUDGEWAVE,SLUDGEBOMB,SANDSTORM,FACADE,REST,ATTRACT,THIEF,SCORESETTLER,BULLDOZE,POISONJAB,SUBSTITUTE,WORKUP,VENOMDRENCH,CRUNCH,FOULPLAY,GASTROACID,GUNKSHOT,SLEEPTALK,LEECHLIFE,SUNNYDAY,FIREFANG,ICEFANG,THUNDERFANG,PINMISSILE,UTURN,SANDTOMB,MUDSHACKLES,QUICKSAND,SPIKES,MUDSLIDE,GAIAPULSE,MINDDRAIN,ROCKSLIDE,ROCKTOMB,ROCKBLAST,STEALTHROCK,MINERALWAVE,ASSURANCE,SNARL,BRUTALSWING,TAUNT,VENDETTA,LOWSWEEP,CROSSPOISON,TOXICSPIKES,POISONFANG,ACIDARMOR,BREAKINGSWIPE,ANCIENTGLARE,CURSE,CONFUSERAY,MEANLOOK,EARTHPOWER,BLOODRITUAL,PSYCHICFANGS,OUTRAGE,DRAGONDANCE,THROATCHOP,SWORDSDANCE,BOOMBOX,CATAPULT,SCORCHINGSANDS,SPOIL,CORROSIVEGAS,SCALESHOT,DRAGONBREATH,ENDERSHOCK,LASHOUT,VITALITYDRAIN,GRUDGE,COUPDEGRACE,EXTREMESPEED,ANCIENTPOWER,HYPERBEAM,GIGAIMPACT,EARTHQUAKE,EggGroups = Field,Dragon,HatchSteps = 5355,Height = 3.5,Weight = 65.0,Color = Brown,Shape = Serpentine,Category = Rattlesnake,Pokedex = The poison of an Arbok is so corrosive that it can melt steel beams. It is able to manipulate the face on its body into different shapes to fool its prey.,Generation = 1,#-------------------------------,[STARYU]
... B698: [CARNIVINE],Name = Carnivine,Types = GRASS,BUG,BaseStats = 74,100,72,46,90,72,GenderRatio = Female50Percent,GrowthRate = Slow,BaseExp = 159,EVs = ATTACK,2,CatchRate = 200,Happiness = 70,Abilities = LEVITATE,Moves = 1,BIND,1,GROWTH,7,BITE,11,VINEWHIP,17,SWEETSCENT,21,INGRAIN,27,FEINTATTACK,31,FORESTLEAP,37,STOCKPILE,37,SPITUP,37,SWALLOW,41,CRUNCH,47,WRINGOUT,50,POWERWHIP,TutorMoves = ATTRACT,BIND,BUGBITE,BULLETSEED,CONFIDE,CUT,DEFOG,DOUBLETEAM,ENDURE,ENERGYBALL,FACADE,FLING,FRUSTRATION,GASTROACID,GIGADRAIN,GIGAIMPACT,GRASSKNOT,HIDDENPOWER,HYPERBEAM,INFESTATION,KNOCKOFF,NATUREPOWER,SCORESETTLER,PROTECT,REST,RETURN,ROUND,PEPPERBURST,SLEEPTALK,SLUDGEBOMB,SNORE,SOLARBEAM,SUBSTITUTE,SUNNYDAY,SWAGGER,SWORDSDANCE,SYNTHESIS,THIEF,THROATCHOP,TOXIC,WORRYSEED,EggMoves = SLEEPPOWDER,STUNSPORE,RAZORLEAF,SLAM,SYNTHESIS,MAGICALLEAF,LEECHSEED,WORRYSEED,GIGADRAIN,RAGEPOWDER,GRASSWHISTLE,VILEFUMES,EggGroups = Grass,HatchSteps = 6400,Height = 1.4,Weight = 27.0,Color = Green,Shape = Multiped,Category = Fly Trap,Pokedex = It binds itself to trees in marshes. It attracts prey with its sweet-smelling drool and gulps them down.,Generation = 4,,

Sheet Worksheet Forms
A1: [SHELLOS,1] | E1: =A1&","&A2&","&A3&","&A4&","&A5&","&A6&","&A7&","&A8&","&A9 -> [SHELLOS,1],FormName = Shellnite,Types = DRAGON,WATER,BaseStats = 64,40,40,57,75,59,EVs = SPECIAL_ATTACK,1,Abilities = GOOEY,SWIFTSWIM,HiddenAbilities = DRIZZLE,Moves = 1,WATERGUN,1,TWISTER,5,MIMIC,9,THUNDERWAVE,13,AQUARING,16,DRAGONBREATH,20,SOAK,24,BRINE,28,GLARE,33,DRAGONGALE,36,MUDDYWATER,40,HURRICANE,44,RAINDANCE,49,DRACOMETEOR,EggMoves = AURORABEAM,OCTAZOOKA,WATERPULSE,AQUAJET,MIST,YAWN,AMNESIA
A2: FormName = Shellnite
A3: Types = DRAGON,WATER
A4: BaseStats = 64,40,40,57,75,59
A5: EVs = SPECIAL_ATTACK,1
A6: Abilities = GOOEY,SWIFTSWIM
A7: HiddenAbilities = DRIZZLE
A8: Moves = 1,WATERGUN,1,TWISTER,5,MIMIC,9,THUNDERWAVE,13,AQUARING,16,DRAGONBREATH,20,SOAK,24,BRINE,28,GLARE,33,DRAGONGALE,36,MUDDYWATER,40,HURRICANE,44,RAINDANCE,49,DRACOMETEOR
A9: EggMoves = AURORABEAM,OCTAZOOKA,WATERPULSE,AQUAJET,MIST,YAWN,AMNESIA
A10: #-------------------------------
A11: [GASTRODON,1] | E11: =A11&","&A12&","&A13&","&A14&","&A15&","&A16&","&A17&","&A18&","&A19 -> [GASTRODON,1],FormName = Gastronair,Types = DRAGON,WATER,BaseStats = 95,50,57,85,110,88,EVs = SPECIAL_ATTACK,2,Abilities = GOOEY,SWIFTSWIM,HiddenAbilities = DRIZZLE,Moves = 0,LIFEDEW,1,LIFEDEW,1,WATERGUN,1,TWISTER,5,MIMIC,9,THUNDERWAVE,13,AQUARING,16,DRAGONBREATH,20,SOAK,24,BRINE,28,GLARE,33,DRAGONGALE,36,MUDDYWATER,40,HURRICANE,44,RAINDANCE,49,DRACOMETEOR,#-------------------------------
A12: FormName = Gastronair
A13: Types = DRAGON,WATER
A14: BaseStats = 95,50,57,85,110,88
A15: EVs = SPECIAL_ATTACK,2
A16: Abilities = GOOEY,SWIFTSWIM
A17: HiddenAbilities = DRIZZLE
A18: Moves = 0,LIFEDEW,1,LIFEDEW,1,WATERGUN,1,TWISTER,5,MIMIC,9,THUNDERWAVE,13,AQUARING,16,DRAGONBREATH,20,SOAK,24,BRINE,28,GLARE,33,DRAGONGALE,36,MUDDYWATER,40,HURRICANE,44,RAINDANCE,49,DRACOMETEOR
A19: #-------------------------------
A20: [SHELLOS,2] | E20: =A20&","&A21&","&A22&","&A23&","&A24&","&A25&","&A26&","&A27&","&A28 -> [SHELLOS,2],FormName = Shew,Types = DRAGON,STEEL,BaseStats = 65,70,80,45,44,47,EVs = DEFENSE,1,Abilities = GOOEY,FORTIFICATION,HiddenAbilities = SHEERFORCE,Moves = 1,SNAPTRAP,1,DRAGONFURY,5,MIMIC,9,SHARPEN,13,DRAGONMAGIC,16,DRAGONGNAW,20,FALSESWIPE,24,VISEGRIP,28,GLARE,33,DRACOSHRED,36,SHIELDBASH,40,CRUNCH,44,KINGSSHIELD,49,DRACONICCRASH,TutorMoves = ANCIENTGLARE,ATTRACT,AURASPHERE,BEJEWELED,BODYPRESS,BREAKINGSWIPE,BULKUP,BULLDOZE,BULLETSEED,BURNINGJEALOUSY,CHIDORI,CLOSECOMBAT,COACHING,CONFUSERAY,COUPDEGRACE,CRUNCH,CURSE,DARKPULSE,DAZZLINGGLEAM,DEADLYREACH,DIVINEPUNISHMENT,DRACARYS,DRACOMETEOR,DRAGONBLOOD,DRAGONBREATH,DRAGONDANCE,DRAGONMAGIC,DRAININGKISS,DRAINPUNCH,DUALWINGBEAT,EARTHPOWER,EARTHQUAKE,ECHOEDVOICE,FABLEDRUSH,FALSESWIPE,FEATHERDANCE,FLIPTURN,FIREFANG,FLAMETHROWER,FLAREBLITZ,FOCUSBLAST,FORTISSIMO,FURYCUTTER,GASTROACID,GOLDENBULLET,GOLDRUSH,GYROBALL,HEATWAVE,HEX,HIDDENPOWER,HIVEMIND,HYPERVOICE,ICEFANG,INCINERATE,IRONDEFENSE,IRONHEAD,KNOCKOFF,LASHOUT,LEECHLIFE,MAGNETICCANNON,MEMENTO,METEORBEAM,METEORDRIVE,METEORMASH,MINERALWAVE,MUDSHACKLES,MUDSLIDE,NASTYPLOT,NOBLEROAR,OUTRAGE,PLAYROUGH,POISONFANG,POISONJAB,POWERUPPUNCH,PROTECT,REST,RETURN,ROCKBLAST,ROCKSLIDE,ROCKTOMB,SANDTOMB,SANDSTORM,SCALD,SCALESHOT,SCORCHINGSANDS,SHADOWBALL,SLEEPTALK,SLUDGEBOMB,SLUDGEWAVE,SNARL,SOAK,SOLARBEAM,SOLARECLIPSE,SPIKES,STARDUSTREVERIE,STEALTHROCK,STEELROLLER,STONEEDGE,SUBSTITUTE,SUPERPOWER,SWORDSDANCE,TAUNT,TERRAINPULSE,THUNDERFANG,THUNDERPUNCH,THUNDERWAVE,TOXIC,TOXICSPIKES,TRIATTACK,UTURN,VENDETTA,VITALITYDRAIN,WILDCHARGE,WORKUP,ZENHEADBUTT
A21: FormName = Shew
A22: Types = DRAGON,STEEL
A23: BaseStats = 65,70,80,45,44,47
A24: EVs = DEFENSE,1
A25: Abilities = GOOEY,FORTIFICATION
A26: HiddenAbilities = SHEERFORCE
A27: Moves = 1,SNAPTRAP,1,DRAGONFURY,5,MIMIC,9,SHARPEN,13,DRAGONMAGIC,16,DRAGONGNAW,20,FALSESWIPE,24,VISEGRIP,28,GLARE,33,DRACOSHRED,36,SHIELDBASH,40,CRUNCH,44,KINGSSHIELD,49,DRACONICCRASH
A28: TutorMoves = ANCIENTGLARE,ATTRACT,AURASPHERE,BEJEWELED,BODYPRESS,BREAKINGSWIPE,BULKUP,BULLDOZE,BULLETSEED,BURNINGJEALOUSY,CHIDORI,CLOSECOMBAT,COACHING,CONFUSERAY,COUPDEGRACE,CRUNCH,CURSE,DARKPULSE,DAZZLINGGLEAM,DEADLYREACH,DIVINEPUNISHMENT,DRACARYS,DRACOMETEOR,DRAGONBLOOD,DRAGONBREATH,DRAGONDANCE,DRAGONMAGIC,DRAININGKISS,DRAINPUNCH,DUALWINGBEAT,EARTHPOWER,EARTHQUAKE,ECHOEDVOICE,FABLEDRUSH,FALSESWIPE,FEATHERDANCE,FLIPTURN,FIREFANG,FLAMETHROWER,FLAREBLITZ,FOCUSBLAST,FORTISSIMO,FURYCUTTER,GASTROACID,GOLDENBULLET,GOLDRUSH,GYROBALL,HEATWAVE,HEX,HIDDENPOWER,HIVEMIND,HYPERVOICE,ICEFANG,INCINERATE,IRONDEFENSE,IRONHEAD,KNOCKOFF,LASHOUT,LEECHLIFE,MAGNETICCANNON,MEMENTO,METEORBEAM,METEORDRIVE,METEORMASH,MINERALWAVE,MUDSHACKLES,MUDSLIDE,NASTYPLOT,NOBLEROAR,OUTRAGE,PLAYROUGH,POISONFANG,POISONJAB,POWERUPPUNCH,PROTECT,REST,RETURN,ROCKBLAST,ROCKSLIDE,ROCKTOMB,SANDTOMB,SANDSTORM,SCALD,SCALESHOT,SCORCHINGSANDS,SHADOWBALL,SLEEPTALK,SLUDGEBOMB,SLUDGEWAVE,SNARL,SOAK,SOLARBEAM,SOLARECLIPSE,SPIKES,STARDUSTREVERIE,STEALTHROCK,STEELROLLER,STONEEDGE,SUBSTITUTE,SUPERPOWER,SWORDSDANCE,TAUNT,TERRAINPULSE,THUNDERFANG,THUNDERPUNCH,THUNDERWAVE,TOXIC,TOXICSPIKES,TRIATTACK,UTURN,VENDETTA,VITALITYDRAIN,WILDCHARGE,WORKUP,ZENHEADBUTT
A29: #-------------------------------
A30: [GASTRODON,2] | E30: =A30&","&A31&","&A32&","&A33&","&A34&","&A35&","&A36&","&A37&","&A38 -> [GASTRODON,2],FormName = Gaxorus,Types = DRAGON,STEEL,BaseStats = 80,106,127,55,55,77,EVs = DEFENSE,2,Abilities = GOOEY,FORTIFICATION,HiddenAbilities = SHEERFORCE,Moves = 0,IRONDEFENSE,1,IRONDEFENSE,1,SNAPTRAP,1,DRAGONFURY,5,MIMIC,9,SHARPEN,13,DRAGONMAGIC,16,DRAGONGNAW,20,FALSESWIPE,24,VISEGRIP,28,GLARE,33,DRACOSHRED,36,SHIELDBASH,40,CRUNCH,44,KINGSSHIELD,49,DRACONICCRASH,TutorMoves = ANCIENTGLARE,ATTRACT,AURASPHERE,BEJEWELED,BODYPRESS,BREAKINGSWIPE,BULKUP,BULLDOZE,BULLETSEED,BURNINGJEALOUSY,CHIDORI,CLOSECOMBAT,COACHING,CONFUSERAY,COUPDEGRACE,CRUNCH,CURSE,DARKPULSE,DAZZLINGGLEAM,DEADLYREACH,DIVINEPUNISHMENT,DRACARYS,DRACOMETEOR,DRAGONBLOOD,DRAGONBREATH,DRAGONDANCE,DRAGONMAGIC,DRAININGKISS,DRAINPUNCH,DUALWINGBEAT,EARTHPOWER,EARTHQUAKE,ECHOEDVOICE,FABLEDRUSH,FALSESWIPE,FEATHERDANCE,FLIPTURN,FIREFANG,FLAMETHROWER,FLAREBLITZ,FOCUSBLAST,FORTISSIMO,FURYCUTTER,GASTROACID,GOLDENBULLET,GOLDRUSH,GYROBALL,HEATWAVE,HEX,HIDDENPOWER,HIVEMIND,HYPERVOICE,ICEFANG,INCINERATE,IRONDEFENSE,IRONHEAD,KNOCKOFF,LASHOUT,LEECHLIFE,MAGNETICCANNON,MEMENTO,METEORBEAM,METEORDRIVE,METEORMASH,MINERALWAVE,MUDSHACKLES,MUDSLIDE,NASTYPLOT,NOBLEROAR,OUTRAGE,PLAYROUGH,POISONFANG,POISONJAB,POWERUPPUNCH,PROTECT,REST,RETURN,ROCKBLAST,ROCKSLIDE,ROCKTOMB,SANDTOMB,SANDSTORM,SCALD,SCALESHOT,SCORCHINGSANDS,SHADOWBALL,SLEEPTALK,SLUDGEBOMB,SLUDGEWAVE,SNARL,SOAK,SOLARBEAM,SOLARECLIPSE,SPIKES,STARDUSTREVERIE,STEALTHROCK,STEELROLLER,STONEEDGE,SUBSTITUTE,SUPERPOWER,SWORDSDANCE,TAUNT,TERRAINPULSE,THUNDERFANG,THUNDERPUNCH,THUNDERWAVE,TOXIC,TOXICSPIKES,TRIATTACK,UTURN,VENDETTA,VITALITYDRAIN,WILDCHARGE,WORKUP,ZENHEADBUTT
A31: FormName = Gaxorus
A32: Types = DRAGON,STEEL
A33: BaseStats = 80,106,127,55,55,77
A34: EVs = DEFENSE,2
A35: Abilities = GOOEY,FORTIFICATION
A36: HiddenAbilities = SHEERFORCE
A37: Moves = 0,IRONDEFENSE,1,IRONDEFENSE,1,SNAPTRAP,1,DRAGONFURY,5,MIMIC,9,SHARPEN,13,DRAGONMAGIC,16,DRAGONGNAW,20,FALSESWIPE,24,VISEGRIP,28,GLARE,33,DRACOSHRED,36,SHIELDBASH,40,CRUNCH,44,KINGSSHIELD,49,DRACONICCRASH
A38: TutorMoves = ANCIENTGLARE,ATTRACT,AURASPHERE,BEJEWELED,BODYPRESS,BREAKINGSWIPE,BULKUP,BULLDOZE,BULLETSEED,BURNINGJEALOUSY,CHIDORI,CLOSECOMBAT,COACHING,CONFUSERAY,COUPDEGRACE,CRUNCH,CURSE,DARKPULSE,DAZZLINGGLEAM,DEADLYREACH,DIVINEPUNISHMENT,DRACARYS,DRACOMETEOR,DRAGONBLOOD,DRAGONBREATH,DRAGONDANCE,DRAGONMAGIC,DRAININGKISS,DRAINPUNCH,DUALWINGBEAT,EARTHPOWER,EARTHQUAKE,ECHOEDVOICE,FABLEDRUSH,FALSESWIPE,FEATHERDANCE,FLIPTURN,FIREFANG,FLAMETHROWER,FLAREBLITZ,FOCUSBLAST,FORTISSIMO,FURYCUTTER,GASTROACID,GOLDENBULLET,GOLDRUSH,GYROBALL,HEATWAVE,HEX,HIDDENPOWER,HIVEMIND,HYPERVOICE,ICEFANG,INCINERATE,IRONDEFENSE,IRONHEAD,KNOCKOFF,LASHOUT,LEECHLIFE,MAGNETICCANNON,MEMENTO,METEORBEAM,METEORDRIVE,METEORMASH,MINERALWAVE,MUDSHACKLES,MUDSLIDE,NASTYPLOT,NOBLEROAR,OUTRAGE,PLAYROUGH,POISONFANG,POISONJAB,POWERUPPUNCH,PROTECT,REST,RETURN,ROCKBLAST,ROCKSLIDE,ROCKTOMB,SANDTOMB,SANDSTORM,SCALD,SCALESHOT,SCORCHINGSANDS,SHADOWBALL,SLEEPTALK,SLUDGEBOMB,SLUDGEWAVE,SNARL,SOAK,SOLARBEAM,SOLARECLIPSE,SPIKES,STARDUSTREVERIE,STEALTHROCK,STEELROLLER,STONEEDGE,SUBSTITUTE,SUPERPOWER,SWORDSDANCE,TAUNT,TERRAINPULSE,THUNDERFANG,THUNDERPUNCH,THUNDERWAVE,TOXIC,TOXICSPIKES,TRIATTACK,UTURN,VENDETTA,VITALITYDRAIN,WILDCHARGE,WORKUP,ZENHEADBUTT
A39: #-------------------------------
A40: [SHELLOS,3] | E40: =A40&","&A41&","&A42&","&A43&","&A44&","&A45&","&A46&","&A47&","&A48 -> [SHELLOS,3],FormName = Sheino,Types = DRAGON,DARK,BaseStats = 55,65,60,74,40,43,EVs = SPEED,1,Abilities = GOOEY,HYPERCUTTER,HiddenAbilities = INTIMIDATE,Moves = 1,FAKEOUT,1,DRAGONFURY,5,MIMIC,9,PRANKCALL,13,DRAGONBLOOD,16,BREAKINGSWIPE,20,TAUNT,24,EVILTHORN,28,GLARE,33,WYVERNSLASH,36,WICKEDSTRIKE,40,CRUNCH,44,OBSTRUCT,49,DRACONICCRASH,EggMoves = BITE,PARTINGSHOT,QUASH,OUTRAGE,SNARL,ZENHEADBUTT,UPROAR
A41: FormName = Sheino
A42: Types = DRAGON,DARK
A43: BaseStats = 55,65,60,74,40,43
A44: EVs = SPEED,1
A45: Abilities = GOOEY,HYPERCUTTER
A46: HiddenAbilities = INTIMIDATE
A47: Moves = 1,FAKEOUT,1,DRAGONFURY,5,MIMIC,9,PRANKCALL,13,DRAGONBLOOD,16,BREAKINGSWIPE,20,TAUNT,24,EVILTHORN,28,GLARE,33,WYVERNSLASH,36,WICKEDSTRIKE,40,CRUNCH,44,OBSTRUCT,49,DRACONICCRASH
A48: EggMoves = BITE,PARTINGSHOT,QUASH,OUTRAGE,SNARL,ZENHEADBUTT,UPROAR
A49: #-------------------------------
A50: [GASTRODON,3] | E50: =A50&","&A51&","&A52&","&A53&","&A54&","&A55&","&A56&","&A57&","&A58 -> [GASTRODON,3],FormName = Gastreigon,Types = DRAGON,DARK,BaseStats = 70,100,70,105,70,80,EVs = ATTACK,1,SPEED,1,Abilities = GOOEY,HYPERCUTTER,HiddenAbilities = INTIMIDATE,Moves = 0,CHEAPSHOT,1,CHEAPSHOT,1,FAKEOUT,1,DRAGONFURY,5,MIMIC,9,PRANKCALL,13,DRAGONBLOOD,16,BREAKINGSWIPE,20,TAUNT,24,EVILTHORN,28,GLARE,33,WYVERNSLASH,36,WICKEDSTRIKE,40,CRUNCH,44,OBSTRUCT,49,DRACONICCRASH,#-------------------------------
A51: FormName = Gastreigon
A52: Types = DRAGON,DARK
A53: BaseStats = 70,100,70,105,70,80
A54: EVs = ATTACK,1,SPEED,1
A55: Abilities = GOOEY,HYPERCUTTER
A56: HiddenAbilities = INTIMIDATE
A57: Moves = 0,CHEAPSHOT,1,CHEAPSHOT,1,FAKEOUT,1,DRAGONFURY,5,MIMIC,9,PRANKCALL,13,DRAGONBLOOD,16,BREAKINGSWIPE,20,TAUNT,24,EVILTHORN,28,GLARE,33,WYVERNSLASH,36,WICKEDSTRIKE,40,CRUNCH,44,OBSTRUCT,49,DRACONICCRASH
A58: #-------------------------------
A59: [SHELLOS,4] | E59: =A59&","&A60&","&A61&","&A62&","&A63&","&A64&","&A65&","&A66&","&A67 -> [SHELLOS,4],FormName = Shommo-o,Types = DRAGON,FIGHTING,BaseStats = 65,45,79,30,50,68,EVs = ATTACK,1,Abilities = GOOEY,MARVELSCALE,HiddenAbilities = NOGUARD,Moves = 1,CHIORB,1,DRAGONFURY,5,MIMIC,9,STEALTHROCK,13,DRAGONBLOOD,16,CIRCLETHROW,20,SPIKES,24,BATTLEOFWITS,28,GLARE,33,WYVERNSLASH,36,FOCUSBLAST,40,TITANHAMMER,44,COACHING,49,DRACOMETEOR,EggMoves = HEADBUTT,CLOSECOMBAT,LOWSWEEP,STOMPINGTANTRUM,ZENHEADBUTT,UPROAR
A60: FormName = Shommo-o
A61: Types = DRAGON,FIGHTING
A62: BaseStats = 65,45,79,30,50,68
A63: EVs = ATTACK,1
A64: Abilities = GOOEY,MARVELSCALE
A65: HiddenAbilities = NOGUARD
A66: Moves = 1,CHIORB,1,DRAGONFURY,5,MIMIC,9,STEALTHROCK,13,DRAGONBLOOD,16,CIRCLETHROW,20,SPIKES,24,BATTLEOFWITS,28,GLARE,33,WYVERNSLASH,36,FOCUSBLAST,40,TITANHAMMER,44,COACHING,49,DRACOMETEOR
A67: EggMoves = HEADBUTT,CLOSECOMBAT,LOWSWEEP,STOMPINGTANTRUM,ZENHEADBUTT,UPROAR
A68: #-------------------------------
A69: [GASTRODON,4] | E69: =A69&","&A70&","&A71&","&A72&","&A73&","&A74&","&A75&","&A76&","&A77 -> [GASTRODON,4],FormName = Gastro-o,Types = DRAGON,FIGHTING,BaseStats = 80,75,100,50,80,90,EVs = ATTACK,1,DEFENSE,1,Abilities = GOOEY,MARVELSCALE,HiddenAbilities = NOGUARD,Moves = 0,BODYPRESS,1,BODYPRESS,1,CHIORB,1,DRAGONFURY,5,MIMIC,9,STEALTHROCK,13,DRAGONBLOOD,16,CIRCLETHROW,20,SPIKES,24,BATTLEOFWITS,28,GLARE,35,WYVERNSLASH,38,FOCUSBLAST,42,TITANHAMMER,46,COACHING,50,DRACOMETEOR,EggMoves = HEADBUTT,CLOSECOMBAT,LOWSWEEP,STOMPINGTANTRUM,ZENHEADBUTT,UPROAR
A70: FormName = Gastro-o
A71: Types = DRAGON,FIGHTING
A72: BaseStats = 80,75,100,50,80,90
A73: EVs = ATTACK,1,DEFENSE,1
A74: Abilities = GOOEY,MARVELSCALE
A75: HiddenAbilities = NOGUARD
A76: Moves = 0,BODYPRESS,1,BODYPRESS,1,CHIORB,1,DRAGONFURY,5,MIMIC,9,STEALTHROCK,13,DRAGONBLOOD,16,CIRCLETHROW,20,SPIKES,24,BATTLEOFWITS,28,GLARE,35,WYVERNSLASH,38,FOCUSBLAST,42,TITANHAMMER,46,COACHING,50,DRACOMETEOR
A77: EggMoves = HEADBUTT,CLOSECOMBAT,LOWSWEEP,STOMPINGTANTRUM,ZENHEADBUTT,UPROAR
A78: #-------------------------------
A79: [SHELLOS,5] | E79: =A79&","&A80&","&A81&","&A82&","&A83&","&A84&","&A85&","&A86&","&A87 -> [SHELLOS,5],FormName = Swallos,Types = DRAGON,FAIRY,BaseStats = 65,37,69,45,50,69,Abilities = GOOEY,HEALER,HiddenAbilities = MISTYSURGE,Moves = 1,PIXIEWAVE,1,TWISTER,5,MIMIC,9,MISTYTERRAIN,13,CHARM,13,CAPTIVATE,16,ANCIENTGLARE,20,FAIRYTALE,24,BEWITCH,28,AMNESIA,33,MISTBALL,36,DRAGONGALE,40,RELICSONG,44,WILDIMAGINATION,49,DRAGONENERGY,#-------------------------------,[GASTRODON,5]
A80: FormName = Swallos
A81: Types = DRAGON,FAIRY
A82: BaseStats = 65,37,69,45,50,69
A83: Abilities = GOOEY,HEALER
A84: HiddenAbilities = MISTYSURGE
A85: Moves = 1,PIXIEWAVE,1,TWISTER,5,MIMIC,9,MISTYTERRAIN,13,CHARM,13,CAPTIVATE,16,ANCIENTGLARE,20,FAIRYTALE,24,BEWITCH,28,AMNESIA,33,MISTBALL,36,DRAGONGALE,40,RELICSONG,44,WILDIMAGINATION,49,DRAGONENERGY
A86: #-------------------------------
A87: [GASTRODON,5] | E87: =A87&","&A88&","&A89&","&A90&","&A91&","&A92&","&A93&","&A94&","&A95 -> [GASTRODON,5],FormName = Gastaria,Types = DRAGON,FAIRY,BaseStats = 80,58,101,72,73,101,EVs = DEFENSE,1,SPECIAL_DEFENSE,1,Abilities = GOOEY,HEALER,HiddenAbilities = MISTYSURGE,Moves = 0,HEALPULSE,1,HEALPULSE,1,PIXIEWAVE,1,TWISTER,5,MIMIC,9,MISTYTERRAIN,13,CHARM,13,CAPTIVATE,16,ANCIENTGLARE,20,FAIRYTALE,24,MISTBALL,28,BALANCERCHANGEREQUIRED,35,DRAGONGALE,38,BALANCERCHANGEREQUIRED,42,RELICSONG,46,WILDIMAGINATION,50,DRAGONENERGY,#-------------------------------
A88: FormName = Gastaria
A89: Types = DRAGON,FAIRY
A90: BaseStats = 80,58,101,72,73,101
A91: EVs = DEFENSE,1,SPECIAL_DEFENSE,1
A92: Abilities = GOOEY,HEALER
A93: HiddenAbilities = MISTYSURGE
A94: Moves = 0,HEALPULSE,1,HEALPULSE,1,PIXIEWAVE,1,TWISTER,5,MIMIC,9,MISTYTERRAIN,13,CHARM,13,CAPTIVATE,16,ANCIENTGLARE,20,FAIRYTALE,24,MISTBALL,28,BALANCERCHANGEREQUIRED,35,DRAGONGALE,38,BALANCERCHANGEREQUIRED,42,RELICSONG,46,WILDIMAGINATION,50,DRAGONENERGY
A95: #-------------------------------
A96: [SHELLOS,6] | E96: =A96&","&A97&","&A98&","&A99&","&A100&","&A101&","&A102&","&A103&","&A104 -> [SHELLOS,6],FormName = Shapinch,Types = DRAGON,BUG,BaseStats = 35,60,45,64,60,45,EVs = SPEED,1,Abilities = GOOEY,COMPOUNDEYES,HiddenAbilities = SKILLLINK,Moves = 1,FIRSTIMPRESSION,1,TWISTER,5,MIMIC,9,POWDER,13,DRAGONMAGIC,16,BREAKINGSWIPE,16,DRAGONBREATH,20,POWDER,24,PINMISSILE,28,GLARE,33,DRAGONCLAW,33,DRACOSURGE,36,DRAGONFLYCHARGE,36,BUGBUZZ,40,GOLDENBULLET,44,STICKYWEB,49,DRACOMETEOR,#-------------------------------
A97: FormName = Shapinch
A98: Types = DRAGON,BUG
A99: BaseStats = 35,60,45,64,60,45
A100: EVs = SPEED,1
...

Sheet DIVIDER>>

Sheet Completed Species
A1: ID | B1: Internal Name | C1: Name | D1: Type1 | E1: Type2 | F1: Concatenated Types | G1: HP | H1: Attack | I1: Defense | J1: Speed | K1: Special Attack | L1: Special Defense | M1: BST Total | N1: EV_Kind1 | O1: Amount1 | P1: EV_Kind2 | Q1: Amount2 | R1: EV_Kind3 | S1: Amount3 | T1: Concatenated EVs | U1: Ability1 | V1: Ability2 | W1: HiddenAbility | X1: Concatenated Abilities | Y1: Move List | Z1: Tutor Moves | AA1: Egg Moves | AB1: Evolves into | AC1: Method | AD1: Evolve Condition | AE1: Evolves into2 | AF1: Method2 | AG1: Evolve Condition2 | AH1: Evolves into3 | AI1: Method3 | AJ1: Evolve Condition3 | AK1: Evolves into4 | AL1: Method4 | AM1: Evolve Condition4 | AN1: Evolves into5 | AO1: Method5 | AP1: Evolve Condition5 | AQ1: Evolves into6 | AR1: Method6 | AS1: Evolve Condition6 | AT1: Evolves into7 | AU1: Method7 | AV1: Evolve Condition7 | AW1: Evolves into8 | AX1: Method8 | AY1: Evolve Condition8
A2: 1 | B2: [KOFFING] | C2: Koffing | D2: ='BST Extract'!J2 -> FIRE | E2: ='BST Extract'!K2 -> POISON | F2: =D2&","&E2 -> FIRE,POISON | G2: ='BST Extract'!C2 -> 60 | H2: ='BST Extract'!D2 -> 40 | I2: ='BST Extract'!E2 -> 55 | J2: ='BST Extract'!F2 -> 35 | K2: ='BST Extract'!G2 -> 65 | L2: ='BST Extract'!H2 -> 85 | M2: ='BST Extract'!I2 -> 340 | N2: SPECIAL_DEFENSE | O2: 1 | T2: =N2&","&O2&","&P2&","&Q2&","&R2&","&S2 -> SPECIAL_DEFENSE,1,,,, | U2: ='Ability Extract'!C2 -> LEVITATE | V2: ='Ability Extract'!D2 -> WHITESMOKE | W2: ='Ability Extract'!E2 -> MAGMAARMOR | X2: ='Ability Extract'!F2 -> LEVITATE,WHITESMOKE,MAGMAARMOR | Y2: =VLOOKUP($A2,'Moves Species'!$A:$E,3,FALSE) -> 1, DEFENSECURL, 1, SMOG, 4, EMBER, 6, POISONGAS, 9, FIRESPIN, 12, HAZE, 15, CLEARSMOG, 18, INCINERATE, 22, CORRODE, 26, FLAMEBURST, 29, SCALD, 32, MIASMA, 35, LAVAPLUME, 38, CORROSIVEGAS, 41, SLUDGEBOMB, 44, FLAMETHROWER, 47, TOXIC, 50, ACIDRAIN, 53, INFERNO, 56, STEAMERUPTION, 60, ERUPTION, | Z2: =VLOOKUP($A2,'Moves Species'!$A:$E,4,FALSE) -> ACIDRAIN, ACROBATICS, AIRSLASH, ATTRACT, BATTERYACID, BODYPRESS, BODYSLAM, BOUNCE, CAUSTICACID, CLEARSMOG, CORROSIVEGAS, DARKPULSE, DAZZLINGGLEAM, DUNEBLAST, DUSTDEVILS, EARTHPOWER, ENERGYBALL, FIREBLAST, FLAMECHARGE, FLAMETHROWER, FLAMEVOLLEY, FLAREBLITZ, FLUXWAVE, GAMMARAY, GASTROACID, GEOMANCY, GIGADRAIN, GOLDRUSH, GOSSIP, GUNKSHOT, GYROBALL, HAZE, HEATWAVE, HIDDENPOWER, INCINERATE, IRONDEFENSE, IRONHEAD, LOVEBURST, MEMENTO, MIASMA, MUDSHACKLES, MUDSLIDE, MYSTICALFIRE, NASTYPLOT, PROTECT, QUICKSAND, RAYOFLIGHT, REST, RETURN, ROCKBLAST, ROCKSLIDE, ROCKTOMB, SANDSTORM, SANDTOMB, SCALD, SCORCHINGSANDS, SLEEPTALK, SLUDGEBOMB, SLUDGEWAVE, STEALTHROCK, STEAMERUPTION, STRANGESTEAM, SUNNYDAY, TAUNT, TERRAINPULSE, TOXIC, VENOMDRAIN, WILDFIRE, WORKUP, | AA2: =VLOOKUP($A2,'Moves Species'!$A:$E,5,FALSE) -> CURSE, HEATCRASH, ALKALINEBOMB, SIZZLE, FIERYDANCE, FIREBLAST, DESTINYBOND, HYDROSTEAM, FIREWALL, | AB2: WEEZING | AC2: Level | AD2: 33
A3: =A2+1 -> 2 | B3: [WEEZING] | C3: Weezing | D3: ='BST Extract'!J3 -> FIRE | E3: ='BST Extract'!K3 -> POISON | F3: =D3&","&E3 -> FIRE,POISON | G3: ='BST Extract'!C3 -> 85 | H3: ='BST Extract'!D3 -> 55 | I3: ='BST Extract'!E3 -> 85 | J3: ='BST Extract'!F3 -> 60 | K3: ='BST Extract'!G3 -> 95 | L3: ='BST Extract'!H3 -> 110 | M3: ='BST Extract'!I3 -> 490 | N3: SPECIAL_DEFENSE | O3: 2 | T3: =N3&","&O3&","&P3&","&Q3&","&R3&","&S3 -> SPECIAL_DEFENSE,2,,,, | U3: ='Ability Extract'!C3 -> LEVITATE | V3: ='Ability Extract'!D3 -> WHITESMOKE | W3: ='Ability Extract'!E3 -> MAGMAARMOR | X3: ='Ability Extract'!F3 -> LEVITATE,WHITESMOKE,MAGMAARMOR | Y3: =VLOOKUP($A3,'Moves Species'!$A:$E,3,FALSE) -> 0, WILLOWISP, 1, WILLOWISP, 1, DEFENSECURL, 1, SMOG, 4, EMBER, 6, POISONGAS, 9, FIRESPIN, 12, HAZE, 15, CLEARSMOG, 18, INCINERATE, 22, CORRODE, 26, FLAMEBURST, 29, SCALD, 32, MIASMA, 35, LAVAPLUME, 38, CORROSIVEGAS, 41, SLUDGEBOMB, 44, FLAMETHROWER, 47, TOXIC, 50, ACIDRAIN, 53, INFERNO, 56, STEAMERUPTION, 60, ERUPTION, | Z3: =VLOOKUP($A3,'Moves Species'!$A:$E,4,FALSE) -> ACIDRAIN, ACROBATICS, AIRSLASH, ATTRACT, BATTERYACID, BODYPRESS, BODYSLAM, BOUNCE, CAUSTICACID, CLEARSMOG, CORROSIVEGAS, DARKPULSE, DAZZLINGGLEAM, DUNEBLAST, DUSTDEVILS, EARTHPOWER, ENERGYBALL, FIREBLAST, FLAMECHARGE, FLAMETHROWER, FLAMEVOLLEY, FLAREBLITZ, FLUXWAVE, GAMMARAY, GASTROACID, GEOMANCY, GIGADRAIN, GOLDRUSH, GOSSIP, GUNKSHOT, GYROBALL, HAZE, HEATWAVE, HIDDENPOWER, INCINERATE, IRONDEFENSE, IRONHEAD, LOVEBURST, MEMENTO, MIASMA, MUDSHACKLES, MUDSLIDE, MYSTICALFIRE, NASTYPLOT, PROTECT, QUICKSAND, RAYOFLIGHT, REST, RETURN, ROCKBLAST, ROCKSLIDE, ROCKTOMB, SANDSTORM, SANDTOMB, SCALD, SCORCHINGSANDS, SLEEPTALK, SLUDGEBOMB, SLUDGEWAVE, STEALTHROCK, STEAMERUPTION, STRANGESTEAM, SUNNYDAY, TAUNT, TERRAINPULSE, TOXIC, VENOMDRAIN, WILDFIRE, WORKUP, | AA3: =VLOOKUP($A3,'Moves Species'!$A:$E,5,FALSE) -> 0
A4: =A3+1 -> 3 | B4: [SOLOSIS] | C4: Solosis | D4: ='BST Extract'!J4 -> WATER | E4: ='BST Extract'!K4 -> PSYCHIC | F4: =D4&","&E4 -> WATER,PSYCHIC | G4: ='BST Extract'!C4 -> 45 | H4: ='BST Extract'!D4 -> 20 | I4: ='BST Extract'!E4 -> 60 | J4: ='BST Extract'!F4 -> 20 | K4: ='BST Extract'!G4 -> 85 | L4: ='BST Extract'!H4 -> 60 | M4: ='BST Extract'!I4 -> 290 | N4: SPECIAL_ATTACK | O4: 1 | T4: =N4&","&O4&","&P4&","&Q4&","&R4&","&S4 -> SPECIAL_ATTACK,1,,,, | U4: ='Ability Extract'!C4 -> SWIFTSWIM | V4: ='Ability Extract'!D4 -> MAGICBOUNCE | W4: ='Ability Extract'!E4 -> TECHNICIAN | X4: ='Ability Extract'!F4 -> SWIFTSWIM,MAGICBOUNCE,TECHNICIAN | Y4: =VLOOKUP($A4,'Moves Species'!$A:$E,3,FALSE) -> 1, CONFUSION, 1, WATERSPORT, 4, BUBBLE, 7, QUICKSPELL, 10, HEALBLOCK, 13, ARCANEBLAST, 16, WATERPULSE, 19, SOAK, 22, PSYBEAM, 25, DRENCH, 28, REFLECT, 28, LIGHTSCREEN, 31, WISH, 34, PSYSHOCK, 37, OCEANBLAST, 40, CALMMIND, 43, PSYCHIC, 46, TIDALWAVE, 49, STOREDPOWER, 52, TRICKROOM, 56, HYDROPUMP, 60, PSYCHOBOOST, | Z4: =VLOOKUP($A4,'Moves Species'!$A:$E,4,FALSE) -> ALLERGY, ARCANEENERGY, ATTRACT, AURASPHERE, BATTLEOFWITS, BLIZZARD, BRINE, CALMMIND, CASCADE, CHARGEBEAM, CHIDORI, CHILLINGTOUCH, CLEANSE, CONFUSERAY, COSMICPOWER, COVET, CURSE, DARKPULSE, DAZZLINGGLEAM, DEFOG, DRAININGKISS, EARTHPOWER, ENERGYBALL, FLIPTURN, FLUXWAVE, GAMMARAY, GIGADRAIN, HAIL, HAZE, HEX, HEXBOLT, HIDDENPOWER, HYPERVOICE, ICEBEAM, ICEPUNCH, ICICLESPEAR, ICYWIND, LIGHTSCREEN, MAGICROOM, METRONOME, MINDDRAIN, MINDMELD, MISSILESHOT, MIST, MIXEDWAVES, MYSTICPULSE, NASTYPLOT, NUMBINGWIND, OCEANWRATH, OVERFLOW, PHOBIA, PIXIEDUST, PROTECT, PSYCHIC, PSYCHICTERRAIN, RAINDANCE, REFLECT, REST, RETURN, SAFEGUARD, SCALD, SIGNALBEAM, SLEEPTALK, SOAK, STRANGESTEAM, SUBMERGE, SUBSTITUTE, TERRAINPULSE, THUNDERWAVE, TIDALWAVE, TOXIC, TRIATTACK, VOLTSWITCH, WAIL, WATERPRESSURE, WATERPULSE, WHIRLPOOL, WISH, WONDERROOM, | AA4: =VLOOKUP($A4,'Moves Species'!$A:$E,5,FALSE) -> ACIDARMOR, GUARDSWAP, POWERSWAP, SPEEDSWAP, TRICK, BUBBLEBEAM, HYPNOSIS, KARMASPELL, FREEZEDRY, EXTRASENSORY, MUDDYWATER, | AB4: DUOSION | AC4: Level | AD4: 27
A5: =A4+1 -> 4 | B5: [DUOSION] | C5: Duosion | D5: ='BST Extract'!J5 -> WATER | E5: ='BST Extract'!K5 -> PSYCHIC | F5: =D5&","&E5 -> WATER,PSYCHIC | G5: ='BST Extract'!C5 -> 60 | H5: ='BST Extract'!D5 -> 35 | I5: ='BST Extract'!E5 -> 70 | J5: ='BST Extract'!F5 -> 35 | K5: ='BST Extract'!G5 -> 100 | L5: ='BST Extract'!H5 -> 70 | M5: ='BST Extract'!I5 -> 370 | N5: SPECIAL_ATTACK | O5: 2 | T5: =N5&","&O5&","&P5&","&Q5&","&R5&","&S5 -> SPECIAL_ATTACK,2,,,, | U5: ='Ability Extract'!C5 -> SWIFTSWIM | V5: ='Ability Extract'!D5 -> MAGICBOUNCE | W5: ='Ability Extract'!E5 -> TECHNICIAN | X5: ='Ability Extract'!F5 -> SWIFTSWIM,MAGICBOUNCE,TECHNICIAN | Y5: =VLOOKUP($A5,'Moves Species'!$A:$E,3,FALSE) -> 0, CHECKMATE, 1, CHECKMATE, 1, CONFUSION, 1, WATERSPORT, 4, BUBBLE, 7, QUICKSPELL, 10, HEALBLOCK, 13, ARCANEBLAST, 16, WATERPULSE, 19, SOAK, 22, PSYBEAM, 25, DRENCH, 28, REFLECT, 28, LIGHTSCREEN, 31, WISH, 34, PSYSHOCK, 37, OCEANBLAST, 40, CALMMIND, 43, PSYCHIC, 46, TIDALWAVE, 49, STOREDPOWER, 52, TRICKROOM, 56, HYDROPUMP, 60, PSYCHOBOOST, | Z5: =VLOOKUP($A5,'Moves Species'!$A:$E,4,FALSE) -> ALLERGY, ARCANEENERGY, ATTRACT, AURASPHERE, BATTLEOFWITS, BLIZZARD, BRINE, CALMMIND, CASCADE, CHARGEBEAM, CHIDORI, CHILLINGTOUCH, CLEANSE, CONFUSERAY, COSMICPOWER, COVET, CURSE, DARKPULSE, DAZZLINGGLEAM, DEFOG, DRAININGKISS, EARTHPOWER, ENERGYBALL, FLIPTURN, FLUXWAVE, GAMMARAY, GIGADRAIN, HAIL, HAZE, HEX, HEXBOLT, HIDDENPOWER, HYPERVOICE, ICEBEAM, ICEPUNCH, ICICLESPEAR, ICYWIND, LIGHTSCREEN, MAGICROOM, METRONOME, MINDDRAIN, MINDMELD, MISSILESHOT, MIST, MIXEDWAVES, MYSTICPULSE, NASTYPLOT, NUMBINGWIND, OCEANWRATH, OVERFLOW, PHOBIA, PIXIEDUST, PROTECT, PSYCHIC, PSYCHICTERRAIN, RAINDANCE, REFLECT, REST, RETURN, SAFEGUARD, SCALD, SIGNALBEAM, SLEEPTALK, SOAK, STRANGESTEAM, SUBMERGE, SUBSTITUTE, TERRAINPULSE, THUNDERWAVE, TIDALWAVE, TOXIC, TRIATTACK, VOLTSWITCH, WAIL, WATERPRESSURE, WATERPULSE, WHIRLPOOL, WISH, WONDERROOM, | AA5: =VLOOKUP($A5,'Moves Species'!$A:$E,5,FALSE) -> 0 | AB5: REUNICLUS | AC5: Level | AD5: 41
A6: =A5+1 -> 5 | B6: [REUNICLUS] | C6: Reuniclus | D6: ='BST Extract'!J6 -> WATER | E6: ='BST Extract'!K6 -> PSYCHIC | F6: =D6&","&E6 -> WATER,PSYCHIC | G6: ='BST Extract'!C6 -> 70 | H6: ='BST Extract'!D6 -> 40 | I6: ='BST Extract'!E6 -> 95 | J6: ='BST Extract'!F6 -> 60 | K6: ='BST Extract'!G6 -> 130 | L6: ='BST Extract'!H6 -> 95 | M6: ='BST Extract'!I6 -> 490 | N6: SPECIAL_ATTACK | O6: 3 | T6: =N6&","&O6&","&P6&","&Q6&","&R6&","&S6 -> SPECIAL_ATTACK,3,,,, | U6: ='Ability Extract'!C6 -> SWIFTSWIM | V6: ='Ability Extract'!D6 -> MAGICBOUNCE | W6: ='Ability Extract'!E6 -> TECHNICIAN | X6: ='Ability Extract'!F6 -> SWIFTSWIM,MAGICBOUNCE,TECHNICIAN | Y6: =VLOOKUP($A6,'Moves Species'!$A:$E,3,FALSE) -> 1, CHECKMATE, 1, CONFUSION, 1, WATERSPORT, 4, BUBBLE, 7, QUICKSPELL, 10, HEALBLOCK, 13, ARCANEBLAST, 16, WATERPULSE, 19, SOAK, 22, PSYBEAM, 25, DRENCH, 28, REFLECT, 28, LIGHTSCREEN, 31, WISH, 34, PSYSHOCK, 37, OCEANBLAST, 40, CALMMIND, 43, PSYCHIC, 46, TIDALWAVE, 49, STOREDPOWER, 52, TRICKROOM, 56, HYDROPUMP, 60, PSYCHOBOOST, | Z6: =VLOOKUP($A6,'Moves Species'!$A:$E,4,FALSE) -> ALLERGY, ARCANEENERGY, ATTRACT, AURASPHERE, BATTLEOFWITS, BLIZZARD, BRINE, CALMMIND, CASCADE, CHARGEBEAM, CHIDORI, CHILLINGTOUCH, CLEANSE, CONFUSERAY, COSMICPOWER, COVET, CURSE, DARKPULSE, DAZZLINGGLEAM, DEFOG, DRAININGKISS, EARTHPOWER, ENERGYBALL, FLIPTURN, FLUXWAVE, GAMMARAY, GIGADRAIN, HAIL, HAZE, HEX, HEXBOLT, HIDDENPOWER, HYPERVOICE, ICEBEAM, ICEPUNCH, ICICLESPEAR, ICYWIND, LIGHTSCREEN, MAGICROOM, METRONOME, MINDDRAIN, MINDMELD, MISSILESHOT, MIST, MIXEDWAVES, MYSTICPULSE, NASTYPLOT, NUMBINGWIND, OCEANWRATH, OVERFLOW, PHOBIA, PIXIEDUST, PROTECT, PSYCHIC, PSYCHICTERRAIN, RAINDANCE, REFLECT, REST, RETURN, SAFEGUARD, SCALD, SIGNALBEAM, SLEEPTALK, SOAK, STRANGESTEAM, SUBMERGE, SUBSTITUTE, TERRAINPULSE, THUNDERWAVE, TIDALWAVE, TOXIC, TRIATTACK, VOLTSWITCH, WAIL, WATERPRESSURE, WATERPULSE, WHIRLPOOL, WISH, WONDERROOM, | AA6: =VLOOKUP($A6,'Moves Species'!$A:$E,5,FALSE) -> 0
A7: =A6+1 -> 6 | B7: [GASTLY] | C7: Gastly | D7: ='BST Extract'!J7 -> ICE | E7: ='BST Extract'!K7 -> FLYING | F7: =D7&","&E7 -> ICE,FLYING | G7: ='BST Extract'!C7 -> 30 | H7: ='BST Extract'!D7 -> 30 | I7: ='BST Extract'!E7 -> 30 | J7: ='BST Extract'!F7 -> 85 | K7: ='BST Extract'!G7 -> 100 | L7: ='BST Extract'!H7 -> 35 | M7: ='BST Extract'!I7 -> 310 | N7: SPECIAL_ATTACK | O7: 1 | T7: =N7&","&O7&","&P7&","&Q7&","&R7&","&S7 -> SPECIAL_ATTACK,1,,,, | U7: ='Ability Extract'!C7 -> FILTER | V7: ='Ability Extract'!D7 -> CLOUDNINE | W7: ='Ability Extract'!E7 -> CURSEDBODY | X7: ='Ability Extract'!F7 -> FILTER,CLOUDNINE,CURSEDBODY | Y7: =VLOOKUP($A7,'Moves Species'!$A:$E,3,FALSE) -> 1, ICEVORTEX, 1, COLDFRONT, 1, POWDERSNOW, 4, GALEHOLD, 8, MIST, 11, HAIL, 15, ICYWIND, 18, AIRCUTTER, 21, HYPOTHERMIA, 24, DEFOG, 27, EROSION, 30, NUMBINGWIND, 33, STARDUSTREVERIE, 36, TORNADO, 39, FROSTBREATH, 42, ICEBEAM, 45, AERIALPULSE, 48, WEATHERBALL, 52, BOREASBREATH, 56, TAILWIND, 60, BLIZZARD, | Z7: =VLOOKUP($A7,'Moves Species'!$A:$E,4,FALSE) -> ACIDRAIN, AERIALACE, AERIALPULSE, AIRSLASH, AMBUSH, ASTRALWIND, ATTRACT, BLIZZARD, BONECHILL, BRINE, CALMMIND, CHARGEBEAM, CHILLINGTOUCH, CLEARSMOG, DAZZLINGGLEAM, DEFOG, DRAGONGALE, DUSTDEVILS, ECHOEDVOICE, FLUXWAVE, FROSTBITE, GENESIS, GOSSIP, HAIL, HAZE, HIDDENPOWER, HURRICANE, HYPERVOICE, HYPOTHERMIA, ICEBEAM, ICEFANG, ICEHAMMER, ICEPUNCH, ICICLESPEAR, ICICLESTRIKE, ICYWIND, LIQUIDATION, MIRRORSHOT, MIST, MOONBLAST, MYSTICPULSE, NASTYPLOT, NEBULASTRIKE, NUMBINGWIND, OCEANWRATH, PIXIEDUST, PROTECT, QUICKGUARD, RAINDANCE, RAYOFLIGHT, REST, RETURN, SCALD, SIGNALBEAM, SLEEPTALK, SOAK, STRANGESTEAM, SWITCHEROO, TAILWIND, TEMPESTFLARE, TERRAINPULSE, TORNADO, TOXIC, TURBULENCE, WAIL, WATERPULSE, WEATHERBALL, WHIRLPOOL, WISH, | AA7: =VLOOKUP($A7,'Moves Species'!$A:$E,5,FALSE) -> AURORAVEIL, HURRICANE, RAINDANCE, TRIATTACK, FROZENHEART, LIQUIDNITROGEN, CHECKMATE, MEMENTO, BONECHILL, SNOWFLAKES, | AB7: HAUNTER | AC7: Level | AD7: 25
A8: =A7+1 -> 7 | B8: [HAUNTER] | C8: Haunter | D8: ='BST Extract'!J8 -> ICE | E8: ='BST Extract'!K8 -> FLYING | F8: =D8&","&E8 -> ICE,FLYING | G8: ='BST Extract'!C8 -> 50 | H8: ='BST Extract'!D8 -> 45 | I8: ='BST Extract'!E8 -> 45 | J8: ='BST Extract'!F8 -> 95 | K8: ='BST Extract'!G8 -> 115 | L8: ='BST Extract'!H8 -> 55 | M8: ='BST Extract'!I8 -> 405 | N8: SPECIAL_ATTACK | O8: 2 | T8: =N8&","&O8&","&P8&","&Q8&","&R8&","&S8 -> SPECIAL_ATTACK,2,,,, | U8: ='Ability Extract'!C8 -> FILTER | V8: ='Ability Extract'!D8 -> CLOUDNINE | W8: ='Ability Extract'!E8 -> SNOWWARNING | X8: ='Ability Extract'!F8 -> FILTER,CLOUDNINE,SNOWWARNING | Y8: =VLOOKUP($A8,'Moves Species'!$A:$E,3,FALSE) -> 0, AIRSLASH, 1, AIRSLASH, 1, ICEVORTEX, 1, COLDFRONT, 1, POWDERSNOW, 4, GALEHOLD, 8, MIST, 11, HAIL, 15, ICYWIND, 18, AIRCUTTER, 21, HYPOTHERMIA, 24, DEFOG, 27, EROSION, 30, NUMBINGWIND, 33, STARDUSTREVERIE, 36, TORNADO, 39, FROSTBREATH, 42, ICEBEAM, 45, AERIALPULSE, 48, WEATHERBALL, 52, BOREASBREATH, 56, TAILWIND, 60, BLIZZARD, | Z8: =VLOOKUP($A8,'Moves Species'!$A:$E,4,FALSE) -> ACIDRAIN, AERIALACE, AERIALPULSE, AIRSLASH, AMBUSH, ASTRALWIND, ATTRACT, BLIZZARD, BONECHILL, BRINE, CALMMIND, CHARGEBEAM, CHILLINGTOUCH, CLEARSMOG, DAZZLINGGLEAM, DEFOG, DRAGONGALE, DUSTDEVILS, ECHOEDVOICE, FLUXWAVE, FROSTBITE, GENESIS, GOSSIP, HAIL, HAZE, HIDDENPOWER, HURRICANE, HYPERVOICE, HYPOTHERMIA, ICEBEAM, ICEFANG, ICEHAMMER, ICEPUNCH, ICICLESPEAR, ICICLESTRIKE, ICYWIND, LIQUIDATION, MIRRORSHOT, MIST, MOONBLAST, MYSTICPULSE, NASTYPLOT, NEBULASTRIKE, NUMBINGWIND, OCEANWRATH, PIXIEDUST, PROTECT, QUICKGUARD, RAINDANCE, RAYOFLIGHT, REST, RETURN, SCALD, SIGNALBEAM, SLEEPTALK, SOAK, STRANGESTEAM, SWITCHEROO, TAILWIND, TEMPESTFLARE, TERRAINPULSE, TORNADO, TOXIC, TURBULENCE, WAIL, WATERPULSE, WEATHERBALL, WHIRLPOOL, WISH, | AA8: =VLOOKUP($A8,'Moves Species'!$A:$E,5,FALSE) -> 0 | AB8: GENGAR | AC8: Item | AD8: WINDSTONE
A9: =A8+1 -> 8 | B9: [GENGAR] | C9: Gengar | D9: ='BST Extract'!J9 -> ICE | E9: ='BST Extract'!K9 -> FLYING | F9: =D9&","&E9 -> ICE,FLYING | G9: ='BST Extract'!C9 -> 65 | H9: ='BST Extract'!D9 -> 60 | I9: ='BST Extract'!E9 -> 60 | J9: ='BST Extract'!F9 -> 115 | K9: ='BST Extract'!G9 -> 130 | L9: ='BST Extract'!H9 -> 70 | M9: ='BST Extract'!I9 -> 500 | N9: SPECIAL_ATTACK | O9: 3 | T9: =N9&","&O9&","&P9&","&Q9&","&R9&","&S9 -> SPECIAL_ATTACK,3,,,, | U9: ='Ability Extract'!C9 -> FILTER | V9: ='Ability Extract'!D9 -> CLOUDNINE | W9: ='Ability Extract'!E9 -> SNOWWARNING | X9: ='Ability Extract'!F9 -> FILTER,CLOUDNINE,SNOWWARNING | Y9: =VLOOKUP($A9,'Moves Species'!$A:$E,3,FALSE) -> 0, FREEZEDRY, 1, FREEZEDRY, 1, AIRSLASH, 1, ICEVORTEX, 1, COLDFRONT, 1, POWDERSNOW, 4, GALEHOLD, 8, MIST, 11, HAIL, 15, ICYWIND, 18, AIRCUTTER, 21, HYPOTHERMIA, 24, DEFOG, 27, EROSION, 30, NUMBINGWIND, 33, STARDUSTREVERIE, 36, TORNADO, 39, FROSTBREATH, 42, ICEBEAM, 45, AERIALPULSE, 48, WEATHERBALL, 52, BOREASBREATH, 56, TAILWIND, 60, BLIZZARD, | Z9: =VLOOKUP($A9,'Moves Species'!$A:$E,4,FALSE) -> ACIDRAIN, AERIALACE, AERIALPULSE, AIRSLASH, AMBUSH, ASTRALWIND, ATTRACT, BLIZZARD, BONECHILL, BRINE, CALMMIND, CHARGEBEAM, CHILLINGTOUCH, CLEARSMOG, DAZZLINGGLEAM, DEFOG, DRAGONGALE, DUSTDEVILS, ECHOEDVOICE, FLUXWAVE, FROSTBITE, GENESIS, GOSSIP, HAIL, HAZE, HIDDENPOWER, HURRICANE, HYPERVOICE, HYPOTHERMIA, ICEBEAM, ICEFANG, ICEHAMMER, ICEPUNCH, ICICLESPEAR, ICICLESTRIKE, ICYWIND, LIQUIDATION, MIRRORSHOT, MIST, MOONBLAST, MYSTICPULSE, NASTYPLOT, NEBULASTRIKE, NUMBINGWIND, OCEANWRATH, PIXIEDUST, PROTECT, QUICKGUARD, RAINDANCE, RAYOFLIGHT, REST, RETURN, SCALD, SIGNALBEAM, SLEEPTALK, SOAK, STRANGESTEAM, SWITCHEROO, TAILWIND, TEMPESTFLARE, TERRAINPULSE, TORNADO, TOXIC, TURBULENCE, WAIL, WATERPULSE, WEATHERBALL, WHIRLPOOL, WISH, | AA9: =VLOOKUP($A9,'Moves Species'!$A:$E,5,FALSE) -> 0
A10: =A9+1 -> 9 | B10: [DODUO] | C10: Doduo | D10: ='BST Extract'!J10 -> COSMIC | E10: ='BST Extract'!K10 -> FLYING | F10: =D10&","&E10 -> COSMIC,FLYING | G10: ='BST Extract'!C10 -> 60 | H10: ='BST Extract'!D10 -> 35 | I10: ='BST Extract'!E10 -> 35 | J10: ='BST Extract'!F10 -> 75 | K10: ='BST Extract'!G10 -> 75 | L10: ='BST Extract'!H10 -> 60 | M10: ='BST Extract'!I10 -> 340 | N10: SPEED | O10: 1 | T10: =N10&","&O10&","&P10&","&Q10&","&R10&","&S10 -> SPEED,1,,,, | U10: ='Ability Extract'!C10 -> EARLYBIRD | V10: ='Ability Extract'!D10 -> COMPETITIVE | W10: ='Ability Extract'!E10 -> DISHEARTEN | X10: ='Ability Extract'!F10 -> EARLYBIRD,COMPETITIVE,DISHEARTEN | Y10: =VLOOKUP($A10,'Moves Species'!$A:$E,3,FALSE) -> 1, RADIATION, 1, STARDUST, 4, GUST, 7, CONFUSION, 10, SWIFT, 13, BLACKOUT, 16, TURBULENCE, 19, STARFALL, 23, HYPNOSIS, 26, PSYBEAM, 29, AIRSLASH, 33, COSMICPOWER, 36, TWINSTARS, 39, PSYBLAST, 42, AERIALPULSE, 45, MOONLIGHT, 48, MOONBLAST, 52, ARCANEENERGY, 56, TEMPESTFLARE, 60, METEORBEAM, | Z10: =VLOOKUP($A10,'Moves Species'!$A:$E,4,FALSE) -> AERIALACE, AERIALPULSE, AIRSLASH, ANTIMATTER, ARCANEENERGY, ASTEROIDBELT, ASTRALWIND, ATTRACT, AURASPHERE, BATTLEOFWITS, CALMMIND, CHIDORI, COACHING, COSMICAVATAR, COSMICPOWER, COVET, DARKPULSE, DAZZLINGGLEAM, DEFOG, DRAGONGALE, DRILLPECK, DUALWINGBEAT, ECLIPSENOVA, ENDERSHOCK, EXPANDINGFORCE, FABLEDRUSH, FEATHERDANCE, FLUXWAVE, FOCUSBLAST, GAMMARAY, GHASTLYFLOOD, GOSSIP, HEX, HEXBOLT, HIDDENPOWER, HYPERVOICE, KAMEHAMEHA, KNOCKOFF, LIGHTSCREEN, LOVEBURST, METEORBEAM, MINDMELD, MIRRORSHOT, MIXEDWAVES, MOONBLAST, MOONSTONERAY, MYSTICPULSE, NASTYPLOT, NEBULASTRIKE, PHOBIA, PIXIEDUST, PROTECT, PSYCHIC, PSYCHICTERRAIN, PURGE, REFLECT, REST, RETURN, ROUND, SAFEGUARD, SATELLITERAY, SHADOWBALL, SIGNALBEAM, SLASH, SLEEPTALK, SOLARECLIPSE, SOULRIP, STARDUSTREVERIE, STELLARRUSH, STRANGESTEAM, SUBSTITUTE, SWIFT, TAILWIND, TEMPESTFLARE, TOXIC, TRIATTACK, TURBULENCE, UMBRALWAVE, WISH, WONDERROOM, ZENHEADBUTT, | AA10: =VLOOKUP($A10,'Moves Species'!$A:$E,5,FALSE) -> FEATHERDANCE, REFLECT, LIGHTSCREEN, STOREDPOWER, BRAVEBIRD, TAILWIND, WISH, METEORSHOWER, FUTURESIGHT, | AB10: DODRIO | AC10: Item | AD10: MOONSTONE
A11: =A10+1 -> 10 | B11: [DODRIO] | C11: Dodrio | D11: ='BST Extract'!J11 -> COSMIC | E11: ='BST Extract'!K11 -> FLYING | F11: =D11&","&E11 -> COSMIC,FLYING | G11: ='BST Extract'!C11 -> 80 | H11: ='BST Extract'!D11 -> 60 | I11: ='BST Extract'!E11 -> 60 | J11: ='BST Extract'!F11 -> 105 | K11: ='BST Extract'!G11 -> 100 | L11: ='BST Extract'!H11 -> 85 | M11: ='BST Extract'!I11 -> 490 | N11: SPEED | O11: 2 | T11: =N11&","&O11&","&P11&","&Q11&","&R11&","&S11 -> SPEED,2,,,, | U11: ='Ability Extract'!C11 -> EARLYBIRD | V11: ='Ability Extract'!D11 -> COMPETITIVE | W11: ='Ability Extract'!E11 -> DISHEARTEN | X11: ='Ability Extract'!F11 -> EARLYBIRD,COMPETITIVE,DISHEARTEN | Y11: =VLOOKUP($A11,'Moves Species'!$A:$E,3,FALSE) -> 0, STARSALIGNED, 1, STARSALIGNED, 1, TRIATTACK, 1, RADIATION, 1, STARDUST, 4, GUST, 7, CONFUSION, 10, SWIFT, 13, BLACKOUT, 16, TURBULENCE, 19, STARFALL, 23, HYPNOSIS, 26, PSYBEAM, 29, AIRSLASH, 33, COSMICPOWER, 36, TWINSTARS, 39, PSYBLAST, 42, AERIALPULSE, 45, MOONLIGHT, 48, MOONBLAST, 52, ARCANEENERGY, 56, TEMPESTFLARE, 60, METEORBEAM, | Z11: =VLOOKUP($A11,'Moves Species'!$A:$E,4,FALSE) -> AERIALACE, AERIALPULSE, AIRSLASH, ANTIMATTER, ARCANEENERGY, ASTEROIDBELT, ASTRALWIND, ATTRACT, AURASPHERE, BATTLEOFWITS, CALMMIND, CHIDORI, COACHING, COSMICAVATAR, COSMICPOWER, COVET, DARKPULSE, DAZZLINGGLEAM, DEFOG, DRAGONGALE, DRILLPECK, DUALWINGBEAT, ECLIPSENOVA, ENDERSHOCK, EXPANDINGFORCE, FABLEDRUSH, FEATHERDANCE, FLUXWAVE, FOCUSBLAST, GAMMARAY, GHASTLYFLOOD, GOSSIP, HEX, HEXBOLT, HIDDENPOWER, HYPERVOICE, KAMEHAMEHA, KNOCKOFF, LIGHTSCREEN, LOVEBURST, METEORBEAM, MINDMELD, MIRRORSHOT, MIXEDWAVES, MOONBLAST, MOONSTONERAY, MYSTICPULSE, NASTYPLOT, NEBULASTRIKE, PHOBIA, PIXIEDUST, PROTECT, PSYCHIC, PSYCHICTERRAIN, PURGE, REFLECT, REST, RETURN, ROUND, SAFEGUARD, SATELLITERAY, SHADOWBALL, SIGNALBEAM, SLASH, SLEEPTALK, SOLARECLIPSE, SOULRIP, STARDUSTREVERIE, STELLARRUSH, STRANGESTEAM, SUBSTITUTE, SWIFT, TAILWIND, TEMPESTFLARE, TOXIC, TRIATTACK, TURBULENCE, UMBRALWAVE, WISH, WONDERROOM, ZENHEADBUTT, | AA11: =VLOOKUP($A11,'Moves Species'!$A:$E,5,FALSE) -> 0
A12: =A11+1 -> 11 | B12: [EKANS] | C12: Ekans | D12: ='BST Extract'!J12 -> GROUND | E12: ='BST Extract'!K12 -> POISON | F12: =D12&","&E12 -> GROUND,POISON | G12: ='BST Extract'!C12 -> 40 | H12: ='BST Extract'!D12 -> 70 | I12: ='BST Extract'!E12 -> 44 | J12: ='BST Extract'!F12 -> 60 | K12: ='BST Extract'!G12 -> 40 | L12: ='BST Extract'!H12 -> 54 | M12: ='BST Extract'!I12 -> 308 | N12: ATTACK | O12: 1 | T12: =N12&","&O12&","&P12&","&Q12&","&R12&","&S12 -> ATTACK,1,,,, | U12: ='Ability Extract'!C12 -> CORROSION | V12: ='Ability Extract'!D12 -> SANDSPIT | W12: ='Ability Extract'!E12 -> LEECHINGFANGS | X12: ='Ability Extract'!F12 -> CORROSION,SANDSPIT,LEECHINGFANGS | Y12: =VLOOKUP($A12,'Moves Species'!$A:$E,3,FALSE) -> 1, WRAP, 1, LEER, 1, SANDJET, 4, POISONSTING, 8, BITE, 11, STEAMROLLER, 14, TOXICTHREAD, 17, POISONFANG, 20, BULLDOZE, 23, HYPNOSIS, 26, POISONTAIL, 29, DIG, 32, VENOMDRAIN, 35, CRUNCH, 38, LEECHLIFE, 41, NEUROTOXIN, 44, THOUSANDWAVES, 47, TOXIC, 50, COIL, 53, PLAGUE, 56, CONTINENTALRIFT, 60, GUNKSHOT, | Z12: =VLOOKUP($A12,'Moves Species'!$A:$E,4,FALSE) -> ALLERGY, AMBUSH, ANCIENTGLARE, ATTRACT, BULLDOZE, BULLETSEED, CAUSTICACID, CLEARSMOG, CONFUSERAY, COUPDEGRACE, COVET, CRUELWHIP, CRUNCH, DARKPULSE, DEFENDORDER, DRAGONBLOOD, DRAGONHAMMER, DUNEBLAST, DUSTDEVILS, EARTHENLANCE, EARTHPOWER, EARTHQUAKE, ENDERSHOCK, EXECUTION, FALSESWIPE, FIREFANG, FURYCUTTER, GAIAPULSE, GOBLINSTRIKE, GOSSIP, HIDDENPOWER, ICEFANG, KNOCKOFF, LASHOUT, LEECHLIFE, MIASMA, MINDDRAIN, MUDSHACKLES, MUDSLIDE, NASTYPLOT, OBSIDIANSHARDS, OUTRAGE, PERCUSSIONBLAST, PLAYROUGH, POISONFANG, POISONJAB, POWERWHIP, PROTECT, PSYCHICFANGS, QUICKSAND, REST, RETURN, ROCKBLAST, ROCKSLIDE, ROCKTOMB, ROUND, SANDSTORM, SANDTOMB, SCORCHINGSANDS, SEISMICCHANT, SLEEPTALK, SLUDGEBOMB, SLUDGEWAVE, SONICBLAST, SPIKES, STEALTHROCK, STONEEDGE, SUNNYDAY, SWITCHEROO, SWORDSDANCE, TAUNT, TERRAINPULSE, THUNDERFANG, TOXIC, TOXICSPIKES, VENDETTA, VENOMDRAIN, VITALITYDRAIN, WEAKSPOT, WORKUP, ZENHEADBUTT, | AA12: =VLOOKUP($A12,'Moves Species'!$A:$E,5,FALSE) -> SWORDSDANCE, DRAGONTAIL, NAGASKIN, KNOCKOFF, CLANGINGSCALES, QUICKSAND, VENOMDRENCH, SCREECH, DRAGONGNAW, SCALESTORM, | AB12: ARBOK | AC12: Level | AD12: 30
A13: =A12+1 -> 12 | B13: [ARBOK] | C13: Arbok | D13: ='BST Extract'!J13 -> GROUND | E13: ='BST Extract'!K13 -> POISON | F13: =D13&","&E13 -> GROUND,POISON | G13: ='BST Extract'!C13 -> 55 | H13: ='BST Extract'!D13 -> 110 | I13: ='BST Extract'!E13 -> 69 | J13: ='BST Extract'!F13 -> 100 | K13: ='BST Extract'!G13 -> 65 | L13: ='BST Extract'!H13 -> 69 | M13: ='BST Extract'!I13 -> 468 | N13: ATTACK | O13: 2 | T13: =N13&","&O13&","&P13&","&Q13&","&R13&","&S13 -> ATTACK,2,,,, | U13: ='Ability Extract'!C13 -> CORROSION | V13: ='Ability Extract'!D13 -> SANDSPIT | W13: ='Ability Extract'!E13 -> LEECHINGFANGS | X13: ='Ability Extract'!F13 -> CORROSION,SANDSPIT,LEECHINGFANGS | Y13: =VLOOKUP($A13,'Moves Species'!$A:$E,3,FALSE) -> 0, RATTLETAIL, 1, RATTLETAIL, 1, WRAP, 1, LEER, 1, SANDJET, 4, POISONSTING, 8, BITE, 11, STEAMROLLER, 14, TOXICTHREAD, 17, POISONFANG, 20, BULLDOZE, 23, HYPNOSIS, 26, POISONTAIL, 29, DIG, 32, VENOMDRAIN, 35, CRUNCH, 38, LEECHLIFE, 41, NEUROTOXIN, 44, THOUSANDWAVES, 47, TOXIC, 50, COIL, 53, PLAGUE, 56, CONTINENTALRIFT, 60, GUNKSHOT, | Z13: =VLOOKUP($A13,'Moves Species'!$A:$E,4,FALSE) -> ALLERGY, AMBUSH, ANCIENTGLARE, ATTRACT, BULLDOZE, BULLETSEED, CAUSTICACID, CLEARSMOG, CONFUSERAY, COUPDEGRACE, COVET, CRUELWHIP, CRUNCH, DARKPULSE, DEFENDORDER, DRAGONBLOOD, DRAGONHAMMER, DUNEBLAST, DUSTDEVILS, EARTHENLANCE, EARTHPOWER, EARTHQUAKE, ENDERSHOCK, EXECUTION, FALSESWIPE, FIREFANG, FURYCUTTER, GAIAPULSE, GOBLINSTRIKE, GOSSIP, HIDDENPOWER, ICEFANG, KNOCKOFF, LASHOUT, LEECHLIFE, MIASMA, MINDDRAIN, MUDSHACKLES, MUDSLIDE, NASTYPLOT, OBSIDIANSHARDS, OUTRAGE, PERCUSSIONBLAST, PLAYROUGH, POISONFANG, POISONJAB, POWERWHIP, PROTECT, PSYCHICFANGS, QUICKSAND, REST, RETURN, ROCKBLAST, ROCKSLIDE, ROCKTOMB, ROUND, SANDSTORM, SANDTOMB, SCORCHINGSANDS, SEISMICCHANT, SLEEPTALK, SLUDGEBOMB, SLUDGEWAVE, SONICBLAST, SPIKES, STEALTHROCK, STONEEDGE, SUNNYDAY, SWITCHEROO, SWORDSDANCE, TAUNT, TERRAINPULSE, THUNDERFANG, TOXIC, TOXICSPIKES, VENDETTA, VENOMDRAIN, VITALITYDRAIN, WEAKSPOT, WORKUP, ZENHEADBUTT, | AA13: =VLOOKUP($A13,'Moves Species'!$A:$E,5,FALSE) -> 0
A14: =A13+1 -> 13 | B14: [STARYU] | C14: Staryu | D14: ='BST Extract'!J14 -> COSMIC | E14: ='BST Extract'!K14 -> ROCK | F14: =D14&","&E14 -> COSMIC,ROCK | G14: ='BST Extract'!C14 -> 45 | H14: ='BST Extract'!D14 -> 30 | I14: ='BST Extract'!E14 -> 55 | J14: ='BST Extract'!F14 -> 70 | K14: ='BST Extract'!G14 -> 85 | L14: ='BST Extract'!H14 -> 55 | M14: ='BST Extract'!I14 -> 340 | N14: SPECIAL_ATTACK | O14: 1 | T14: =N14&","&O14&","&P14&","&Q14&","&R14&","&S14 -> SPECIAL_ATTACK,1,,,, | U14: ='Ability Extract'!C14 -> SYNCHRONIZE | V14: ='Ability Extract'!D14 -> FILTER | W14: ='Ability Extract'!E14 -> FORTIFICATION | X14: ='Ability Extract'!F14 -> SYNCHRONIZE,FILTER,FORTIFICATION | Y14: =VLOOKUP($A14,'Moves Species'!$A:$E,3,FALSE) -> 1, HARDEN, 1, VACUUMWAVE, 1, CRYSTALDUST, 5, SWIFT, 9, INNERVATE, 12, MINERALWAVE, 15, STARFALL, 18, FLASH, 21, ANCIENTPOWER, 24, SUPERNOVA, 27, SIGNALBEAM, 30, DIAMONDSTORM, 33, GLISTEN, 36, STARDUSTREVERIE, 39, COSMICPOWER, 42, BEJEWELED, 46, MOONBLAST, 50, ASTEROIDBELT, 54, MOONSTONERAY, 58, CORECOLLAPSE, 62, METEORBEAM, | Z14: =VLOOKUP($A14,'Moves Species'!$A:$E,4,FALSE) -> ANTIMATTER, ARCANEENERGY, ASTEROIDBELT, ASTRALWIND, AURASPHERE, BATTLEOFWITS, BEJEWELED, BOULDERCRUSH, CALMMIND, CATAPULT, CHARGEBEAM, CLEANSE, COSMICAVATAR, COSMICPOWER, CRYSTALLINEBEAM, CRYSTALSHOWER, DARKPULSE, DAZZLINGGLEAM, DUNEBLAST, DUSTDEVILS, EARTHENLANCE, EARTHPOWER, ECLIPSENOVA, ENDERSHOCK, ENERGYBALL, EXPANDINGFORCE, FLUXWAVE, GAIAPULSE, GAMMARAY, GEOMANCY, GLISTEN, GOLDRUSH, HAZE, HEALBELL, HEXBOLT, HIDDENPOWER, IRONDEFENSE, IRONHEAD, IRONIMPACT, KAMEHAMEHA, LIGHTSCREEN, MAGICROOM, MAGNETICCANNON, METEORBEAM, METEORDRIVE, MINDMELD, MINERALWAVE, MIRRORSHOT, MISSILESHOT, MISTYTERRAIN, MIXEDWAVES, MOONBLAST, MOONSTONERAY, MUDSHACKLES, MUDSLIDE, MYSTICPULSE, NASTYPLOT, NEBULASTRIKE, OBSIDIANSHARDS, PIXIEDUST, POWERGEM, PROTECT, PSYCHIC, PSYCHICTERRAIN, PURGE, QUICKSAND, RADIANTLANCE, RAYOFLIGHT, REFLECT, REST, RETURN, SAFEGUARD, SATELLITERAY, SEISMICCHANT, SIGNALBEAM, SLEEPTALK, STARDUSTREVERIE, STELLARRUSH, STRANGESTEAM, SUBSTITUTE, SWIFT, TERRAINPULSE, THUNDER, THUNDERBOLT, THUNDERWAVE, TOXIC, TRIATTACK, VOLTSWITCH, WILDCHARGE, WISH, | AA14: =VLOOKUP($A14,'Moves Species'!$A:$E,5,FALSE) -> 0 | AB14: STARMIE | AC14: Item | AD14: GEMSTONE
A15: =A14+1 -> 14 | B15: [STARMIE] | C15: Starmie | D15: ='BST Extract'!J15 -> COSMIC | E15: ='BST Extract'!K15 -> ROCK | F15: =D15&","&E15 -> COSMIC,ROCK | G15: ='BST Extract'!C15 -> 75 | H15: ='BST Extract'!D15 -> 75 | I15: ='BST Extract'!E15 -> 80 | J15: ='BST Extract'!F15 -> 100 | K15: ='BST Extract'!G15 -> 110 | L15: ='BST Extract'!H15 -> 80 | M15: ='BST Extract'!I15 -> 520 | N15: SPECIAL_ATTACK | O15: 2 | T15: =N15&","&O15&","&P15&","&Q15&","&R15&","&S15 -> SPECIAL_ATTACK,2,,,, | U15: ='Ability Extract'!C15 -> SYNCHRONIZE | V15: ='Ability Extract'!D15 -> FILTER | W15: ='Ability Extract'!E15 -> FORTIFICATION | X15: ='Ability Extract'!F15 -> SYNCHRONIZE,FILTER,FORTIFICATION | Y15: =VLOOKUP($A15,'Moves Species'!$A:$E,3,FALSE) -> 0, TWINSTARS, 1, TWINSTARS, 1, HEALINGWISH, 1, MOONLIGHT, 1, HARDEN, 1, VACUUMWAVE, 1, CRYSTALDUST, 5, SWIFT, 9, INNERVATE, 12, MINERALWAVE, 15, STARFALL, 18, FLASH, 21, ANCIENTPOWER, 24, SUPERNOVA, 27, SIGNALBEAM, 30, DIAMONDSTORM, 33, GLISTEN, 36, STARDUSTREVERIE, 39, COSMICPOWER, 42, BEJEWELED, 46, MOONBLAST, 50, ASTEROIDBELT, 54, MOONSTONERAY, 58, CORECOLLAPSE, 62, METEORBEAM, | Z15: =VLOOKUP($A15,'Moves Species'!$A:$E,4,FALSE) -> ANTIMATTER, ARCANEENERGY, ASTEROIDBELT, ASTRALWIND, AURASPHERE, BATTLEOFWITS, BEJEWELED, BOULDERCRUSH, CALMMIND, CATAPULT, CHARGEBEAM, CLEANSE, COSMICAVATAR, COSMICPOWER, CRYSTALLINEBEAM, CRYSTALSHOWER, DARKPULSE, DAZZLINGGLEAM, DUNEBLAST, DUSTDEVILS, EARTHENLANCE, EARTHPOWER, ECLIPSENOVA, ENDERSHOCK, ENERGYBALL, EXPANDINGFORCE, FLUXWAVE, GAIAPULSE, GAMMARAY, GEOMANCY, GLISTEN, GOLDRUSH, HAZE, HEALBELL, HEXBOLT, HIDDENPOWER, IRONDEFENSE, IRONHEAD, IRONIMPACT, KAMEHAMEHA, LIGHTSCREEN, MAGICROOM, MAGNETICCANNON, METEORBEAM, METEORDRIVE, MINDMELD, MINERALWAVE, MIRRORSHOT, MISSILESHOT, MISTYTERRAIN, MIXEDWAVES, MOONBLAST, MOONSTONERAY, MUDSHACKLES, MUDSLIDE, MYSTICPULSE, NASTYPLOT, NEBULASTRIKE, OBSIDIANSHARDS, PIXIEDUST, POWERGEM, PROTECT, PSYCHIC, PSYCHICTERRAIN, PURGE, QUICKSAND, RADIANTLANCE, RAYOFLIGHT, REFLECT, REST, RETURN, SAFEGUARD, SATELLITERAY, SEISMICCHANT, SIGNALBEAM, SLEEPTALK, STARDUSTREVERIE, STELLARRUSH, STRANGESTEAM, SUBSTITUTE, SWIFT, TERRAINPULSE, THUNDER, THUNDERBOLT, THUNDERWAVE, TOXIC, TRIATTACK, VOLTSWITCH, WILDCHARGE, WISH, | AA15: =VLOOKUP($A15,'Moves Species'!$A:$E,5,FALSE) -> 0
A16: =A15+1 -> 15 | B16: [ONIX] | C16: Onix | D16: ='BST Extract'!J16 -> ICE | E16: ='BST Extract'!K16 -> ROCK | F16: =D16&","&E16 -> ICE,ROCK | G16: ='BST Extract'!C16 -> 35 | H16: ='BST Extract'!D16 -> 85 | I16: ='BST Extract'!E16 -> 120 | J16: ='BST Extract'!F16 -> 70 | K16: ='BST Extract'!G16 -> 30 | L16: ='BST Extract'!H16 -> 45 | M16: ='BST Extract'!I16 -> 385 | N16: DEFENSE | O16: 1 | T16: =N16&","&O16&","&P16&","&Q16&","&R16&","&S16 -> DEFENSE,1,,,, | U16: ='Ability Extract'!C16 -> VENGEFUL | V16: ='Ability Extract'!D16 -> STURDY | W16: ='Ability Extract'!E16 -> SLUSHRUSH | X16: ='Ability Extract'!F16 -> VENGEFUL,STURDY,SLUSHRUSH | Y16: =VLOOKUP($A16,'Moves Species'!$A:$E,3,FALSE) -> 1, HARDEN, 1, TACKLE, 1, ROCKTHROW, 4, ICESHARD, 7, BIND, 10, ROCKPOLISH, 13, BOULDERHURL, 16, STEALTHROCK, 19, ICEFANG, 22, ROCKBLAST, 25, ICETOMB, 28, DIAMONDBLADE, 31, ROCKSLIDE, 34, ICICLECRASH, 37, CRUNCH, 40, SCREECH, 43, FROSTBITE, 46, STONEEDGE, 49, EARTHQUAKE, 52, COIL, 55, POLARSPEAR, 58, BOULDERCRUSH, 62, GLACIALLANCE, | Z16: =VLOOKUP($A16,'Moves Species'!$A:$E,4,FALSE) -> ANCIENTGLARE, ATTRACT, BEJEWELED, BODYPRESS, BODYSLAM, BOULDERCRUSH, BULKUP, BULLDOZE, CATAPULT, CHILLINGTOUCH, CLOSECOMBAT, CRUNCH, CRYSTALLINEBEAM, CRYSTALSHOWER, DARKPULSE, DRACOMETEOR, DRAGONBREATH, DRAGONDANCE, DRAGONHAMMER, DUNEBLAST, EARTHENLANCE, EARTHPOWER, EARTHQUAKE, ECHOEDVOICE, ENDERSHOCK, EXECUTION, FIREFANG, FOCUSBLAST, FROSTBITE, GAIAPULSE, GLISTEN, GOLDRUSH, HAIL, HIDDENPOWER, ICEBEAM, ICEFANG, ICEHAMMER, ICICLESPEAR, ICICLESTRIKE, ICYWIND, IRONDEFENSE, IRONHEAD, IRONIMPACT, KNOCKOFF, LASHOUT, MAGNETICCANNON, MEMENTO, METEORDRIVE, MINERALWAVE, MIRRORSHOT, MISSILESHOT, MOONBLAST, MOONSTONERAY, MUDSHACKLES, MUDSLIDE, NUMBINGWIND, OBSIDIANSHARDS, OUTRAGE, PLAYROUGH, POWERGEM, PROTECT, QUICKSAND, REST, RETURN, ROCKBLAST, ROCKSLIDE, ROCKTOMB, SANDSTORM, SANDTOMB, SEISMICCHANT, SLEEPTALK, SNARL, SONICBLAST, STEALTHROCK, STEELROLLER, STONEEDGE, SUPERPOWER, TAUNT, TERRAINPULSE, THUNDERFANG, TOXIC, UTURN, WAIL, WILDCHARGE, WORKUP, ZENHEADBUTT, | AA16: =VLOOKUP($A16,'Moves Species'!$A:$E,5,FALSE) -> AVALANCHE, ENDEAVOR, IRONHEAD, ZENHEADBUTT, ANCIENTPOWER, HEAVYSLAM, AURORAVEIL, BULLDOZE, ICICLESPEAR, UPROAR, CURSE, | AB16: STEELIX | AC16: Item | AD16: ICESTONE
A17: =A16+1 -> 16 | B17: [STEELIX] | C17: Steelix | D17: ='BST Extract'!J17 -> ICE | E17: ='BST Extract'!K17 -> ROCK | F17: =D17&","&E17 -> ICE,ROCK | G17: ='BST Extract'!C17 -> 75 | H17: ='BST Extract'!D17 -> 115 | I17: ='BST Extract'!E17 -> 140 | J17: ='BST Extract'!F17 -> 60 | K17: ='BST Extract'!G17 -> 55 | L17: ='BST Extract'!H17 -> 65 | M17: ='BST Extract'!I17 -> 510 | N17: DEFENSE | O17: 2 | T17: =N17&","&O17&","&P17&","&Q17&","&R17&","&S17 -> DEFENSE,2,,,, | U17: ='Ability Extract'!C17 -> VENGEFUL | V17: ='Ability Extract'!D17 -> STURDY | W17: ='Ability Extract'!E17 -> SLUSHRUSH | X17: ='Ability Extract'!F17 -> VENGEFUL,STURDY,SLUSHRUSH | Y17: =VLOOKUP($A17,'Moves Species'!$A:$E,3,FALSE) -> 0, WEARDOWN, 1, WEARDOWN, 1, HARDEN, 1, TACKLE, 1, ROCKTHROW, 4, ICESHARD, 7, BIND, 10, ROCKPOLISH, 13, BOULDERHURL, 16, STEALTHROCK, 19, ICEFANG, 22, ROCKBLAST, 25, ICETOMB, 28, DIAMONDBLADE, 31, ROCKSLIDE, 34, ICICLECRASH, 37, CRUNCH, 40, SCREECH, 43, FROSTBITE, 46, STONEEDGE, 49, EARTHQUAKE, 52, COIL, 55, POLARSPEAR, 58, BOULDERCRUSH, 62, GLACIALLANCE, | Z17: =VLOOKUP($A17,'Moves Species'!$A:$E,4,FALSE) -> ANCIENTGLARE, ATTRACT, BEJEWELED, BODYPRESS, BODYSLAM, BOULDERCRUSH, BULKUP, BULLDOZE, CATAPULT, CHILLINGTOUCH, CLOSECOMBAT, CRUNCH, CRYSTALLINEBEAM, CRYSTALSHOWER, DARKPULSE, DRACOMETEOR, DRAGONBREATH, DRAGONDANCE, DRAGONHAMMER, DUNEBLAST, EARTHENLANCE, EARTHPOWER, EARTHQUAKE, ECHOEDVOICE, ENDERSHOCK, EXECUTION, FIREFANG, FOCUSBLAST, FROSTBITE, GAIAPULSE, GLISTEN, GOLDRUSH, HAIL, HIDDENPOWER, ICEBEAM, ICEFANG, ICEHAMMER, ICICLESPEAR, ICICLESTRIKE, ICYWIND, IRONDEFENSE, IRONHEAD, IRONIMPACT, KNOCKOFF, LASHOUT, MAGNETICCANNON, MEMENTO, METEORDRIVE, MINERALWAVE, MIRRORSHOT, MISSILESHOT, MOONBLAST, MOONSTONERAY, MUDSHACKLES, MUDSLIDE, NUMBINGWIND, OBSIDIANSHARDS, OUTRAGE, PLAYROUGH, POWERGEM, PROTECT, QUICKSAND, REST, RETURN, ROCKBLAST, ROCKSLIDE, ROCKTOMB, SANDSTORM, SANDTOMB, SEISMICCHANT, SLEEPTALK, SNARL, SONICBLAST, STEALTHROCK, STEELROLLER, STONEEDGE, SUPERPOWER, TAUNT, TERRAINPULSE, THUNDERFANG, TOXIC, UTURN, WAIL, WILDCHARGE, WORKUP, ZENHEADBUTT, | AA17: =VLOOKUP($A17,'Moves Species'!$A:$E,5,FALSE) -> 0
A18: =A17+1 -> 17 | B18: [SLUGMA] | C18: Slugma | D18: ='BST Extract'!J18 -> POISON | E18: ='BST Extract'!K18 -> 0 | F18: =D18&","&E18 -> POISON,0 | G18: ='BST Extract'!C18 -> 55 | H18: ='BST Extract'!D18 -> 50 | I18: ='BST Extract'!E18 -> 45 | J18: ='BST Extract'!F18 -> 20 | K18: ='BST Extract'!G18 -> 70 | L18: ='BST Extract'!H18 -> 65 | M18: ='BST Extract'!I18 -> 305 | N18: SPECIAL_ATTACK | O18: 1 | T18: =N18&","&O18&","&P18&","&Q18&","&R18&","&S18 -> SPECIAL_ATTACK,1,,,, | U18: ='Ability Extract'!C18 -> UNAWARE | V18: ='Ability Extract'!D18 -> LIQUIDOOZE | W18: ='Ability Extract'!E18 -> CORROSION | X18: ='Ability Extract'!F18 -> UNAWARE,LIQUIDOOZE,CORROSION | Y18: =VLOOKUP($A18,'Moves Species'!$A:$E,3,FALSE) -> 1, HARDEN, 1, DISABLE, 1, ACID, 4, QUICKSILVER, 7, POISONGAS, 10, SIPHON, 13, GASTROACID, 16, SLUDGE, 19, DOUBLETEAM, 22, SHRAPNEL, 25, CORRODE, 28, HAZE, 31, STOCKPILE, 31, SWALLOW, 31, SPITUP, 34, COBALTRAY, 37, BLIGHT, 40, BANEFULBUNKER, 43, SLUDGEBOMB, 46, PLASMAFORGE, 49, RECOVER, 52, CAUSTICACID, 57, STEELBEAM, 62, SHELLSMASH, | Z18: =VLOOKUP($A18,'Moves Species'!$A:$E,4,FALSE) -> ACIDRAIN, ALLERGY, AMBUSH, ATTRACT, BATTERYACID, BODYSLAM, BRINE, BULLETSEED, CATAPULT, CAUSTICACID, CLEARSMOG, CONCOCTION, CONFUSERAY, CORROSIVEGAS, DARKPULSE, DEFENDORDER, DUNEBLAST, EARTHPOWER, ENERGYBALL, FIREBLAST, FLAMECHARGE, FLAMETHROWER, FLUXWAVE, GAMMARAY, GASTROACID, GEOMANCY, GLISTEN, GUNKSHOT, HAZE, HEATWAVE, HIDDENPOWER, INCINERATE, IRONIMPACT, IRONTEMPEST, KNOCKOFF, MAGNETICCANNON, MIASMA, MINDDRAIN, MISSILESHOT, NASTYPLOT, PHOBIA, POISONJAB, PROTECT, QUICKSAND, REFURBISH, REST, RETURN, SATELLITERAY, SHADOWBALL, SLEEPTALK, SLUDGEBOMB, SLUDGEWAVE, STRANGESTEAM, SUBSTITUTE, SWARMATTACK, SYNTHESIS, TERRAINPULSE, TOXIC, TURBULENCE, UMBRALWAVE, UTURN, VENDETTA, VENOMDRAIN, VITALITYDRAIN, WAIL, WORKUP, | AA18: =VLOOKUP($A18,'Moves Species'!$A:$E,5,FALSE) -> DARKPULSE, ACIDARMOR, CURSE, AMNESIA, CLEARSMOG, MEMENTO, VENOMDRENCH, VILEFUMES, MAGNETICCANNON, | AB18: MAGCARGO | AC18: Level | AD18: 33
A19: =A18+1 -> 18 | B19: [MAGCARGO] | C19: Magcargo | D19: ='BST Extract'!J19 -> POISON | E19: ='BST Extract'!K19 -> STEEL | F19: =D19&","&E19 -> POISON,STEEL | G19: ='BST Extract'!C19 -> 90 | H19: ='BST Extract'!D19 -> 60 | I19: ='BST Extract'!E19 -> 90 | J19: ='BST Extract'!F19 -> 30 | K19: ='BST Extract'!G19 -> 110 | L19: ='BST Extract'!H19 -> 90 | M19: ='BST Extract'!I19 -> 470 | N19: DEFENSE | O19: 2 | T19: =N19&","&O19&","&P19&","&Q19&","&R19&","&S19 -> DEFENSE,2,,,, | U19: ='Ability Extract'!C19 -> UNAWARE | V19: ='Ability Extract'!D19 -> LIQUIDOOZE | W19: ='Ability Extract'!E19 -> CORROSION | X19: ='Ability Extract'!F19 -> UNAWARE,LIQUIDOOZE,CORROSION | Y19: =VLOOKUP($A19,'Moves Species'!$A:$E,3,FALSE) -> 0, TOXIC, 1, TOXIC, 1, HARDEN, 1, DISABLE, 1, ACID, 4, QUICKSILVER, 7, POISONGAS, 10, SIPHON, 13, GASTROACID, 16, SLUDGE, 19, DOUBLETEAM, 22, SHRAPNEL, 25, CORRODE, 28, HAZE, 31, STOCKPILE, 31, SWALLOW, 31, SPITUP, 34, COBALTRAY, 37, BLIGHT, 40, BANEFULBUNKER, 43, SLUDGEBOMB, 46, PLASMAFORGE, 49, RECOVER, 52, CAUSTICACID, 57, STEELBEAM, 62, SHELLSMASH, | Z19: =VLOOKUP($A19,'Moves Species'!$A:$E,4,FALSE) -> ACIDRAIN, ALLERGY, AMBUSH, ATTRACT, BATTERYACID, BODYSLAM, BRINE, BULLETSEED, CATAPULT, CAUSTICACID, CLEARSMOG, CONCOCTION, CONFUSERAY, CORROSIVEGAS, DARKPULSE, DEFENDORDER, DUNEBLAST, EARTHPOWER, ENERGYBALL, FIREBLAST, FLAMECHARGE, FLAMETHROWER, FLUXWAVE, GAMMARAY, GASTROACID, GEOMANCY, GLISTEN, GUNKSHOT, HAZE, HEATWAVE, HIDDENPOWER, INCINERATE, IRONIMPACT, IRONTEMPEST, KNOCKOFF, MAGNETICCANNON, MIASMA, MINDDRAIN, MISSILESHOT, NASTYPLOT, PHOBIA, POISONJAB, PROTECT, QUICKSAND, REFURBISH, REST, RETURN, SATELLITERAY, SHADOWBALL, SLEEPTALK, SLUDGEBOMB, SLUDGEWAVE, STRANGESTEAM, SUBSTITUTE, SWARMATTACK, SYNTHESIS, TERRAINPULSE, TOXIC, TURBULENCE, UMBRALWAVE, UTURN, VENDETTA, VENOMDRAIN, VITALITYDRAIN, WAIL, WORKUP, | AA19: =VLOOKUP($A19,'Moves Species'!$A:$E,5,FALSE) -> 0
A20: =A19+1 -> 19 | B20: [WAILMER] | C20: Wailmer | D20: ='BST Extract'!J20 -> GHOST | E20: ='BST Extract'!K20 -> WATER | F20: =D20&","&E20 -> GHOST,WATER | G20: ='BST Extract'!C20 -> 95 | H20: ='BST Extract'!D20 -> 40 | I20: ='BST Extract'!E20 -> 55 | J20: ='BST Extract'!F20 -> 60 | K20: ='BST Extract'!G20 -> 50 | L20: ='BST Extract'!H20 -> 100 | M20: ='BST Extract'!I20 -> 400 | N20: HP | O20: 1 | T20: =N20&","&O20&","&P20&","&Q20&","&R20&","&S20 -> HP,1,,,, | U20: ='Ability Extract'!C20 -> ETHEREAL | V20: ='Ability Extract'!D20 -> INNARDSOUT | W20: ='Ability Extract'!E20 -> TORMENTED | X20: ='Ability Extract'!F20 -> ETHEREAL,INNARDSOUT,TORMENTED | Y20: =VLOOKUP($A20,'Moves Species'!$A:$E,3,FALSE) -> 1, DARKWHISPERS, 1, GOOSEBUMP, 1, WATERGUN, 4, DEFENSECURL, 8, SPITE, 11, SHIVER, 14, WATERPULSE, 17, ECHOEDVOICE, 20, OCTAZOOKA, 23, BONECHILL, 26, DIRGE, 29, SCREECH, 32, OCEANBLAST, 35, SHADOWBALL, 38, DARKPULSE, 41, SOUNDBARRIER, 44, TIDALWAVE, 47, SLUDGEWAVE, 50, GHASTLYFLOOD, 54, WATERSPOUT, 57, MEMENTO, 60, DESTINYBOND, | Z20: =VLOOKUP($A20,'Moves Species'!$A:$E,4,FALSE) -> AMBUSH, ATTRACT, AURASPHERE, BLIZZARD, BODYPRESS, BODYSLAM, BONECHILL, BOOMBURST, BOUNCE, BRINE, BULKUP, BULLDOZE, CATAPULT, CHILLINGTOUCH, CLEARSMOG, CONFUSERAY, CORROSIVEGAS, CRUNCH, CURSE, CURSEDTOUCH, DARKPULSE, DEFOG, ECHOEDVOICE, ECLIPSENOVA, EXPANDINGFORCE, FLIPTURN, FLUXWAVE, FOCUSBLAST, FROSTBITE, GAMMARAY, GASTROACID, GHASTLYFLOOD, GOSSIP, HAIL, HAZE, HEX, HIDDENPOWER, HYPERVOICE, ICEBEAM, ICEFANG, ICICLESPEAR, ICICLESTRIKE, ICYWIND, IRONHEAD, KNOCKOFF, MACABREDANCE, MEMENTO, MIASMA, MINDDRAIN, MIST, MOONBLAST, MYSTICPULSE, NASTYPLOT, NUMBINGWIND, OCEANWRATH, OVERFLOW, PERCUSSIONBLAST, PHANTOMFORCE, PHOBIA, PLAYROUGH, POISONJAB, PROTECT, RAINDANCE, REST, RETURN, ROUND, SAFEGUARD, SHADOWBALL, SLEEPTALK, SLUDGEBOMB, SLUDGEWAVE, SONICBLAST, SOULRIP, SOULSHIELD, SOUNDBARRIER, STEELROLLER, SUBMERGE, SUBSTITUTE, SWITCHEROO, TAUNT, TERRAINPULSE, THUNDERWAVE, TIDALWAVE, TOXIC, UMBRALWAVE, UTURN, VENDETTA, VENOMDRAIN, VITALITYDRAIN, WAIL, WATERPRESSURE, WATERPULSE, WEATHERBALL, WHIRLPOOL, WILLOWISP, WORKUP, ZENHEADBUTT, | AA20: =VLOOKUP($A20,'Moves Species'!$A:$E,5,FALSE) -> SLUDGEBOMB, BODYSLAM, CURSE, SOAK, THRASH, ZENHEADBUTT, PERISHSONG, HEX, NIGHTSHADE, ECTOPLASM, MIST, OMINOUSWIND, | AB20: WAILORD | AC20: Level | AD20: 40
A21: =A20+1 -> 20 | B21: [WAILORD] | C21: Wailord | D21: ='BST Extract'!J21 -> GHOST | E21: ='BST Extract'!K21 -> WATER | F21: =D21&","&E21 -> GHOST,WATER | G21: ='BST Extract'!C21 -> 120 | H21: ='BST Extract'!D21 -> 50 | I21: ='BST Extract'!E21 -> 65 | J21: ='BST Extract'!F21 -> 80 | K21: ='BST Extract'!G21 -> 80 | L21: ='BST Extract'!H21 -> 115 | M21: ='BST Extract'!I21 -> 510 | N21: HP | O21: 2 | T21: =N21&","&O21&","&P21&","&Q21&","&R21&","&S21 -> HP,2,,,, | U21: ='Ability Extract'!C21 -> ETHEREAL | V21: ='Ability Extract'!D21 -> INNARDSOUT | W21: ='Ability Extract'!E21 -> TORMENTED | X21: ='Ability Extract'!F21 -> ETHEREAL,INNARDSOUT,TORMENTED | Y21: =VLOOKUP($A21,'Moves Species'!$A:$E,3,FALSE) -> 0, ELEGY, 1, ELEGY, 1, DARKWHISPERS, 1, GOOSEBUMP, 1, WATERGUN, 4, DEFENSECURL, 8, SPITE, 11, SHIVER, 14, WATERPULSE, 17, ECHOEDVOICE, 20, OCTAZOOKA, 23, BONECHILL, 26, DIRGE, 29, SCREECH, 32, OCEANBLAST, 35, SHADOWBALL, 38, DARKPULSE, 41, SOUNDBARRIER, 44, TIDALWAVE, 47, SLUDGEWAVE, 50, GHASTLYFLOOD, 54, WATERSPOUT, 57, MEMENTO, 60, DESTINYBOND, | Z21: =VLOOKUP($A21,'Moves Species'!$A:$E,4,FALSE) -> AMBUSH, ATTRACT, AURASPHERE, BLIZZARD, BODYPRESS, BODYSLAM, BONECHILL, BOOMBURST, BOUNCE, BRINE, BULKUP, BULLDOZE, CATAPULT, CHILLINGTOUCH, CLEARSMOG, CONFUSERAY, CORROSIVEGAS, CRUNCH, CURSE, CURSEDTOUCH, DARKPULSE, DEFOG, ECHOEDVOICE, ECLIPSENOVA, EXPANDINGFORCE, FLIPTURN, FLUXWAVE, FOCUSBLAST, FROSTBITE, GAMMARAY, GASTROACID, GHASTLYFLOOD, GOSSIP, HAIL, HAZE, HEX, HIDDENPOWER, HYPERVOICE, ICEBEAM, ICEFANG, ICICLESPEAR, ICICLESTRIKE, ICYWIND, IRONHEAD, KNOCKOFF, MACABREDANCE, MEMENTO, MIASMA, MINDDRAIN, MIST, MOONBLAST, MYSTICPULSE, NASTYPLOT, NUMBINGWIND, OCEANWRATH, OVERFLOW, PERCUSSIONBLAST, PHANTOMFORCE, PHOBIA, PLAYROUGH, POISONJAB, PROTECT, RAINDANCE, REST, RETURN, ROUND, SAFEGUARD, SHADOWBALL, SLEEPTALK, SLUDGEBOMB, SLUDGEWAVE, SONICBLAST, SOULRIP, SOULSHIELD, SOUNDBARRIER, STEELROLLER, SUBMERGE, SUBSTITUTE, SWITCHEROO, TAUNT, TERRAINPULSE, THUNDERWAVE, TIDALWAVE, TOXIC, UMBRALWAVE, UTURN, VENDETTA, VENOMDRAIN, VITALITYDRAIN, WAIL, WATERPRESSURE, WATERPULSE, WEATHERBALL, WHIRLPOOL, WILLOWISP, WORKUP, ZENHEADBUTT, | AA21: =VLOOKUP($A21,'Moves Species'!$A:$E,5,FALSE) -> 0
A22: =A21+1 -> 21 | B22: [FLETCHLING] | C22: Fletchling | D22: ='BST Extract'!J22 -> ELECTRIC | E22: ='BST Extract'!K22 -> FLYING | F22: =D22&","&E22 -> ELECTRIC,FLYING | G22: ='BST Extract'!C22 -> 55 | H22: ='BST Extract'!D22 -> 50 | I22: ='BST Extract'!E22 -> 48 | J22: ='BST Extract'!F22 -> 62 | K22: ='BST Extract'!G22 -> 30 | L22: ='BST Extract'!H22 -> 33 | M22: ='BST Extract'!I22 -> 278 | N22: SPEED | O22: 1 | T22: =N22&","&O22&","&P22&","&Q22&","&R22&","&S22 -> SPEED,1,,,, | U22: ='Ability Extract'!C22 -> KEENEYE | V22: ='Ability Extract'!D22 -> GALVANIZE | W22: ='Ability Extract'!E22 -> GALEWINGS | X22: ='Ability Extract'!F22 -> KEENEYE,GALVANIZE,GALEWINGS | Y22: =VLOOKUP($A22,'Moves Species'!$A:$E,3,FALSE) -> 1, LEER, 1, STATICSHOCK, 4, PECK, 8, QUICKATTACK, 11, FEATHERDANCE, 14, SPARK, 17, WINGATTACK, 20, CHIPAWAY, 23, ROOST, 26, ARCINGBLOW, 29, STREAMRUSH, 32, SWEEPINGTALON, 35, BALLLIGHTNING, 38, BIRDOFPREY, 41, WILDCHARGE, 44, TAKEDOWN, 47, DRILLPECK, 50, TAILWIND, 53, BOLTBEAK, 56, BRAVEBIRD, 59, VOLTTACKLE, 62, DOUBLEEDGE, | Z22: =VLOOKUP($A22,'Moves Species'!$A:$E,4,FALSE) -> ACROBATICS, AERIALACE, AERIALPULSE, AIRSLASH, AMBUSH, ASTRALWIND, ATTRACT, BALLLIGHTNING, BOLTCRASH, BOUNCE, BRAVEBIRD, BULLETSEED, CHARGEBEAM, CLOSECOMBAT, COUPDEGRACE, COVET, DAZZLINGGLEAM, DEFOG, DIVINEPUNISHMENT, DRAGONGALE, DRILLPECK, DUALWINGBEAT, ECHOEDVOICE, ELECTRICTERRAIN, ELECTRONCRUSH, ENERGYSURGE, EXECUTION, FABLEDRUSH, FALSESWIPE, FEATHERDANCE, FLAMECHARGE, FLAREBLITZ, FLOCK, FLUTTER, GOLDENBULLET, GOLDRUSH, HIDDENPOWER, HURRICANE, KNOCKOFF, MIRRORSHOT, NASTYPLOT, PARABOLICCHARGE, PLAYROUGH, PROTECT, QUICKGUARD, RADIANTLANCE, RAYOFLIGHT, REST, RETURN, RISINGVOLTAGE, ROUND, SLEEPTALK, SONICBLAST, STEELWING, SUNNYDAY, SWORDSDANCE, TAILWIND, TEMPESTFLARE, TERRAINPULSE, THUNDER, THUNDERBOLT, THUNDERWAVE, TORNADO, TOXIC, TURBULENCE, VENDETTA, VOLTSWITCH, WEATHERBALL, WILDCHARGE, WORKUP, | AA22: =VLOOKUP($A22,'Moves Species'!$A:$E,5,FALSE) -> AEROBLAST, NIGHTSLASH, SHOOTINGSTAR, CUPIDSARROW, AGILITY, DEATHVORTEX, STALKPREY, PROTONCRASH, | AB22: FLETCHINDER | AC22: Level | AD22: 18
A23: =A22+1 -> 22 | B23: [FLETCHINDER] | C23: Fletchinder | D23: ='BST Extract'!J23 -> ELECTRIC | E23: ='BST Extract'!K23 -> FLYING | F23: =D23&","&E23 -> ELECTRIC,FLYING | G23: ='BST Extract'!C23 -> 72 | H23: ='BST Extract'!D23 -> 78 | I23: ='BST Extract'!E23 -> 55 | J23: ='BST Extract'!F23 -> 80 | K23: ='BST Extract'!G23 -> 45 | L23: ='BST Extract'!H23 -> 52 | M23: ='BST Extract'!I23 -> 382 | N23: SPEED | O23: 2 | T23: =N23&","&O23&","&P23&","&Q23&","&R23&","&S23 -> SPEED,2,,,, | U23: ='Ability Extract'!C23 -> KEENEYE | V23: ='Ability Extract'!D23 -> GALVANIZE | W23: ='Ability Extract'!E23 -> GALEWINGS | X23: ='Ability Extract'!F23 -> KEENEYE,GALVANIZE,GALEWINGS | Y23: =VLOOKUP($A23,'Moves Species'!$A:$E,3,FALSE) -> 1, LEER, 1, STATICSHOCK, 4, PECK, 8, QUICKATTACK, 11, FEATHERDANCE, 14, SPARK, 17, WINGATTACK, 20, CHIPAWAY, 23, ROOST, 26, ARCINGBLOW, 29, STREAMRUSH, 32, SWEEPINGTALON, 35, BALLLIGHTNING, 38, BIRDOFPREY, 41, WILDCHARGE, 44, TAKEDOWN, 47, DRILLPECK, 50, TAILWIND, 53, BOLTBEAK, 56, BRAVEBIRD, 59, VOLTTACKLE, 62, DOUBLEEDGE, | Z23: =VLOOKUP($A23,'Moves Species'!$A:$E,4,FALSE) -> ACROBATICS, AERIALACE, AERIALPULSE, AIRSLASH, AMBUSH, ASTRALWIND, ATTRACT, BALLLIGHTNING, BOLTCRASH, BOUNCE, BRAVEBIRD, BULLETSEED, CHARGEBEAM, CLOSECOMBAT, COUPDEGRACE, COVET, DAZZLINGGLEAM, DEFOG, DIVINEPUNISHMENT, DRAGONGALE, DRILLPECK, DUALWINGBEAT, ECHOEDVOICE, ELECTRICTERRAIN, ELECTRONCRUSH, ENERGYSURGE, EXECUTION, FABLEDRUSH, FALSESWIPE, FEATHERDANCE, FLAMECHARGE, FLAREBLITZ, FLOCK, FLUTTER, GOLDENBULLET, GOLDRUSH, HIDDENPOWER, HURRICANE, KNOCKOFF, MIRRORSHOT, NASTYPLOT, PARABOLICCHARGE, PLAYROUGH, PROTECT, QUICKGUARD, RADIANTLANCE, RAYOFLIGHT, REST, RETURN, RISINGVOLTAGE, ROUND, SLEEPTALK, SONICBLAST, STEELWING, SUNNYDAY, SWORDSDANCE, TAILWIND, TEMPESTFLARE, TERRAINPULSE, THUNDER, THUNDERBOLT, THUNDERWAVE, TORNADO, TOXIC, TURBULENCE, VENDETTA, VOLTSWITCH, WEATHERBALL, WILDCHARGE, WORKUP, | AA23: =VLOOKUP($A23,'Moves Species'!$A:$E,5,FALSE) -> 0 | AB23: TALONFLAME | AC23: Level | AD23: 37
A24: =A23+1 -> 23 | B24: [TALONFLAME] | C24: Talonflame | D24: ='BST Extract'!J24 -> ELECTRIC | E24: ='BST Extract'!K24 -> FLYING | F24: =D24&","&E24 -> ELECTRIC,FLYING | G24: ='BST Extract'!C24 -> 82 | H24: ='BST Extract'!D24 -> 90 | I24: ='BST Extract'!E24 -> 77 | J24: ='BST Extract'!F24 -> 126 | K24: ='BST Extract'!G24 -> 59 | L24: ='BST Extract'!H24 -> 65 | M24: ='BST Extract'!I24 -> 499 | N24: SPEED | O24: 3 | T24: =N24&","&O24&","&P24&","&Q24&","&R24&","&S24 -> SPEED,3,,,, | U24: ='Ability Extract'!C24 -> KEENEYE | V24: ='Ability Extract'!D24 -> GALVANIZE | W24: ='Ability Extract'!E24 -> GALEWINGS | X24: ='Ability Extract'!F24 -> KEENEYE,GALVANIZE,GALEWINGS | Y24: =VLOOKUP($A24,'Moves Species'!$A:$E,3,FALSE) -> 0, ELECTRIFY, 1, ELECTRIFY, 1, LEER, 1, STATICSHOCK, 4, PECK, 8, QUICKATTACK, 11, FEATHERDANCE, 14, SPARK, 17, WINGATTACK, 20, CHIPAWAY, 23, ROOST, 26, ARCINGBLOW, 29, STREAMRUSH, 32, SWEEPINGTALON, 35, BALLLIGHTNING, 38, BIRDOFPREY, 41, WILDCHARGE, 44, TAKEDOWN, 47, DRILLPECK, 50, TAILWIND, 53, BOLTBEAK, 56, BRAVEBIRD, 59, VOLTTACKLE, 62, DOUBLEEDGE, | Z24: =VLOOKUP($A24,'Moves Species'!$A:$E,4,FALSE) -> ACROBATICS, AERIALACE, AERIALPULSE, AIRSLASH, AMBUSH, ASTRALWIND, ATTRACT, BALLLIGHTNING, BOLTCRASH, BOUNCE, BRAVEBIRD, BULLETSEED, CHARGEBEAM, CLOSECOMBAT, COUPDEGRACE, COVET, DAZZLINGGLEAM, DEFOG, DIVINEPUNISHMENT, DRAGONGALE, DRILLPECK, DUALWINGBEAT, ECHOEDVOICE, ELECTRICTERRAIN, ELECTRONCRUSH, ENERGYSURGE, EXECUTION, FABLEDRUSH, FALSESWIPE, FEATHERDANCE, FLAMECHARGE, FLAREBLITZ, FLOCK, FLUTTER, GOLDENBULLET, GOLDRUSH, HIDDENPOWER, HURRICANE, KNOCKOFF, MIRRORSHOT, NASTYPLOT, PARABOLICCHARGE, PLAYROUGH, PROTECT, QUICKGUARD, RADIANTLANCE, RAYOFLIGHT, REST, RETURN, RISINGVOLTAGE, ROUND, SLEEPTALK, SONICBLAST, STEELWING, SUNNYDAY, SWORDSDANCE, TAILWIND, TEMPESTFLARE, TERRAINPULSE, THUNDER, THUNDERBOLT, THUNDERWAVE, TORNADO, TOXIC, TURBULENCE, VENDETTA, VOLTSWITCH, WEATHERBALL, WILDCHARGE, WORKUP, | AA24: =VLOOKUP($A24,'Moves Species'!$A:$E,5,FALSE) -> 0
A25: =A24+1 -> 24 | B25: [NATU] | C25: Natu | D25: ='BST Extract'!J25 -> STEEL | E25: ='BST Extract'!K25 -> ELECTRIC | F25: =D25&","&E25 -> STEEL,ELECTRIC | G25: ='BST Extract'!C25 -> 50 | H25: ='BST Extract'!D25 -> 70 | I25: ='BST Extract'!E25 -> 40 | J25: ='BST Extract'!F25 -> 70 | K25: ='BST Extract'!G25 -> 70 | L25: ='BST Extract'!H25 -> 45 | M25: ='BST Extract'!I25 -> 345 | N25: SPECIAL_ATTACK | O25: 1 | T25: =N25&","&O25&","&P25&","&Q25&","&R25&","&S25 -> SPECIAL_ATTACK,1,,,, | U25: ='Ability Extract'!C25 -> BATTERY | V25: ='Ability Extract'!D25 -> DOWNLOAD | W25: ='Ability Extract'!E25 -> MAGICBOUNCE | X25: ='Ability Extract'!F25 -> BATTERY,DOWNLOAD,MAGICBOUNCE | Y25: =VLOOKUP($A25,'Moves Species'!$A:$E,3,FALSE) -> 1, PECK, 1, LEER, 1, NUZZLE, 4, MISSILESHOT, 6, THUNDERSHOCK, 8, GEARUP, 8, MAGNETICFLUX, 11, SPARK, 11, BULLETCHARGE, 14, SHOCKWAVE, 14, TIMEBOMB, 17, SCREECH, 17, METALSOUND, 20, IRONSPARKS, 23, MAGNETBOMB, 26, ARCINGBLOW, 29, REFLECT, 29, LIGHTSCREEN, 32, DISCHARGE, 35, PROTONCRASH, 38, CLUSTERROCKETS, 41, IRONIMPACT, 44, ENERGYSURGE, 44, THUNDERBOLT, 47, MAGNETICCANNON, 50, ELECTRONCRUSH, 53, BOMBARDMENT, 56, LOCKON, 56, ZAPCANNON, 60, STEELBEAM, | Z25: =VLOOKUP($A25,'Moves Species'!$A:$E,4,FALSE) -> ACROBATICS, AERIALACE, AERIALPULSE, AIRSLASH, AMBUSH, ANTIMATTER, ATTRACT, AURASPHERE, BALLLIGHTNING, BATTLEOFWITS, BOLTCRASH, BOUNCE, BRAVEBIRD, BULLETSEED, CHARGEBEAM, CLUSTERROCKETS, CONFUSERAY, COUPDEGRACE, DAZZLINGGLEAM, DEFOG, DRILLPECK, DUALWINGBEAT, ECHOEDVOICE, ELECTRICTERRAIN, ELECTRONCRUSH, ENERGYSURGE, FLOCK, FLUTTER, FLUXWAVE, GAMMARAY, GLISTEN, GOSSIP, HIDDENPOWER, IRONDEFENSE, IRONHEAD, IRONIMPACT, IRONTEMPEST, KNOCKOFF, LIGHTSCREEN, MAGNETICCANNON, MAGNETRISE, METEORBEAM, METEORDRIVE, MIRRORSHOT, MISSILESHOT, MIXEDWAVES, NASTYPLOT, OVERCLOCK, PARABOLICCHARGE, PROTECT, REFLECT, REFURBISH, REST, RETURN, RISINGVOLTAGE, SAFEGUARD, SATELLITERAY, SIGNALBEAM, SLEEPTALK, SOUNDBARRIER, STEELWING, SWIFT, SWITCHEROO, TAILWIND, TEMPESTFLARE, THUNDER, THUNDERBOLT, THUNDERWAVE, TOXIC, TRIATTACK, UTURN, VOLTSWITCH, WORKUP, | AA25: =VLOOKUP($A25,'Moves Species'!$A:$E,5,FALSE) -> SHRAPNEL, MAGNETRISE, OVERCLOCK, METALBURST, SYNCHRONOISE, SPIKES, SELFDESTRUCT, EXPLOSION, COBALTRAY, EERIEIMPULSE, | AB25: XATU | AC25: Level | AD25: 25
A26: =A25+1 -> 25 | B26: [XATU] | C26: Xatu | D26: ='BST Extract'!J26 -> STEEL | E26: ='BST Extract'!K26 -> ELECTRIC | F26: =D26&","&E26 -> STEEL,ELECTRIC | G26: ='BST Extract'!C26 -> 75 | H26: ='BST Extract'!D26 -> 95 | I26: ='BST Extract'!E26 -> 65 | J26: ='BST Extract'!F26 -> 95 | K26: ='BST Extract'!G26 -> 95 | L26: ='BST Extract'!H26 -> 70 | M26: ='BST Extract'!I26 -> 495 | N26: SPECIAL_ATTACK | O26: 1 | P26: SPEED | Q26: 1 | T26: =N26&","&O26&","&P26&","&Q26&","&R26&","&S26 -> SPECIAL_ATTACK,1,SPEED,1,, | U26: ='Ability Extract'!C26 -> BATTERY | V26: ='Ability Extract'!D26 -> DOWNLOAD | W26: ='Ability Extract'!E26 -> MAGICBOUNCE | X26: ='Ability Extract'!F26 -> BATTERY,DOWNLOAD,MAGICBOUNCE | Y26: =VLOOKUP($A26,'Moves Species'!$A:$E,3,FALSE) -> 0, PARABOLICCHARGE, 1, PARABOLICCHARGE, 1, PECK, 1, LEER, 1, NUZZLE, 4, MISSILESHOT, 6, THUNDERSHOCK, 8, GEARUP, 8, MAGNETICFLUX, 11, SPARK, 11, BULLETCHARGE, 14, SHOCKWAVE, 14, TIMEBOMB, 17, SCREECH, 17, METALSOUND, 20, IRONSPARKS, 23, MAGNETBOMB, 26, ARCINGBLOW, 29, REFLECT, 29, LIGHTSCREEN, 32, DISCHARGE, 35, PROTONCRASH, 38, CLUSTERROCKETS, 41, IRONIMPACT, 44, ENERGYSURGE, 44, THUNDERBOLT, 47, MAGNETICCANNON, 50, ELECTRONCRUSH, 53, BOMBARDMENT, 56, LOCKON, 56, ZAPCANNON, 60, STEELBEAM, | Z26: =VLOOKUP($A26,'Moves Species'!$A:$E,4,FALSE) -> ACROBATICS, AERIALACE, AERIALPULSE, AIRSLASH, AMBUSH, ANTIMATTER, ATTRACT, AURASPHERE, BALLLIGHTNING, BATTLEOFWITS, BOLTCRASH, BOUNCE, BRAVEBIRD, BULLETSEED, CHARGEBEAM, CLUSTERROCKETS, CONFUSERAY, COUPDEGRACE, DAZZLINGGLEAM, DEFOG, DRILLPECK, DUALWINGBEAT, ECHOEDVOICE, ELECTRICTERRAIN, ELECTRONCRUSH, ENERGYSURGE, FLOCK, FLUTTER, FLUXWAVE, GAMMARAY, GLISTEN, GOSSIP, HIDDENPOWER, IRONDEFENSE, IRONHEAD, IRONIMPACT, IRONTEMPEST, KNOCKOFF, LIGHTSCREEN, MAGNETICCANNON, MAGNETRISE, METEORBEAM, METEORDRIVE, MIRRORSHOT, MISSILESHOT, MIXEDWAVES, NASTYPLOT, OVERCLOCK, PARABOLICCHARGE, PROTECT, REFLECT, REFURBISH, REST, RETURN, RISINGVOLTAGE, SAFEGUARD, SATELLITERAY, SIGNALBEAM, SLEEPTALK, SOUNDBARRIER, STEELWING, SWIFT, SWITCHEROO, TAILWIND, TEMPESTFLARE, THUNDER, THUNDERBOLT, THUNDERWAVE, TOXIC, TRIATTACK, UTURN, VOLTSWITCH, WORKUP, | AA26: =VLOOKUP($A26,'Moves Species'!$A:$E,5,FALSE) -> 0
A27: =A26+1 -> 26 | B27: [RUFFLET] | C27: Rufflet | D27: ='BST Extract'!J27 -> FIRE | E27: ='BST Extract'!K27 -> FLYING | F27: =D27&","&E27 -> FIRE,FLYING | G27: ='BST Extract'!C27 -> 70 | H27: ='BST Extract'!D27 -> 83 | I27: ='BST Extract'!E27 -> 50 | J27: ='BST Extract'!F27 -> 75 | K27: ='BST Extract'!G27 -> 37 | L27: ='BST Extract'!H27 -> 50 | M27: ='BST Extract'!I27 -> 365 | N27: ATTACK | O27: 1 | T27: =N27&","&O27&","&P27&","&Q27&","&R27&","&S27 -> ATTACK,1,,,, | U27: ='Ability Extract'!C27 -> KEENEYE | V27: ='Ability Extract'!D27 -> DEFIANT | W27: ='Ability Extract'!E27 -> BLAZE | X27: ='Ability Extract'!F27 -> KEENEYE,DEFIANT,BLAZE | Y27: =VLOOKUP($A27,'Moves Species'!$A:$E,3,FALSE) -> 1, PECK, 1, STALKPREY, 1, KINDLE, 4, SCORCH, 8, JETDIVE, 11, FLAMECHARGE, 14, BIRDOFPREY, 17, PLUCK, 20, FLAMEWHEEL, 23, TAILWIND, 26, FLAMEPILLAR, 29, ACROBATICS, 32, HELLBRAND, 35, SWEEPINGTALON, 38, FIREWALL, 42, SUNNYDAY, 46, SKYDIVE, 49, SACREDFIRE, 53, BRAVEBIRD, 57, BEAKBLAST, 62, FLAREBLITZ, | Z27: =VLOOKUP($A27,'Moves Species'!$A:$E,4,FALSE) -> ACROBATICS, AERIALACE, AERIALPULSE, AIRSLASH, AMBUSH, ANCIENTGLARE, ATTRACT, BRAVEBIRD, BREAKINGSWIPE, CLEANSE, COUPDEGRACE, COVET, DAZZLINGGLEAM, DEFOG, DRACOMETEOR, DRACONICWAVE, DRAGONCLAW, DRAGONGALE, DRILLPECK, DUALWINGBEAT, DUSTDEVILS, ECHOEDVOICE, ENDERSHOCK, FEATHERDANCE, FIREBLAST, FLAMECHARGE, FLAMETHROWER, FLAMEVOLLEY, FLAREBLITZ, FLOCK, HEATWAVE, HIDDENPOWER, HOLYNOVA, HURRICANE, INCINERATE, KNOCKOFF, MYSTICALFIRE, NASTYPLOT, OUTRAGE, PROTECT, RADIANTLANCE, RAYOFLIGHT, REST, RETURN, SACREDSTRIKE, SLEEPTALK, SONICBLAST, STEELWING, STELLARRUSH, SUNNYDAY, SWIFT, SWORDSDANCE, TAILWIND, TEMPESTFLARE, TERRAINPULSE, TORNADO, TOXIC, TURBULENCE, UTURN, VENDETTA, WEATHERBALL, WILDCHARGE, WILDFIRE, WORKUP, | AA27: =VLOOKUP($A27,'Moves Species'!$A:$E,5,FALSE) -> DRILLPECK, FLARESWEEP, VOLTTACKLE, ROOST, AIRCUTTER, HONECLAWS, SWOOPATTACK, DIVEBOMB, MELTINGHORN, | AB27: BRAVIARY | AC27: Level | AD27: 40
A28: =A27+1 -> 27 | B28: [BRAVIARY] | C28: Braviary | D28: ='BST Extract'!J28 -> FIRE | E28: ='BST Extract'!K28 -> FLYING | F28: =D28&","&E28 -> FIRE,FLYING | G28: ='BST Extract'!C28 -> 100 | H28: ='BST Extract'!D28 -> 123 | I28: ='BST Extract'!E28 -> 75 | J28: ='BST Extract'!F28 -> 95 | K28: ='BST Extract'!G28 -> 57 | L28: ='BST Extract'!H28 -> 75 | M28: ='BST Extract'!I28 -> 525 | N28: ATTACK | O28: 2 | T28: =N28&","&O28&","&P28&","&Q28&","&R28&","&S28 -> ATTACK,2,,,, | U28: ='Ability Extract'!C28 -> KEENEYE | V28: ='Ability Extract'!D28 -> DEFIANT | W28: ='Ability Extract'!E28 -> BLAZE | X28: ='Ability Extract'!F28 -> KEENEYE,DEFIANT,BLAZE | Y28: =VLOOKUP($A28,'Moves Species'!$A:$E,3,FALSE) -> 1, PECK, 1, STALKPREY, 1, KINDLE, 4, SCORCH, 8, JETDIVE, 11, FLAMECHARGE, 14, BIRDOFPREY, 17, PLUCK, 20, FLAMEWHEEL, 23, TAILWIND, 26, FLAMEPILLAR, 29, ACROBATICS, 32, HELLBRAND, 35, SWEEPINGTALON, 38, FIREWALL, 42, SUNNYDAY, 46, SKYDIVE, 49, SACREDFIRE, 53, BRAVEBIRD, 57, BEAKBLAST, 62, FLAREBLITZ, | Z28: =VLOOKUP($A28,'Moves Species'!$A:$E,4,FALSE) -> ACROBATICS, AERIALACE, AERIALPULSE, AIRSLASH, AMBUSH, ANCIENTGLARE, ATTRACT, BRAVEBIRD, BREAKINGSWIPE, CLEANSE, COUPDEGRACE, COVET, DAZZLINGGLEAM, DEFOG, DRACOMETEOR, DRACONICWAVE, DRAGONCLAW, DRAGONGALE, DRILLPECK, DUALWINGBEAT, DUSTDEVILS, ECHOEDVOICE, ENDERSHOCK, FEATHERDANCE, FIREBLAST, FLAMECHARGE, FLAMETHROWER, FLAMEVOLLEY, FLAREBLITZ, FLOCK, HEATWAVE, HIDDENPOWER, HOLYNOVA, HURRICANE, INCINERATE, KNOCKOFF, MYSTICALFIRE, NASTYPLOT, OUTRAGE, PROTECT, RADIANTLANCE, RAYOFLIGHT, REST, RETURN, SACREDSTRIKE, SLEEPTALK, SONICBLAST, STEELWING, STELLARRUSH, SUNNYDAY, SWIFT, SWORDSDANCE, TAILWIND, TEMPESTFLARE, TERRAINPULSE, TORNADO, TOXIC, TURBULENCE, UTURN, VENDETTA, WEATHERBALL, WILDCHARGE, WILDFIRE, WORKUP, | AA28: =VLOOKUP($A28,'Moves Species'!$A:$E,5,FALSE) -> 0
A29: =A28+1 -> 28 | B29: [NOSEPASS] | C29: Nosepass | D29: ='BST Extract'!J29 -> GRASS | E29: ='BST Extract'!K29 -> PSYCHIC | F29: =D29&","&E29 -> GRASS,PSYCHIC | G29: ='BST Extract'!C29 -> 40 | H29: ='BST Extract'!D29 -> 95 | I29: ='BST Extract'!E29 -> 60 | J29: ='BST Extract'!F29 -> 75 | K29: ='BST Extract'!G29 -> 95 | L29: ='BST Extract'!H29 -> 60 | M29: ='BST Extract'!I29 -> 425 | N29: ATTACK | O29: 1 | T29: =N29&","&O29&","&P29&","&Q29&","&R29&","&S29 -> ATTACK,1,,,, | U29: ='Ability Extract'!C29 -> NATURALCURE | V29: ='Ability Extract'!D29 -> LEADERSHIP | W29: ='Ability Extract'!E29 -> CHLOROPHYLL | X29: ='Ability Extract'!F29 -> NATURALCURE,LEADERSHIP,CHLOROPHYLL | Y29: =VLOOKUP($A29,'Moves Species'!$A:$E,3,FALSE) -> 1, THORNPRISON, 1, TACKLE, 1, ESSENCEARROW, 4, CONFUSION, 6, GROWTH, 8, RAZORLEAF, 11, MIXEDWAVES, 11, ESSENCEBLOOM, 14, SMACKDOWN, 14, BULLETSEED, 17, PSYBEAM, 17, LEAFTORNADO, 20, STEALTHROCK, 23, PSYCHOCUT, 23, BATTLECRY, 26, SYNTHESIS, 29, GIGADRAIN, 32, EXTRASENSORY, 35, PSYBLADE, 38, FLORALHEALING, 41, LEAFBLADE, 44, ENERGYBALL, 47, PSYCHIC, 47, SCRAMBLEMIND, 50, PETALDANCE, 53, MAGICCOAT, 56, SOLARBEAM, 59, ARCANEENERGY, 62, SOLARBLADE, | Z29: =VLOOKUP($A29,'Moves Species'!$A:$E,4,FALSE) -> AMBUSH, ANCIENTGLARE, ARCANEENERGY, AROMATHERAPY, ATTRACT, AURASPHERE, BATTLEOFWITS, BLOODRITUAL, BODYPRESS, BODYSLAM, BOOMBURST, BRICKBREAK, BULLETSEED, CALMMIND, CATAPULT, CHIDORI, CLEANSE, CONFUSERAY, COVET, CURSE, CURSEDTOUCH, DARKPULSE, DAZZLINGGLEAM, DEFENDORDER, EARTHENLANCE, EARTHPOWER, ECHOEDVOICE, ENERGYBALL, ESSENCEBLOOM, EXPANDINGFORCE, FLUXWAVE, FURYCUTTER, GAIAPULSE, GHASTLYFLOOD, GIGADRAIN, GOBLINSTRIKE, GOSSIP, GRASSYTERRAIN, HEX, HEXBOLT, HIDDENPOWER, KNOCKOFF, LEAFBLADE, LIGHTSCREEN, MAGICALLEAF, MAGICROOM, METRONOME, MINDDRAIN, MINDMELD, MIXEDWAVES, MOSSYPUNCH, MYSTICALFIRE, MYSTICPULSE, NASTYPLOT, NATURESWRATH, NECTARTAP, PERCUSSIONBLAST, PETALTEMPEST, PINMISSILE, PIXIEDUST, POISONJAB, POWERWHIP, PROTECT, PSYCHIC, PSYCHICTERRAIN, QUICKGUARD, REFLECT, REST, RETURN, ROCKBLAST, ROCKSLIDE, ROCKTOMB, SANDTOMB, SCENTEDSHIELD, SEISMICCHANT, SHADOWBALL, SLASH, SLEEPTALK, SOLARBEAM, SONICBLAST, SOULRIP, SPIKES, STEALTHROCK, STONEEDGE, SUNNYDAY, SWITCHEROO, SYNTHESIS, TAUNT, TERRAINPULSE, TOXIC, TOXICSPIKES, WEAKSPOT, WEATHERBALL, WONDERROOM, WORKUP, ZENHEADBUTT, | AA29: =VLOOKUP($A29,'Moves Species'!$A:$E,5,FALSE) -> PSYSHOCK, CALMMIND, UPROAR, ANCIENTPOWER, ROCKSLIDE, LEECHSEED, FUTURESIGHT, HELPINGHAND, GUTTURALROAR, MINDCRUSH, AUTUMNBLAST, | AB29: PROBOPASS | AC29: Level | AD29: 30
A30: =A29+1 -> 29 | B30: [PROBOPASS] | C30: Probopass | D30: ='BST Extract'!J30 -> GRASS | E30: ='BST Extract'!K30 -> PSYCHIC | F30: =D30&","&E30 -> GRASS,PSYCHIC | G30: ='BST Extract'!C30 -> 60 | H30: ='BST Extract'!D30 -> 105 | I30: ='BST Extract'!E30 -> 95 | J30: ='BST Extract'!F30 -> 60 | K30: ='BST Extract'!G30 -> 115 | L30: ='BST Extract'!H30 -> 90 | M30: ='BST Extract'!I30 -> 525 | N30: ATTACK | O30: 1 | P30: SPECIAL_ATTACK | Q30: 1 | T30: =N30&","&O30&","&P30&","&Q30&","&R30&","&S30 -> ATTACK,1,SPECIAL_ATTACK,1,, | U30: ='Ability Extract'!C30 -> NATURALCURE | V30: ='Ability Extract'!D30 -> LEADERSHIP | W30: ='Ability Extract'!E30 -> CHLOROPHYLL | X30: ='Ability Extract'!F30 -> NATURALCURE,LEADERSHIP,CHLOROPHYLL | Y30: =VLOOKUP($A30,'Moves Species'!$A:$E,3,FALSE) -> 0, STRANDINGROOTS, 1, STRANDINGROOTS, 1, THORNPRISON, 1, TACKLE, 1, ESSENCEARROW, 4, CONFUSION, 6, GROWTH, 8, RAZORLEAF, 11, MIXEDWAVES, 11, ESSENCEBLOOM, 14, SMACKDOWN, 14, BULLETSEED, 17, PSYBEAM, 17, LEAFTORNADO, 20, STEALTHROCK, 23, PSYCHOCUT, 23, BATTLECRY, 26, SYNTHESIS, 29, GIGADRAIN, 32, EXTRASENSORY, 35, PSYBLADE, 38, FLORALHEALING, 41, LEAFBLADE, 44, ENERGYBALL, 47, PSYCHIC, 47, SCRAMBLEMIND, 50, PETALDANCE, 53, MAGICCOAT, 56, SOLARBEAM, 59, ARCANEENERGY, 62, SOLARBLADE, | Z30: =VLOOKUP($A30,'Moves Species'!$A:$E,4,FALSE) -> AMBUSH, ANCIENTGLARE, ARCANEENERGY, AROMATHERAPY, ATTRACT, AURASPHERE, BATTLEOFWITS, BLOODRITUAL, BODYPRESS, BODYSLAM, BOOMBURST, BRICKBREAK, BULLETSEED, CALMMIND, CATAPULT, CHIDORI, CLEANSE, CONFUSERAY, COVET, CURSE, CURSEDTOUCH, DARKPULSE, DAZZLINGGLEAM, DEFENDORDER, EARTHENLANCE, EARTHPOWER, ECHOEDVOICE, ENERGYBALL, ESSENCEBLOOM, EXPANDINGFORCE, FLUXWAVE, FURYCUTTER, GAIAPULSE, GHASTLYFLOOD, GIGADRAIN, GOBLINSTRIKE, GOSSIP, GRASSYTERRAIN, HEX, HEXBOLT, HIDDENPOWER, KNOCKOFF, LEAFBLADE, LIGHTSCREEN, MAGICALLEAF, MAGICROOM, METRONOME, MINDDRAIN, MINDMELD, MIXEDWAVES, MOSSYPUNCH, MYSTICALFIRE, MYSTICPULSE, NASTYPLOT, NATURESWRATH, NECTARTAP, PERCUSSIONBLAST, PETALTEMPEST, PINMISSILE, PIXIEDUST, POISONJAB, POWERWHIP, PROTECT, PSYCHIC, PSYCHICTERRAIN, QUICKGUARD, REFLECT, REST, RETURN, ROCKBLAST, ROCKSLIDE, ROCKTOMB, SANDTOMB, SCENTEDSHIELD, SEISMICCHANT, SHADOWBALL, SLASH, SLEEPTALK, SOLARBEAM, SONICBLAST, SOULRIP, SPIKES, STEALTHROCK, STONEEDGE, SUNNYDAY, SWITCHEROO, SYNTHESIS, TAUNT, TERRAINPULSE, TOXIC, TOXICSPIKES, WEAKSPOT, WEATHERBALL, WONDERROOM, WORKUP, ZENHEADBUTT, | AA30: =VLOOKUP($A30,'Moves Species'!$A:$E,5,FALSE) -> 0
A31: =A30+1 -> 30 | B31: [ZUBAT] | C31: Zubat | D31: ='BST Extract'!J31 -> DARK | E31: ='BST Extract'!K31 -> SOUND | F31: =D31&","&E31 -> DARK,SOUND | G31: ='BST Extract'!C31 -> 35 | H31: ='BST Extract'!D31 -> 50 | I31: ='BST Extract'!E31 -> 35 | J31: ='BST Extract'!F31 -> 60 | K31: ='BST Extract'!G31 -> 30 | L31: ='BST Extract'!H31 -> 35 | M31: ='BST Extract'!I31 -> 245 | N31: SPEED | O31: 1 | T31: =N31&","&O31&","&P31&","&Q31&","&R31&","&S31 -> SPEED,1,,,, | U31: ='Ability Extract'!C31 -> LEVITATE | V31: ='Ability Extract'!D31 -> LEECHINGFANGS | W31: ='Ability Extract'!E31 -> MERCILESS | X31: ='Ability Extract'!F31 -> LEVITATE,LEECHINGFANGS,MERCILESS | Y31: =VLOOKUP($A31,'Moves Species'!$A:$E,3,FALSE) -> 1, DARKWHISPERS, 1, STALKPREY, 1, MEGAPHONE, 4, BACKSTABBING, 8, POISONSPIT, 11, DEAFEN, 14, TAUNT, 17, BITE, 20, SONICBLAST, 23, NECROPHAGY, 26, CHEAPSHOT, 29, SHATTER, 32, CRUNCH, 35, SCREECH, 38, LEECHLIFE, 41, DEADSILENCE, 44, AMBUSH, 47, DEATHVORTEX, 50, SONICNOVA, 53, PLAGUE, 56, EXECUTION, 60, UPROAR, | Z31: =VLOOKUP($A31,'Moves Species'!$A:$E,4,FALSE) -> ACROBATICS, AERIALACE, AERIALPULSE, AIRSLASH, AMBUSH, ATTRACT, BLOODRITUAL, BONECHILL, BOOMBURST, BRAVEBIRD, BUGBITE, CAUSTICACID, CLEARSMOG, CONFUSERAY, COUPDEGRACE, COVET, CRUNCH, DARKPULSE, DEAFEN, DEFOG, DRAGONDANCE, DRAININGKISS, DUALWINGBEAT, ECHOEDVOICE, ECLIPSENOVA, ENDERSHOCK, EXECUTION, FALSESWIPE, FIREFANG, FLOCK, FLUTTER, FURYCUTTER, GOBLINSTRIKE, GOSSIP, HAZE, HEX, HIDDENPOWER, HYPERVOICE, ICEFANG, ICYWIND, LASHOUT, LEAFBLADE, LEECHLIFE, MIASMA, MINDDRAIN, NASTYPLOT, PERCUSSIONBLAST, POISONFANG, POISONJAB, PROTECT, PSYCHICFANGS, QUICKGUARD, REST, RETURN, ROUND, SHADOWBALL, SLASH, SLEEPTALK, SLUDGEBOMB, SONICBLAST, SOULSHIELD, SOUNDBARRIER, STEELWING, SWITCHEROO, SWORDSDANCE, TAILWIND, TAUNT, THUNDERFANG, TOXIC, TOXICSPIKES, TURBULENCE, UMBRALWAVE, UTURN, VENDETTA, VENOMDRAIN, VITALITYDRAIN, WAIL, WEAKSPOT, WILDCHARGE, WORKUP, | AA31: =VLOOKUP($A31,'Moves Species'!$A:$E,5,FALSE) -> BRAVEBIRD, JETDIVE, POISONFANG, WAIL, NEUROTOXIN, TAILWIND, ASTONISH, MEMENTO, STEELWING, VENOMDRAIN, MEANLOOK, PURSUIT, BATTLECRY, HUNTDOWN, | AB31: GOLBAT | AC31: Level | AD31: 26
A32: =A31+1 -> 31 | B32: [GOLBAT] | C32: Golbat | D32: ='BST Extract'!J32 -> DARK | E32: ='BST Extract'!K32 -> SOUND | F32: =D32&","&E32 -> DARK,SOUND | G32: ='BST Extract'!C32 -> 75 | H32: ='BST Extract'!D32 -> 80 | I32: ='BST Extract'!E32 -> 65 | J32: ='BST Extract'!F32 -> 90 | K32: ='BST Extract'!G32 -> 60 | L32: ='BST Extract'!H32 -> 60 | M32: ='BST Extract'!I32 -> 430 | N32: SPEED | O32: 2 | T32: =N32&","&O32&","&P32&","&Q32&","&R32&","&S32 -> SPEED,2,,,, | U32: ='Ability Extract'!C32 -> LEVITATE | V32: ='Ability Extract'!D32 -> LEECHINGFANGS | W32: ='Ability Extract'!E32 -> MERCILESS | X32: ='Ability Extract'!F32 -> LEVITATE,LEECHINGFANGS,MERCILESS | Y32: =VLOOKUP($A32,'Moves Species'!$A:$E,3,FALSE) -> 0, CROSSPOISON, 1, CROSSPOISON, 1, DARKWHISPERS, 1, STALKPREY, 1, MEGAPHONE, 4, BACKSTABBING, 8, POISONSPIT, 11, DEAFEN, 14, TAUNT, 17, BITE, 20, SONICBLAST, 23, NECROPHAGY, 26, CHEAPSHOT, 29, SHATTER, 32, CRUNCH, 35, SCREECH, 38, LEECHLIFE, 41, DEADSILENCE, 44, AMBUSH, 47, DEATHVORTEX, 50, SONICNOVA, 53, PLAGUE, 56, EXECUTION, 60, UPROAR, | Z32: =VLOOKUP($A32,'Moves Species'!$A:$E,4,FALSE) -> ACROBATICS, AERIALACE, AERIALPULSE, AIRSLASH, AMBUSH, ATTRACT, BLOODRITUAL, BONECHILL, BOOMBURST, BRAVEBIRD, BUGBITE, CAUSTICACID, CLEARSMOG, CONFUSERAY, COUPDEGRACE, COVET, CRUNCH, DARKPULSE, DEAFEN, DEFOG, DRAGONDANCE, DRAININGKISS, DUALWINGBEAT, ECHOEDVOICE, ECLIPSENOVA, ENDERSHOCK, EXECUTION, FALSESWIPE, FIREFANG, FLOCK, FLUTTER, FURYCUTTER, GOBLINSTRIKE, GOSSIP, HAZE, HEX, HIDDENPOWER, HYPERVOICE, ICEFANG, ICYWIND, LASHOUT, LEAFBLADE, LEECHLIFE, MIASMA, MINDDRAIN, NASTYPLOT, PERCUSSIONBLAST, POISONFANG, POISONJAB, PROTECT, PSYCHICFANGS, QUICKGUARD, REST, RETURN, ROUND, SHADOWBALL, SLASH, SLEEPTALK, SLUDGEBOMB, SONICBLAST, SOULSHIELD, SOUNDBARRIER, STEELWING, SWITCHEROO, SWORDSDANCE, TAILWIND, TAUNT, THUNDERFANG, TOXIC, TOXICSPIKES, TURBULENCE, UMBRALWAVE, UTURN, VENDETTA, VENOMDRAIN, VITALITYDRAIN, WAIL, WEAKSPOT, WILDCHARGE, WORKUP, | AA32: =VLOOKUP($A32,'Moves Species'!$A:$E,5,FALSE) -> 0 | AB32: CROBAT | AC32: Level | AD32: 42
A33: =A32+1 -> 32 | B33: [CROBAT] | C33: Crobat | D33: ='BST Extract'!J33 -> DARK | E33: ='BST Extract'!K33 -> SOUND | F33: =D33&","&E33 -> DARK,SOUND | G33: ='BST Extract'!C33 -> 85 | H33: ='BST Extract'!D33 -> 95 | I33: ='BST Extract'!E33 -> 85 | J33: ='BST Extract'!F33 -> 120 | K33: ='BST Extract'!G33 -> 70 | L33: ='BST Extract'!H33 -> 80 | M33: ='BST Extract'!I33 -> 535 | N33: SPEED | O33: 3 | T33: =N33&","&O33&","&P33&","&Q33&","&R33&","&S33 -> SPEED,3,,,, | U33: ='Ability Extract'!C33 -> LEVITATE | V33: ='Ability Extract'!D33 -> LEECHINGFANGS | W33: ='Ability Extract'!E33 -> MERCILESS | X33: ='Ability Extract'!F33 -> LEVITATE,LEECHINGFANGS,MERCILESS | Y33: =VLOOKUP($A33,'Moves Species'!$A:$E,3,FALSE) -> 0, STREAMRUSH, 1, STREAMRUSH, 1, CROSSPOISON, 1, DARKWHISPERS, 1, STALKPREY, 1, MEGAPHONE, 4, BACKSTABBING, 8, POISONSPIT, 11, DEAFEN, 14, TAUNT, 17, BITE, 20, SONICBLAST, 23, NECROPHAGY, 26, CHEAPSHOT, 29, SHATTER, 32, CRUNCH, 35, SCREECH, 38, LEECHLIFE, 41, DEADSILENCE, 44, AMBUSH, 47, DEATHVORTEX, 50, SONICNOVA, 53, PLAGUE, 56, EXECUTION, 60, UPROAR, | Z33: =VLOOKUP($A33,'Moves Species'!$A:$E,4,FALSE) -> ACROBATICS, AERIALACE, AERIALPULSE, AIRSLASH, AMBUSH, ATTRACT, BLOODRITUAL, BONECHILL, BOOMBURST, BRAVEBIRD, BUGBITE, CAUSTICACID, CLEARSMOG, CONFUSERAY, COUPDEGRACE, COVET, CRUNCH, DARKPULSE, DEAFEN, DEFOG, DRAGONDANCE, DRAININGKISS, DUALWINGBEAT, ECHOEDVOICE, ECLIPSENOVA, ENDERSHOCK, EXECUTION, FALSESWIPE, FIREFANG, FLOCK, FLUTTER, FURYCUTTER, GOBLINSTRIKE, GOSSIP, HAZE, HEX, HIDDENPOWER, HYPERVOICE, ICEFANG, ICYWIND, LASHOUT, LEAFBLADE, LEECHLIFE, MIASMA, MINDDRAIN, NASTYPLOT, PERCUSSIONBLAST, POISONFANG, POISONJAB, PROTECT, PSYCHICFANGS, QUICKGUARD, REST, RETURN, ROUND, SHADOWBALL, SLASH, SLEEPTALK, SLUDGEBOMB, SONICBLAST, SOULSHIELD, SOUNDBARRIER, STEELWING, SWITCHEROO, SWORDSDANCE, TAILWIND, TAUNT, THUNDERFANG, TOXIC, TOXICSPIKES, TURBULENCE, UMBRALWAVE, UTURN, VENDETTA, VENOMDRAIN, VITALITYDRAIN, WAIL, WEAKSPOT, WILDCHARGE, WORKUP, | AA33: =VLOOKUP($A33,'Moves Species'!$A:$E,5,FALSE) -> 0
A34: =A33+1 -> 33 | B34: [TANGELA] | C34: Tangela | D34: ='BST Extract'!J34 -> GROUND | E34: ='BST Extract'!K34 -> GRASS | F34: =D34&","&E34 -> GROUND,GRASS | G34: ='BST Extract'!C34 -> 65 | H34: ='BST Extract'!D34 -> 75 | I34: ='BST Extract'!E34 -> 115 | J34: ='BST Extract'!F34 -> 90 | K34: ='BST Extract'!G34 -> 50 | L34: ='BST Extract'!H34 -> 40 | M34: ='BST Extract'!I34 -> 435 | N34: DEFENSE | O34: 1 | T34: =N34&","&O34&","&P34&","&Q34&","&R34&","&S34 -> DEFENSE,1,,,, | U34: ='Ability Extract'!C34 -> SANDRUSH | V34: ='Ability Extract'!D34 -> STORMDRAIN | W34: ='Ability Extract'!E34 -> REGROWTH | X34: ='Ability Extract'!F34 -> SANDRUSH,STORMDRAIN,REGROWTH | Y34: =VLOOKUP($A34,'Moves Species'!$A:$E,3,FALSE) -> 1, ROTOTILLER, 1, SANDATTACK, 1, VINEWHIP, 4, SANDTOMB, 8, SANDJET, 12, THORNPRISON, 15, NEEDLEARM, 18, BULLDOZE, 21, SPIKES, 24, KNOCKOFF, 27, ACROBATICS, 30, SEEDBOMB, 33, EARTHENLANCE, 36, BOUNCE, 39, BODYSLAM, 42, LANDSWRATH, 45, LEAFBLADE, 48, SANDSTORM, 52, EARTHQUAKE, 56, POWERWHIP, 60, SANDSHROUD, | Z34: =VLOOKUP($A34,'Moves Species'!$A:$E,4,FALSE) -> ACROBATICS, ATTRACT, BODYPRESS, BODYSLAM, BOULDERCRUSH, BOUNCE, BRICKBREAK, BULLDOZE, BULLETSEED, CATAPULT, COVET, DUNEBLAST, DUSTDEVILS, EARTHENLANCE, EARTHPOWER, EARTHQUAKE, ENERGYBALL, ESSENCEBLOOM, GAIAPULSE, GEOMANCY, GIGADRAIN, GOLDRUSH, GRASSYTERRAIN, GYROBALL, HIDDENPOWER, IRONDEFENSE, IRONHEAD, KNOCKOFF, LEAFBLADE, MAGICALLEAF, MEMENTO, MUDSHACKLES, MUDSLIDE, NATURESWRATH, PETALTEMPEST, PLAYROUGH, POWERWHIP, PROTECT, QUICKSAND, REST, RETURN, ROCKBLAST, ROCKSLIDE, ROCKTOMB, SANDSTORM, SANDTOMB, SCENTEDSHIELD, SCORCHINGSANDS, SEISMICCHANT, SLEEPTALK, SOLARBEAM, SPIKES, SPIKYSHIELD, STEALTHROCK, STONEEDGE, SUNNYDAY, SYNTHESIS, TAILWIND, TERRAINPULSE, TOXIC, WORKUP, ZENHEADBUTT, | AA34: =VLOOKUP($A34,'Moves Species'!$A:$E,5,FALSE) -> AMNESIA, GIGADRAIN, ENDEAVOR, FLAIL, LEECHSEED, MEGADRAIN, NATURALGIFT, SPIKYSHIELD, MUDSHACKLES, DIG, SANDPIT, CATACLYSM, | AB34: TANGROWTH | AC34: Level | AD34: 40
A35: =A34+1 -> 34 | B35: [TANGROWTH] | C35: Tangrowth | D35: ='BST Extract'!J35 -> GROUND | E35: ='BST Extract'!K35 -> GRASS | F35: =D35&","&E35 -> GROUND,GRASS | G35: ='BST Extract'!C35 -> 100 | H35: ='BST Extract'!D35 -> 100 | I35: ='BST Extract'!E35 -> 125 | J35: ='BST Extract'!F35 -> 80 | K35: ='BST Extract'!G35 -> 60 | L35: ='BST Extract'!H35 -> 70 | M35: ='BST Extract'!I35 -> 535 | N35: DEFENSE | O35: 2 | T35: =N35&","&O35&","&P35&","&Q35&","&R35&","&S35 -> DEFENSE,2,,,, | U35: ='Ability Extract'!C35 -> SANDRUSH | V35: ='Ability Extract'!D35 -> STORMDRAIN | W35: ='Ability Extract'!E35 -> REGROWTH | X35: ='Ability Extract'!F35 -> SANDRUSH,STORMDRAIN,REGROWTH | Y35: =VLOOKUP($A35,'Moves Species'!$A:$E,3,FALSE) -> 1, ROTOTILLER, 1, SANDATTACK, 1, VINEWHIP, 4, SANDTOMB, 8, SANDJET, 12, THORNPRISON, 15, NEEDLEARM, 18, BULLDOZE, 21, SPIKES, 24, KNOCKOFF, 27, ACROBATICS, 30, SEEDBOMB, 33, EARTHENLANCE, 36, BOUNCE, 39, BODYSLAM, 42, LANDSWRATH, 45, LEAFBLADE, 48, SANDSTORM, 52, EARTHQUAKE, 56, POWERWHIP, 60, SANDSHROUD, | Z35: =VLOOKUP($A35,'Moves Species'!$A:$E,4,FALSE) -> ACROBATICS, ATTRACT, BODYPRESS, BODYSLAM, BOULDERCRUSH, BOUNCE, BRICKBREAK, BULLDOZE, BULLETSEED, CATAPULT, COVET, DUNEBLAST, DUSTDEVILS, EARTHENLANCE, EARTHPOWER, EARTHQUAKE, ENERGYBALL, ESSENCEBLOOM, GAIAPULSE, GEOMANCY, GIGADRAIN, GOLDRUSH, GRASSYTERRAIN, GYROBALL, HIDDENPOWER, IRONDEFENSE, IRONHEAD, KNOCKOFF, LEAFBLADE, MAGICALLEAF, MEMENTO, MUDSHACKLES, MUDSLIDE, NATURESWRATH, PETALTEMPEST, PLAYROUGH, POWERWHIP, PROTECT, QUICKSAND, REST, RETURN, ROCKBLAST, ROCKSLIDE, ROCKTOMB, SANDSTORM, SANDTOMB, SCENTEDSHIELD, SCORCHINGSANDS, SEISMICCHANT, SLEEPTALK, SOLARBEAM, SPIKES, SPIKYSHIELD, STEALTHROCK, STONEEDGE, SUNNYDAY, SYNTHESIS, TAILWIND, TERRAINPULSE, TOXIC, WORKUP, ZENHEADBUTT, | AA35: =VLOOKUP($A35,'Moves Species'!$A:$E,5,FALSE) -> 0
A36: =A35+1 -> 35 | B36: [TYMPOLE] | C36: Tympole | D36: ='BST Extract'!J36 -> GRASS | E36: ='BST Extract'!K36 -> POISON | F36: =D36&","&E36 -> GRASS,POISON | G36: ='BST Extract'!C36 -> 50 | H36: ='BST Extract'!D36 -> 40 | I36: ='BST Extract'!E36 -> 55 | J36: ='BST Extract'!F36 -> 40 | K36: ='BST Extract'!G36 -> 55 | L36: ='BST Extract'!H36 -> 54 | M36: ='BST Extract'!I36 -> 294 | N36: SPECIAL_DEFENSE | O36: 1 | T36: =N36&","&O36&","&P36&","&Q36&","&R36&","&S36 -> SPECIAL_DEFENSE,1,,,, | U36: ='Ability Extract'!C36 -> EFFECTSPORE | V36: ='Ability Extract'!D36 -> DAMP | W36: ='Ability Extract'!E36 -> PROTEAN | X36: ='Ability Extract'!F36 -> EFFECTSPORE,DAMP,PROTEAN | Y36: =VLOOKUP($A36,'Moves Species'!$A:$E,3,FALSE) -> 1, MUDSLAP, 1, AQUARING, 1, ACID, 4, MEGADRAIN, 6, MUDSHACKLES, 8, POISONPOWDER, 11, VIRUS, 14, STUNSPORE, 17, MAGICALLEAF, 20, ALLERGY, 23, SLEEPPOWDER, 26, INFECTION, 29, ACIDARMOR, 32, GIGADRAIN, 35, BLIGHT, 38, MUDDYWATER, 41, SLUDGEBOMB, 44, ENERGYBALL, 48, SLUDGEWAVE, 52, SPORE, 56, ACIDRAIN, 60, NATURESWRATH, | Z36: =VLOOKUP($A36,'Moves Species'!$A:$E,4,FALSE) -> ACIDRAIN, ALLERGY, ATTRACT, BODYSLAM, BOUNCE, BULLETSEED, CATAPULT, CAUSTICACID, CLEARSMOG, DRAINPUNCH, EARTHPOWER, EARTHQUAKE, ENERGYBALL, ESSENCEBLOOM, GAIAPULSE, GIGADRAIN, GUNKSHOT, HIDDENPOWER, KNOCKOFF, LEAFBLADE, LEECHLIFE, MAGICALLEAF, MIASMA, MOSSYPUNCH, MUDSHACKLES, MUDSLIDE, NECTARTAP, PETALTEMPEST, PHOBIA, PINMISSILE, POISONJAB, POWERWHIP, PROTECT, REST, RETURN, ROCKBLAST, ROCKSLIDE, ROCKTOMB, SAFEGUARD, SCENTEDSHIELD, SEISMICCHANT, SLEEPTALK, SLUDGEBOMB, SLUDGEWAVE, SOLARBEAM, SPIKYSHIELD, STEALTHROCK, STRANGESTEAM, SUBMERGE, SUNNYDAY, SYNTHESIS, TERRAINPULSE, TOXIC, VENOMDRAIN, VITALITYDRAIN, WORKUP, ZENHEADBUTT, | AA36: =VLOOKUP($A36,'Moves Species'!$A:$E,5,FALSE) -> CLEARSMOG, AMNESIA, GRASSYGLIDE, VEXINGVINES, BELCH, TEATIME, ECTOPLASM, SLUDGE, GUTTURALROAR, AUTUMNBLAST, | AB36: PALPITOAD | AC36: Level | AD36: 23
A37: =A36+1 -> 36 | B37: [PALPITOAD] | C37: Palpitoad | D37: ='BST Extract'!J37 -> GRASS | E37: ='BST Extract'!K37 -> POISON | F37: =D37&","&E37 -> GRASS,POISON | G37: ='BST Extract'!C37 -> 75 | H37: ='BST Extract'!D37 -> 55 | I37: ='BST Extract'!E37 -> 75 | J37: ='BST Extract'!F37 -> 50 | K37: ='BST Extract'!G37 -> 69 | L37: ='BST Extract'!H37 -> 60 | M37: ='BST Extract'!I37 -> 384 | N37: SPECIAL_DEFENSE | O37: 2 | T37: =N37&","&O37&","&P37&","&Q37&","&R37&","&S37 -> SPECIAL_DEFENSE,2,,,, | U37: ='Ability Extract'!C37 -> EFFECTSPORE | V37: ='Ability Extract'!D37 -> DAMP | W37: ='Ability Extract'!E37 -> PROTEAN | X37: ='Ability Extract'!F37 -> EFFECTSPORE,DAMP,PROTEAN | Y37: =VLOOKUP($A37,'Moves Species'!$A:$E,3,FALSE) -> 0, TOXICSPIKES, 1, TOXICSPIKES, 1, MUDSLAP, 1, AQUARING, 1, ACID, 4, MEGADRAIN, 6, MUDSHACKLES, 8, POISONPOWDER, 11, VIRUS, 14, STUNSPORE, 17, MAGICALLEAF, 20, ALLERGY, 23, SLEEPPOWDER, 26, INFECTION, 29, ACIDARMOR, 32, GIGADRAIN, 35, BLIGHT, 38, MUDDYWATER, 41, SLUDGEBOMB, 44, ENERGYBALL, 48, SLUDGEWAVE, 52, SPORE, 56, ACIDRAIN, 60, NATURESWRATH, | Z37: =VLOOKUP($A37,'Moves Species'!$A:$E,4,FALSE) -> ACIDRAIN, ALLERGY, ATTRACT, BODYSLAM, BOUNCE, BULLETSEED, CATAPULT, CAUSTICACID, CLEARSMOG, DRAINPUNCH, EARTHPOWER, EARTHQUAKE, ENERGYBALL, ESSENCEBLOOM, GAIAPULSE, GIGADRAIN, GUNKSHOT, HIDDENPOWER, KNOCKOFF, LEAFBLADE, LEECHLIFE, MAGICALLEAF, MIASMA, MOSSYPUNCH, MUDSHACKLES, MUDSLIDE, NECTARTAP, PETALTEMPEST, PHOBIA, PINMISSILE, POISONJAB, POWERWHIP, PROTECT, REST, RETURN, ROCKBLAST, ROCKSLIDE, ROCKTOMB, SAFEGUARD, SCENTEDSHIELD, SEISMICCHANT, SLEEPTALK, SLUDGEBOMB, SLUDGEWAVE, SOLARBEAM, SPIKYSHIELD, STEALTHROCK, STRANGESTEAM, SUBMERGE, SUNNYDAY, SYNTHESIS, TERRAINPULSE, TOXIC, VENOMDRAIN, VITALITYDRAIN, WORKUP, ZENHEADBUTT, | AA37: =VLOOKUP($A37,'Moves Species'!$A:$E,5,FALSE) -> 0 | AB37: SEISMITOAD | AC37: Level | AD37: 38
A38: =A37+1 -> 37 | B38: [SEISMITOAD] | C38: Seismitoad | D38: ='BST Extract'!J38 -> GRASS | E38: ='BST Extract'!K38 -> POISON | F38: =D38&","&E38 -> GRASS,POISON | G38: ='BST Extract'!C38 -> 95 | H38: ='BST Extract'!D38 -> 70 | I38: ='BST Extract'!E38 -> 105 | J38: ='BST Extract'!F38 -> 70 | K38: ='BST Extract'!G38 -> 94 | L38: ='BST Extract'!H38 -> 75 | M38: ='BST Extract'!I38 -> 509 | N38: DEFENSE | O38: 1 | P38: SPECIAL_DEFENSE | Q38: 2 | T38: =N38&","&O38&","&P38&","&Q38&","&R38&","&S38 -> DEFENSE,1,SPECIAL_DEFENSE,2,, | U38: ='Ability Extract'!C38 -> EFFECTSPORE | V38: ='Ability Extract'!D38 -> DAMP | W38: ='Ability Extract'!E38 -> PROTEAN | X38: ='Ability Extract'!F38 -> EFFECTSPORE,DAMP,PROTEAN | Y38: =VLOOKUP($A38,'Moves Species'!$A:$E,3,FALSE) -> 1, TOXICSPIKES, 1, MUDSLAP, 1, AQUARING, 1, ACID, 4, MEGADRAIN, 6, MUDSHACKLES, 8, POISONPOWDER, 11, VIRUS, 14, STUNSPORE, 17, MAGICALLEAF, 20, ALLERGY, 23, SLEEPPOWDER, 26, INFECTION, 29, ACIDARMOR, 32, GIGADRAIN, 35, BLIGHT, 38, MUDDYWATER, 41, SLUDGEBOMB, 44, ENERGYBALL, 48, SLUDGEWAVE, 52, SPORE, 56, ACIDRAIN, 60, NATURESWRATH, | Z38: =VLOOKUP($A38,'Moves Species'!$A:$E,4,FALSE) -> ACIDRAIN, ALLERGY, ATTRACT, BODYSLAM, BOUNCE, BULLETSEED, CATAPULT, CAUSTICACID, CLEARSMOG, DRAINPUNCH, EARTHPOWER, EARTHQUAKE, ENERGYBALL, ESSENCEBLOOM, GAIAPULSE, GIGADRAIN, GUNKSHOT, HIDDENPOWER, KNOCKOFF, LEAFBLADE, LEECHLIFE, MAGICALLEAF, MIASMA, MOSSYPUNCH, MUDSHACKLES, MUDSLIDE, NECTARTAP, PETALTEMPEST, PHOBIA, PINMISSILE, POISONJAB, POWERWHIP, PROTECT, REST, RETURN, ROCKBLAST, ROCKSLIDE, ROCKTOMB, SAFEGUARD, SCENTEDSHIELD, SEISMICCHANT, SLEEPTALK, SLUDGEBOMB, SLUDGEWAVE, SOLARBEAM, SPIKYSHIELD, STEALTHROCK, STRANGESTEAM, SUBMERGE, SUNNYDAY, SYNTHESIS, TERRAINPULSE, TOXIC, VENOMDRAIN, VITALITYDRAIN, WORKUP, ZENHEADBUTT, | AA38: =VLOOKUP($A38,'Moves Species'!$A:$E,5,FALSE) -> 0
A39: =A38+1 -> 38 | B39: [GULPIN] | C39: Gulpin | D39: ='BST Extract'!J39 -> GROUND | E39: ='BST Extract'!K39 -> 0 | F39: =D39&","&E39 -> GROUND,0 | G39: ='BST Extract'!C39 -> 65 | H39: ='BST Extract'!D39 -> 33 | I39: ='BST Extract'!E39 -> 63 | J39: ='BST Extract'!F39 -> 25 | K39: ='BST Extract'!G39 -> 50 | L39: ='BST Extract'!H39 -> 76 | M39: ='BST Extract'!I39 -> 312 | N39: SPECIAL_DEFENSE | O39: 1 | T39: =N39&","&O39&","&P39&","&Q39&","&R39&","&S39 -> SPECIAL_DEFENSE,1,,,, | U39: ='Ability Extract'!C39 -> REGENERATOR | V39: ='Ability Extract'!D39 -> WATERABSORB | W39: ='Ability Extract'!E39 -> CLAYFORM | X39: ='Ability Extract'!F39 -> REGENERATOR,WATERABSORB,CLAYFORM | Y39: =VLOOKUP($A39,'Moves Species'!$A:$E,3,FALSE) -> 1, SANDSTORM, 1, SANDTOMB, 1, SANDATTACK, 4, SANDSPRAY, 6, SPIKES, 9, SANDJET, 12, BOULDERHURL, 15, DUNEBLAST, 18, YAWN, 21, STEALTHROCK, 24, SCORCHINGSANDS, 27, MINIMIZE, 30, GIGADRAIN, 33, DUSTDEVILS, 36, SHOREUP, 39, POWERGEM, 42, SANDFLURRY, 45, MUDDYWATER, 48, AMBERWAVE, 52, SANDSNARE, 56, SANDSHROUD, 60, MUDSURGE, | Z39: =VLOOKUP($A39,'Moves Species'!$A:$E,4,FALSE) -> ATTRACT, BEJEWELED, BODYPRESS, BODYSLAM, BULKUP, BULLDOZE, BULLETSEED, CALMMIND, CLEARSMOG, CRYSTALLINEBEAM, CRYSTALSHOWER, CURSE, DUNEBLAST, DUSTDEVILS, EARTHENLANCE, EARTHPOWER, EARTHQUAKE, ECHOEDVOICE, ENERGYBALL, FLUXWAVE, FOCUSBLAST, GAIAPULSE, GEOMANCY, GIGADRAIN, GOLDRUSH, HEATWAVE, HIDDENPOWER, HYPERVOICE, KNOCKOFF, MEMENTO, MUDSHACKLES, MUDSLIDE, OBSIDIANSHARDS, PIXIEDUST, PROTECT, QUICKSAND, REST, RETURN, ROCKBLAST, ROCKSLIDE, ROCKTOMB, SANDSTORM, SANDTOMB, SCALD, SEISMICCHANT, SLEEPTALK, SLUDGEBOMB, SOLARBEAM, SPIKES, STEALTHROCK, STEELROLLER, STONEEDGE, SUNNYDAY, SYNTHESIS, TERRAINPULSE, TOXIC, UTURN, WORKUP, ZENHEADBUTT, | AA39: =VLOOKUP($A39,'Moves Species'!$A:$E,5,FALSE) -> IRONDEFENSE, ROCKPOLISH, WIDEGUARD, GEOMANCY, MUDSPORT, MUDSHOT, BODYPRESS, HARDEN, TOXICSPIKES, AMNESIA, GEMSTORM, SLUDGEWAVE, MUDSLAP, MUDSLIDE, MUDBLAST, SANDWAVE, | AB39: SWALOT | AC39: Level | AD39: 31
A40: =A39+1 -> 39 | B40: [SWALOT] | C40: Swalot | D40: ='BST Extract'!J40 -> GROUND | E40: ='BST Extract'!K40 -> 0 | F40: =D40&","&E40 -> GROUND,0 | G40: ='BST Extract'!C40 -> 80 | H40: ='BST Extract'!D40 -> 50 | I40: ='BST Extract'!E40 -> 90 | J40: ='BST Extract'!F40 -> 40 | K40: ='BST Extract'!G40 -> 95 | L40: ='BST Extract'!H40 -> 120 | M40: ='BST Extract'!I40 -> 475 | N40: SPECIAL_DEFENSE | O40: 2 | T40: =N40&","&O40&","&P40&","&Q40&","&R40&","&S40 -> SPECIAL_DEFENSE,2,,,, | U40: ='Ability Extract'!C40 -> REGENERATOR | V40: ='Ability Extract'!D40 -> WATERABSORB | W40: ='Ability Extract'!E40 -> SANDSPIT | X40: ='Ability Extract'!F40 -> REGENERATOR,WATERABSORB,SANDSPIT | Y40: =VLOOKUP($A40,'Moves Species'!$A:$E,3,FALSE) -> 0, QUICKSAND, 1, QUICKSAND, 0, SANDPIT, 1, SANDPIT, 1, SANDSTORM, 1, SANDTOMB, 1, SANDATTACK, 4, SANDSPRAY, 6, SPIKES, 9, SANDJET, 12, BOULDERHURL, 15, DUNEBLAST, 18, YAWN, 21, STEALTHROCK, 24, SCORCHINGSANDS, 27, MINIMIZE, 30, GIGADRAIN, 33, DUSTDEVILS, 36, SHOREUP, 39, POWERGEM, 42, SANDFLURRY, 45, MUDDYWATER, 48, AMBERWAVE, 52, SANDSNARE, 56, SANDSHROUD, 60, MUDSURGE, | Z40: =VLOOKUP($A40,'Moves Species'!$A:$E,4,FALSE) -> ATTRACT, BEJEWELED, BODYPRESS, BODYSLAM, BULKUP, BULLDOZE, BULLETSEED, CALMMIND, CLEARSMOG, CRYSTALLINEBEAM, CRYSTALSHOWER, CURSE, DUNEBLAST, DUSTDEVILS, EARTHENLANCE, EARTHPOWER, EARTHQUAKE, ECHOEDVOICE, ENERGYBALL, FLUXWAVE, FOCUSBLAST, GAIAPULSE, GEOMANCY, GIGADRAIN, GOLDRUSH, HEATWAVE, HIDDENPOWER, HYPERVOICE, KNOCKOFF, MEMENTO, MUDSHACKLES, MUDSLIDE, OBSIDIANSHARDS, PIXIEDUST, PROTECT, QUICKSAND, REST, RETURN, ROCKBLAST, ROCKSLIDE, ROCKTOMB, SANDSTORM, SANDTOMB, SCALD, SEISMICCHANT, SLEEPTALK, SLUDGEBOMB, SOLARBEAM, SPIKES, STEALTHROCK, STEELROLLER, STONEEDGE, SUNNYDAY, SYNTHESIS, TERRAINPULSE, TOXIC, UTURN, WORKUP, ZENHEADBUTT, | AA40: =VLOOKUP($A40,'Moves Species'!$A:$E,5,FALSE) -> 0
A41: =A40+1 -> 40 | B41: [SPINARAK] | C41: Spinarak | D41: ='BST Extract'!J41 -> DARK | E41: ='BST Extract'!K41 -> POISON | F41: =D41&","&E41 -> DARK,POISON | G41: ='BST Extract'!C41 -> 55 | H41: ='BST Extract'!D41 -> 60 | I41: ='BST Extract'!E41 -> 50 | J41: ='BST Extract'!F41 -> 50 | K41: ='BST Extract'!G41 -> 35 | L41: ='BST Extract'!H41 -> 50 | M41: ='BST Extract'!I41 -> 300 | N41: ATTACK | O41: 1 | T41: =N41&","&O41&","&P41&","&Q41&","&R41&","&S41 -> ATTACK,1,,,, | U41: ='Ability Extract'!C41 -> POISONTOUCH | V41: ='Ability Extract'!D41 -> STAKEOUT | W41: ='Ability Extract'!E41 -> MERCILESS | X41: ='Ability Extract'!F41 -> POISONTOUCH,STAKEOUT,MERCILESS | Y41: =VLOOKUP($A41,'Moves Species'!$A:$E,3,FALSE) -> 1, LEER, 1, POISONSTING, 1, SPIDERWEB, 4, BACKSTABBING, 8, TORMENT, 11, POISONFANG, 14, TOXICSPIKES, 17, BITE, 20, TOXICTHREAD, 23, SPOIL, 26, PUNISHMENT, 29, OBSTRUCT, 32, VENOMDRAIN, 35, CRUNCH, 38, LUNGE, 41, NEUROTOXIN, 44, AMBUSH, 47, SWARMATTACK, 50, PLAGUE, 53, MEGAHORN, 56, SHADOWFORCE, 60, EXECUTION, | Z41: =VLOOKUP($A41,'Moves Species'!$A:$E,4,FALSE) -> AERIALACE, ALLERGY, AMBUSH, ATTRACT, BATTLEOFWITS, BLOODRITUAL, BUGBITE, BUGBUZZ, CAUSTICACID, CLEARSMOG, COVET, CRUNCH, CURSE, CURSEDTOUCH, DARKPULSE, DEFENDORDER, ECLIPSENOVA, ENERGYBALL, FALSESWIPE, FURYCUTTER, GASTROACID, GIGADRAIN, GOBLINSTRIKE, HIDDENPOWER, KNOCKOFF, LASHOUT, LEAFBLADE, LEECHLIFE, MEMENTO, MIASMA, NASTYPLOT, NATURESWRATH, NECTARTAP, PHANTOMFORCE, PHOBIA, PINMISSILE, PIXIEDUST, PLAYROUGH, POISONFANG, POISONJAB, PROTECT, PSYCHICFANGS, PSYCHICTERRAIN, QUICKGUARD, REST, RETURN, ROUND, SHADOWBALL, SLASH, SLEEPTALK, SLUDGEBOMB, SLUDGEWAVE, SOULRIP, SPIKES, STEALTHROCK, STRUGGLEBUG, SUBSTITUTE, SUNNYDAY, SWARMATTACK, SWARMOVERLOAD, SWITCHEROO, SWORDSDANCE, TAUNT, TOXIC, TOXICSPIKES, UMBRALWAVE, UTURN, VENDETTA, VENOMDRAIN, VITALITYDRAIN, WEAKSPOT, WORKUP, | AA41: =VLOOKUP($A41,'Moves Species'!$A:$E,5,FALSE) -> NIGHTSLASH, ELECTROWEB, CROSSPOISON, POISONJAB, PURSUIT, TWINEEDLE, SHADOWSNEAK, STICKYWEB, POWERTRIP, | AB41: ARIADOS | AC41: Level | AD41: 22
A42: =A41+1 -> 41 | B42: [ARIADOS] | C42: Ariados | D42: ='BST Extract'!J42 -> DARK | E42: ='BST Extract'!K42 -> POISON | F42: =D42&","&E42 -> DARK,POISON | G42: ='BST Extract'!C42 -> 80 | H42: ='BST Extract'!D42 -> 100 | I42: ='BST Extract'!E42 -> 70 | J42: ='BST Extract'!F42 -> 85 | K42: ='BST Extract'!G42 -> 55 | L42: ='BST Extract'!H42 -> 70 | M42: ='BST Extract'!I42 -> 460 | N42: ATTACK | O42: 2 | T42: =N42&","&O42&","&P42&","&Q42&","&R42&","&S42 -> ATTACK,2,,,, | U42: ='Ability Extract'!C42 -> POISONTOUCH | V42: ='Ability Extract'!D42 -> STAKEOUT | W42: ='Ability Extract'!E42 -> MERCILESS | X42: ='Ability Extract'!F42 -> POISONTOUCH,STAKEOUT,MERCILESS | Y42: =VLOOKUP($A42,'Moves Species'!$A:$E,3,FALSE) -> 0, VENDETTA, 1, VENDETTA, 1, LEER, 1, POISONSTING, 1, SPIDERWEB, 4, BACKSTABBING, 8, TORMENT, 11, POISONFANG, 14, TOXICSPIKES, 17, BITE, 20, TOXICTHREAD, 23, SPOIL, 26, PUNISHMENT, 29, OBSTRUCT, 32, VENOMDRAIN, 35, CRUNCH, 38, LUNGE, 41, NEUROTOXIN, 44, AMBUSH, 47, SWARMATTACK, 50, PLAGUE, 53, MEGAHORN, 56, SHADOWFORCE, 60, EXECUTION, | Z42: =VLOOKUP($A42,'Moves Species'!$A:$E,4,FALSE) -> AERIALACE, ALLERGY, AMBUSH, ATTRACT, BATTLEOFWITS, BLOODRITUAL, BUGBITE, BUGBUZZ, CAUSTICACID, CLEARSMOG, COVET, CRUNCH, CURSE, CURSEDTOUCH, DARKPULSE, DEFENDORDER, ECLIPSENOVA, ENERGYBALL, FALSESWIPE, FURYCUTTER, GASTROACID, GIGADRAIN, GOBLINSTRIKE, HIDDENPOWER, KNOCKOFF, LASHOUT, LEAFBLADE, LEECHLIFE, MEMENTO, MIASMA, NASTYPLOT, NATURESWRATH, NECTARTAP, PHANTOMFORCE, PHOBIA, PINMISSILE, PIXIEDUST, PLAYROUGH, POISONFANG, POISONJAB, PROTECT, PSYCHICFANGS, PSYCHICTERRAIN, QUICKGUARD, REST, RETURN, ROUND, SHADOWBALL, SLASH, SLEEPTALK, SLUDGEBOMB, SLUDGEWAVE, SOULRIP, SPIKES, STEALTHROCK, STRUGGLEBUG, SUBSTITUTE, SUNNYDAY, SWARMATTACK, SWARMOVERLOAD, SWITCHEROO, SWORDSDANCE, TAUNT, TOXIC, TOXICSPIKES, UMBRALWAVE, UTURN, VENDETTA, VENOMDRAIN, VITALITYDRAIN, WEAKSPOT, WORKUP, | AA42: =VLOOKUP($A42,'Moves Species'!$A:$E,5,FALSE) -> 0
A43: =A42+1 -> 42 | B43: [BALTOY] | C43: Baltoy | D43: ='BST Extract'!J43 -> ELECTRIC | E43: ='BST Extract'!K43 -> PSYCHIC | F43: =D43&","&E43 -> ELECTRIC,PSYCHIC | G43: ='BST Extract'!C43 -> 60 | H43: ='BST Extract'!D43 -> 20 | I43: ='BST Extract'!E43 -> 55 | J43: ='BST Extract'!F43 -> 55 | K43: ='BST Extract'!G43 -> 40 | L43: ='BST Extract'!H43 -> 70 | M43: ='BST Extract'!I43 -> 300 | N43: SPECIAL_DEFENSE | O43: 1 | T43: =N43&","&O43&","&P43&","&Q43&","&R43&","&S43 -> SPECIAL_DEFENSE,1,,,, | U43: ='Ability Extract'!C43 -> LEVITATE | V43: ='Ability Extract'!D43 -> CLEARBODY | W43: ='Ability Extract'!E43 -> OWNTEMPO | X43: ='Ability Extract'!F43 -> LEVITATE,CLEARBODY,OWNTEMPO | Y43: =VLOOKUP($A43,'Moves Species'!$A:$E,3,FALSE) -> 1, CHARGE, 1, THUNDERSHOCK, 4, CONFUSION, 6, TELEKINESIS, 8, BARRIER, 11, SHOCKWAVE, 14, LIGHTSCREEN, 14, REFLECT, 17, PSYBEAM, 21, CHARGEBEAM, 25, MAGNETICFLUX, 25, GEARUP, 28, RISINGVOLTAGE, 31, EXTRASENSORY, 34, AUTOTOMIZE, 37, DISCHARGE, 40, PSYBLAST, 43, MAGNETFORCE, 46, EXPANDINGFORCE, 49, FLASHCANNON, 52, LOCKON, 52, ZAPCANNON, 55, FUTURESIGHT, 58, STOREDPOWER, 62, ARCANEENERGY, | Z43: =VLOOKUP($A43,'Moves Species'!$A:$E,4,FALSE) -> ANTIMATTER, ARCANEENERGY, ASTRALWIND, AURASPHERE, BALLLIGHTNING, BATTLEOFWITS, BOLTCRASH, CALMMIND, CHARGEBEAM, CLEANSE, CONFUSERAY, COSMICPOWER, COVET, DARKPULSE, DAZZLINGGLEAM, EARTHPOWER, ECLIPSENOVA, ELECTRICTERRAIN, ELECTRONCRUSH, ENERGYSURGE, EXPANDINGFORCE, FANTASYSEAL, FLUXWAVE, FOCUSBLAST, GAMMARAY, GLISTEN, GOLDENBULLET, HEXBOLT, HIDDENPOWER, IRONDEFENSE, IRONHEAD, IRONIMPACT, IRONTEMPEST, KAMEHAMEHA, LIGHTSCREEN, MAGNETICCANNON, MAGNETRISE, MEMENTO, MINDMELD, MIRRORSHOT, MISSILESHOT, MIXEDWAVES, MYSTICPULSE, NASTYPLOT, OVERCLOCK, PARABOLICCHARGE, PIXIEDUST, POWERGEM, PROTECT, PSYCHIC, PSYCHICTERRAIN, REFLECT, REST, RETURN, RISINGVOLTAGE, SAFEGUARD, SATELLITERAY, SEISMICCHANT, SHADOWBALL, SIGNALBEAM, SLEEPTALK, TERRAINPULSE, THUNDER, THUNDERBOLT, THUNDERWAVE, TOXIC, TRIATTACK, VOLTSWITCH, WILDCHARGE, | AA43: =VLOOKUP($A43,'Moves Species'!$A:$E,5,FALSE) -> 0 | AB43: CLAYDOL | AC43: Level | AD43: 36
A44: =A43+1 -> 43 | B44: [CLAYDOL] | C44: Claydol | D44: ='BST Extract'!J44 -> ELECTRIC | E44: ='BST Extract'!K44 -> PSYCHIC | F44: =D44&","&E44 -> ELECTRIC,PSYCHIC | G44: ='BST Extract'!C44 -> 100 | H44: ='BST Extract'!D44 -> 50 | I44: ='BST Extract'!E44 -> 85 | J44: ='BST Extract'!F44 -> 75 | K44: ='BST Extract'!G44 -> 95 | L44: ='BST Extract'!H44 -> 95 | M44: ='BST Extract'!I44 -> 500 | N44: SPECIAL_DEFENSE | O44: 2 | T44: =N44&","&O44&","&P44&","&Q44&","&R44&","&S44 -> SPECIAL_DEFENSE,2,,,, | U44: ='Ability Extract'!C44 -> LEVITATE | V44: ='Ability Extract'!D44 -> CLEARBODY | W44: ='Ability Extract'!E44 -> PSYCHICSURGE | X44: ='Ability Extract'!F44 -> LEVITATE,CLEARBODY,PSYCHICSURGE | Y44: =VLOOKUP($A44,'Moves Species'!$A:$E,3,FALSE) -> 1, CHARGE, 1, THUNDERSHOCK, 4, CONFUSION, 6, TELEKINESIS, 8, BARRIER, 11, SHOCKWAVE, 14, LIGHTSCREEN, 14, REFLECT, 17, PSYBEAM, 21, CHARGEBEAM, 25, MAGNETICFLUX, 25, GEARUP, 28, RISINGVOLTAGE, 31, EXTRASENSORY, 34, AUTOTOMIZE, 37, DISCHARGE, 40, PSYBLAST, 43, MAGNETFORCE, 46, EXPANDINGFORCE, 49, FLASHCANNON, 52, LOCKON, 52, ZAPCANNON, 55, FUTURESIGHT, 58, STOREDPOWER, 62, ARCANEENERGY, | Z44: =VLOOKUP($A44,'Moves Species'!$A:$E,4,FALSE) -> ANTIMATTER, ARCANEENERGY, ASTRALWIND, AURASPHERE, BALLLIGHTNING, BATTLEOFWITS, BOLTCRASH, CALMMIND, CHARGEBEAM, CLEANSE, CONFUSERAY, COSMICPOWER, COVET, DARKPULSE, DAZZLINGGLEAM, EARTHPOWER, ECLIPSENOVA, ELECTRICTERRAIN, ELECTRONCRUSH, ENERGYSURGE, EXPANDINGFORCE, FANTASYSEAL, FLUXWAVE, FOCUSBLAST, GAMMARAY, GLISTEN, GOLDENBULLET, HEXBOLT, HIDDENPOWER, IRONDEFENSE, IRONHEAD, IRONIMPACT, IRONTEMPEST, KAMEHAMEHA, LIGHTSCREEN, MAGNETICCANNON, MAGNETRISE, MEMENTO, MINDMELD, MIRRORSHOT, MISSILESHOT, MIXEDWAVES, MYSTICPULSE, NASTYPLOT, OVERCLOCK, PARABOLICCHARGE, PIXIEDUST, POWERGEM, PROTECT, PSYCHIC, PSYCHICTERRAIN, REFLECT, REST, RETURN, RISINGVOLTAGE, SAFEGUARD, SATELLITERAY, SEISMICCHANT, SHADOWBALL, SIGNALBEAM, SLEEPTALK, TERRAINPULSE, THUNDER, THUNDERBOLT, THUNDERWAVE, TOXIC, TRIATTACK, VOLTSWITCH, WILDCHARGE, | AA44: =VLOOKUP($A44,'Moves Species'!$A:$E,5,FALSE) -> 0
A45: =A44+1 -> 44 | B45: [ZORUA] | C45: Zorua | D45: ='BST Extract'!J45 -> ICE | E45: ='BST Extract'!K45 -> DARK | F45: =D45&","&E45 -> ICE,DARK | G45: ='BST Extract'!C45 -> 40 | H45: ='BST Extract'!D45 -> 75 | I45: ='BST Extract'!E45 -> 40 | J45: ='BST Extract'!F45 -> 75 | K45: ='BST Extract'!G45 -> 60 | L45: ='BST Extract'!H45 -> 40 | M45: ='BST Extract'!I45 -> 330 | N45: ATTACK | O45: 1 | T45: =N45&","&O45&","&P45&","&Q45&","&R45&","&S45 -> ATTACK,1,,,, | U45: ='Ability Extract'!C45 -> SNOWCLOAK | V45: ='Ability Extract'!D45 -> MOXIE | W45: ='Ability Extract'!E45 -> MERCILESS | X45: ='Ability Extract'!F45 -> SNOWCLOAK,MOXIE,MERCILESS | Y45: =VLOOKUP($A45,'Moves Species'!$A:$E,3,FALSE) -> 1, SCRATCH, 1, LEER, 1, PURSUIT, 4, SNOWBALL, 6, FROSTNIP, 9, GOBLINSTRIKE, 11, SNARL, 14, BITE, 17, ICEFANG, 20, SCARYFACE, 23, SLASH, 26, NIGHTSLASH, 29, SWAGGER, 32, CRUSHCLAW, 35, CRUNCH, 38, TUNDRARUSH, 42, AMBUSH, 45, FROSTBITE, 48, PLAYROUGH, 52, FRENZY, 56, HONECLAWS, 60, WINTERSHOWL, | Z45: =VLOOKUP($A45,'Moves Species'!$A:$E,4,FALSE) -> AERIALACE, AMBUSH, ATTRACT, BLIZZARD, BONECHILL, BRICKBREAK, CHARM, CHILLINGTOUCH, COUPDEGRACE, COVET, CRUNCH, CURSEDTOUCH, DARKPULSE, DRAGONCLAW, DRAGONDANCE, ECHOEDVOICE, ECLIPSENOVA, EXECUTION, FALSESWIPE, FANTASYSEAL, FIREFANG, FURYCUTTER, GOBLINSTRIKE, HAIL, HIDDENPOWER, HYPERVOICE, HYPOTHERMIA, ICEBEAM, ICEFANG, ICEHAMMER, ICEPUNCH, ICICLESPEAR, ICICLESTRIKE, ICYWIND, IRONHEAD, KNOCKOFF, LASHOUT, LOVEBURST, MEMENTO, MIST, NASTYPLOT, NOBLEROAR, NUMBINGWIND, PHANTOMFORCE, PLAYROUGH, POWERUPPUNCH, PROTECT, PSYCHICFANGS, QUICKGUARD, REST, RETURN, SHADOWBALL, SHADOWPUNCH, SLASH, SLEEPTALK, SNARL, SONICBLAST, SOULRIP, STELLARRUSH, SWITCHEROO, SWORDSDANCE, TAUNT, TOXIC, TRIPLEAXEL, UMBRALWAVE, VITALITYDRAIN, WAIL, WEAKSPOT, WORKUP, ZENHEADBUTT, | AA45: =VLOOKUP($A45,'Moves Species'!$A:$E,5,FALSE) -> KNOCKOFF, VENDETTA, PARTINGSHOT, WICKEDSTRIKE, DARKESTLARIAT, PSYCHICFANGS, BRICKBREAK, ICICLECRASH, ICESHARD, HELPINGHAND, | AB45: ZOROARK | AC45: Item | AD45: ICESTONE
A46: =A45+1 -> 45 | B46: [ZOROARK] | C46: Zoroark | D46: ='BST Extract'!J46 -> ICE | E46: ='BST Extract'!K46 -> DARK | F46: =D46&","&E46 -> ICE,DARK | G46: ='BST Extract'!C46 -> 70 | H46: ='BST Extract'!D46 -> 115 | I46: ='BST Extract'!E46 -> 60 | J46: ='BST Extract'!F46 -> 115 | K46: ='BST Extract'!G46 -> 90 | L46: ='BST Extract'!H46 -> 60 | M46: ='BST Extract'!I46 -> 510 | N46: ATTACK | O46: 2 | T46: =N46&","&O46&","&P46&","&Q46&","&R46&","&S46 -> ATTACK,2,,,, | U46: ='Ability Extract'!C46 -> SNOWCLOAK | V46: ='Ability Extract'!D46 -> MOXIE | W46: ='Ability Extract'!E46 -> MERCILESS | X46: ='Ability Extract'!F46 -> SNOWCLOAK,MOXIE,MERCILESS | Y46: =VLOOKUP($A46,'Moves Species'!$A:$E,3,FALSE) -> 0, ICEPUNCH, 1, ICEPUNCH, 1, SCRATCH, 1, LEER, 1, PURSUIT, 4, SNOWBALL, 6, FROSTNIP, 9, GOBLINSTRIKE, 11, SNARL, 14, BITE, 17, ICEFANG, 20, SCARYFACE, 23, SLASH, 26, NIGHTSLASH, 29, SWAGGER, 32, CRUSHCLAW, 35, CRUNCH, 38, TUNDRARUSH, 42, AMBUSH, 45, FROSTBITE, 48, PLAYROUGH, 52, FRENZY, 56, HONECLAWS, 60, WINTERSHOWL, | Z46: =VLOOKUP($A46,'Moves Species'!$A:$E,4,FALSE) -> AERIALACE, AMBUSH, ATTRACT, BLIZZARD, BONECHILL, BRICKBREAK, CHARM, CHILLINGTOUCH, COUPDEGRACE, COVET, CRUNCH, CURSEDTOUCH, DARKPULSE, DRAGONCLAW, DRAGONDANCE, ECHOEDVOICE, ECLIPSENOVA, EXECUTION, FALSESWIPE, FANTASYSEAL, FIREFANG, FURYCUTTER, GOBLINSTRIKE, HAIL, HIDDENPOWER, HYPERVOICE, HYPOTHERMIA, ICEBEAM, ICEFANG, ICEHAMMER, ICEPUNCH, ICICLESPEAR, ICICLESTRIKE, ICYWIND, IRONHEAD, KNOCKOFF, LASHOUT, LOVEBURST, MEMENTO, MIST, NASTYPLOT, NOBLEROAR, NUMBINGWIND, PHANTOMFORCE, PLAYROUGH, POWERUPPUNCH, PROTECT, PSYCHICFANGS, QUICKGUARD, REST, RETURN, SHADOWBALL, SHADOWPUNCH, SLASH, SLEEPTALK, SNARL, SONICBLAST, SOULRIP, STELLARRUSH, SWITCHEROO, SWORDSDANCE, TAUNT, TOXIC, TRIPLEAXEL, UMBRALWAVE, VITALITYDRAIN, WAIL, WEAKSPOT, WORKUP, ZENHEADBUTT, | AA46: =VLOOKUP($A46,'Moves Species'!$A:$E,5,FALSE) -> 0
A47: =A46+1 -> 46 | B47: [DUCKLETT] | C47: Ducklett | D47: ='BST Extract'!J47 -> LIGHT | E47: ='BST Extract'!K47 -> FLYING | F47: =D47&","&E47 -> LIGHT,FLYING | G47: ='BST Extract'!C47 -> 62 | H47: ='BST Extract'!D47 -> 39 | I47: ='BST Extract'!E47 -> 40 | J47: ='BST Extract'!F47 -> 65 | K47: ='BST Extract'!G47 -> 64 | L47: ='BST Extract'!H47 -> 60 | M47: ='BST Extract'!I47 -> 330 | N47: SPEED | O47: 1 | T47: =N47&","&O47&","&P47&","&Q47&","&R47&","&S47 -> SPEED,1,,,, | U47: ='Ability Extract'!C47 -> FRIENDGUARD | V47: ='Ability Extract'!D47 -> SERENEGRACE | W47: ='Ability Extract'!E47 -> EARLYBIRD | X47: ='Ability Extract'!F47 -> FRIENDGUARD,SERENEGRACE,EARLYBIRD | Y47: =VLOOKUP($A47,'Moves Species'!$A:$E,3,FALSE) -> 1, SWEETKISS, 1, RENEWAL, 4, GALEHOLD, 7, SAFEGUARD, 10, AURORABEAM, 13, HALLOWEDGROUND, 16, SWANSONG, 19, HALLELUJAH, 22, FLASH, 25, SIRENSSONG, 28, SIGNALBEAM, 31, AIRSLASH, 34, ROOST, 37, SHINYPLUMES, 40, TYPHOON, 43, APHRODITESMIRROR, 46, BLINDINGFLASH, 49, AERIALPULSE, 52, TITANIASLAW, 56, DIVINEPUNISHMENT, 60, HURRICANE, | Z47: =VLOOKUP($A47,'Moves Species'!$A:$E,4,FALSE) -> ACROBATICS, AERIALACE, AERIALPULSE, AIRSLASH, ASTRALWIND, ATTRACT, AURASPHERE, BLIZZARD, BRAVEBIRD, BRINE, CLEANSE, COVET, DAZZLINGGLEAM, DEFOG, DIVINEPUNISHMENT, DRILLPECK, DUALWINGBEAT, ECHOEDVOICE, FABLEDRUSH, FAIRYTALE, FANTASYSEAL, FLOCK, FLUTTER, FLUXWAVE, GENESIS, GENTLECHIMES, HAIL, HIDDENPOWER, HOLYNOVA, HURRICANE, HYPERVOICE, ICEBEAM, ICYWIND, LIGHTSCREEN, LOVEBURST, MAGICROOM, MIST, MISTYTERRAIN, MYSTICPULSE, NUMBINGWIND, ODETOJOY, OVERFLOW, PAYDAY, PIXIEDUST, PLAYROUGH, PROTECT, PURGE, RADIANTLANCE, RAYOFLIGHT, REFLECT, REST, RETURN, ROUND, SACREDSTRIKE, SAFEGUARD, SIGNALBEAM, SLEEPTALK, STEELWING, STRANGESTEAM, SUBMERGE, SUNNYDAY, SYNTHESIS, TAILWIND, TEMPESTFLARE, TERRAINPULSE, TITANIASLAW, TOXIC, VALKYRIECHARIOT, WATERPULSE, WONDERROOM, WORKUP, | AA47: =VLOOKUP($A47,'Moves Species'!$A:$E,5,FALSE) -> FAESBLESSING, DECORATE, MYSTICPULSE, TAILWIND, SPOTLIGHT, BOREASBREATH, GUARDIANANGEL, REVITALIZE, EROSION, FLASHCANNON, | AB47: SWANNA | AC47: Level | AD47: 32
A48: =A47+1 -> 47 | B48: [SWANNA] | C48: Swanna | D48: ='BST Extract'!J48 -> LIGHT | E48: ='BST Extract'!K48 -> FLYING | F48: =D48&","&E48 -> LIGHT,FLYING | G48: ='BST Extract'!C48 -> 70 | H48: ='BST Extract'!D48 -> 62 | I48: ='BST Extract'!E48 -> 63 | J48: ='BST Extract'!F48 -> 110 | K48: ='BST Extract'!G48 -> 95 | L48: ='BST Extract'!H48 -> 90 | M48: ='BST Extract'!I48 -> 490 | N48: SPEED | O48: 2 | T48: =N48&","&O48&","&P48&","&Q48&","&R48&","&S48 -> SPEED,2,,,, | U48: ='Ability Extract'!C48 -> FRIENDGUARD | V48: ='Ability Extract'!D48 -> SERENEGRACE | W48: ='Ability Extract'!E48 -> EARLYBIRD | X48: ='Ability Extract'!F48 -> FRIENDGUARD,SERENEGRACE,EARLYBIRD | Y48: =VLOOKUP($A48,'Moves Species'!$A:$E,3,FALSE) -> 1, SWEETKISS, 1, RENEWAL, 4, GALEHOLD, 7, SAFEGUARD, 10, AURORABEAM, 13, HALLOWEDGROUND, 16, SWANSONG, 19, HALLELUJAH, 22, FLASH, 25, SIRENSSONG, 28, SIGNALBEAM, 31, AIRSLASH, 34, ROOST, 37, SHINYPLUMES, 40, TYPHOON, 43, APHRODITESMIRROR, 46, BLINDINGFLASH, 49, AERIALPULSE, 52, TITANIASLAW, 56, DIVINEPUNISHMENT, 60, HURRICANE, | Z48: =VLOOKUP($A48,'Moves Species'!$A:$E,4,FALSE) -> ACROBATICS, AERIALACE, AERIALPULSE, AIRSLASH, ASTRALWIND, ATTRACT, AURASPHERE, BLIZZARD, BRAVEBIRD, BRINE, CLEANSE, COVET, DAZZLINGGLEAM, DEFOG, DIVINEPUNISHMENT, DRILLPECK, DUALWINGBEAT, ECHOEDVOICE, FABLEDRUSH, FAIRYTALE, FANTASYSEAL, FLOCK, FLUTTER, FLUXWAVE, GENESIS, GENTLECHIMES, HAIL, HIDDENPOWER, HOLYNOVA, HURRICANE, HYPERVOICE, ICEBEAM, ICYWIND, LIGHTSCREEN, LOVEBURST, MAGICROOM, MIST, MISTYTERRAIN, MYSTICPULSE, NUMBINGWIND, ODETOJOY, OVERFLOW, PAYDAY, PIXIEDUST, PLAYROUGH, PROTECT, PURGE, RADIANTLANCE, RAYOFLIGHT, REFLECT, REST, RETURN, ROUND, SACREDSTRIKE, SAFEGUARD, SIGNALBEAM, SLEEPTALK, STEELWING, STRANGESTEAM, SUBMERGE, SUNNYDAY, SYNTHESIS, TAILWIND, TEMPESTFLARE, TERRAINPULSE, TITANIASLAW, TOXIC, VALKYRIECHARIOT, WATERPULSE, WONDERROOM, WORKUP, | AA48: =VLOOKUP($A48,'Moves Species'!$A:$E,5,FALSE) -> 0
A49: =A48+1 -> 48 | B49: [GOLETT] | C49: Golett | D49: ='BST Extract'!J49 -> STEEL | E49: ='BST Extract'!K49 -> PSYCHIC | F49: =D49&","&E49 -> STEEL,PSYCHIC | G49: ='BST Extract'!C49 -> 64 | H49: ='BST Extract'!D49 -> 69 | I49: ='BST Extract'!E49 -> 65 | J49: ='BST Extract'!F49 -> 35 | K49: ='BST Extract'!G49 -> 45 | L49: ='BST Extract'!H49 -> 45 | M49: ='BST Extract'!I49 -> 323 | N49: ATTACK | O49: 1 | T49: =N49&","&O49&","&P49&","&Q49&","&R49&","&S49 -> ATTACK,1,,,, | U49: ='Ability Extract'!C49 -> LONGREACH | V49: ='Ability Extract'!D49 -> IRONFIST | W49: ='Ability Extract'!E49 -> SUPERCONDUCTIVE | X49: ='Ability Extract'!F49 -> LONGREACH,IRONFIST,SUPERCONDUCTIVE | Y49: =VLOOKUP($A49,'Moves Species'!$A:$E,3,FALSE) -> 1, POUND, 1, MINDBLAST, 1, CONFUSERAY, 4, BULLETPUNCH, 8, MIXEDWAVES, 12, AUTOTOMIZE, 15, MEMORYBLOCK, 18, VISEGRIP, 21, IRONDEFENSE, 23, FIREPUNCH, 25, ICEPUNCH, 27, THUNDERPUNCH, 30, POWERDRILL, 33, ZENHEADBUTT, 36, COSMICPOWER, 39, IRONHEAD, 42, MAGNETRISE, 45, SCRAMBLEMIND, 48, METEORMASH, 52, HAMMERARM, 56, MANICOVERLOAD, 60, DOUBLEIRONBASH, | Z49: =VLOOKUP($A49,'Moves Species'!$A:$E,4,FALSE) -> ANTIMATTER, ASTEROIDBELT, AURASPHERE, BALLLIGHTNING, BEJEWELED, BODYPRESS, BODYSLAM, BOMBARDMENT, BRICKBREAK, BULKUP, BULLDOZE, CALMMIND, CHARGEBEAM, CLEANSE, CLUSTERROCKETS, CONFUSERAY, COSMICPOWER, CRYSTALLINEBEAM, CURSEDTOUCH, DARKPULSE, DAZZLINGGLEAM, DRAINPUNCH, EARTHENLANCE, EARTHPOWER, EARTHQUAKE, ELECTRICTERRAIN, ELECTRONCRUSH, ENDERSHOCK, ENERGYSURGE, FIREPUNCH, FLAMECHARGE, FLAREBLITZ, FLUXWAVE, GAMMARAY, GOLDENBULLET, GYROBALL, HEAVENSKNUCKLE, HEXBOLT, HIDDENPOWER, ICEBEAM, ICEHAMMER, ICEPUNCH, IRONDEFENSE, IRONHEAD, IRONIMPACT, IRONTEMPEST, KNOCKOFF, LASHOUT, LIGHTSCREEN, MAGICROOM, MAGNETRISE, METEORBEAM, METEORDRIVE, METEORMASH, METRONOME, MINDMELD, MIRRORSHOT, MISSILESHOT, MIXEDWAVES, MUDSLIDE, MYSTICPULSE, NASTYPLOT, NEBULASTRIKE, OVERCLOCK, PARABOLICCHARGE, PROTECT, RADIANTLANCE, REFLECT, REFURBISH, REST, RETURN, ROCKBLAST, ROCKSLIDE, ROCKTOMB, SATELLITERAY, SHADOWBALL, SHADOWPUNCH, SLEEPTALK, SOULRIP, STEELROLLER, STELLARRUSH, SUPERPOWER, SWIFT, TERRAINPULSE, THUNDERBOLT, THUNDERPUNCH, TOXIC, VOLTSWITCH, WILDCHARGE, WONDERROOM, WORKUP, ZENHEADBUTT, | AA49: =VLOOKUP($A49,'Moves Species'!$A:$E,5,FALSE) -> 0 | AB49: GOLURK | AC49: Level | AD49: 43
A50: =A49+1 -> 49 | B50: [GOLURK] | C50: Golurk | D50: ='BST Extract'!J50 -> STEEL | E50: ='BST Extract'!K50 -> PSYCHIC | F50: =D50&","&E50 -> STEEL,PSYCHIC | G50: ='BST Extract'!C50 -> 94 | H50: ='BST Extract'!D50 -> 99 | I50: ='BST Extract'!E50 -> 105 | J50: ='BST Extract'!F50 -> 55 | K50: ='BST Extract'!G50 -> 75 | L50: ='BST Extract'!H50 -> 75 | M50: ='BST Extract'!I50 -> 503 | N50: ATTACK | O50: 2 | T50: =N50&","&O50&","&P50&","&Q50&","&R50&","&S50 -> ATTACK,2,,,, | U50: ='Ability Extract'!C50 -> LONGREACH | V50: ='Ability Extract'!D50 -> IRONFIST | W50: ='Ability Extract'!E50 -> SUPERCONDUCTIVE | X50: ='Ability Extract'!F50 -> LONGREACH,IRONFIST,SUPERCONDUCTIVE | Y50: =VLOOKUP($A50,'Moves Species'!$A:$E,3,FALSE) -> 1, POUND, 1, MINDBLAST, 1, CONFUSERAY, 4, BULLETPUNCH, 8, MIXEDWAVES, 12, AUTOTOMIZE, 15, MEMORYBLOCK, 18, VISEGRIP, 21, IRONDEFENSE, 23, FIREPUNCH, 25, ICEPUNCH, 27, THUNDERPUNCH, 30, POWERDRILL, 33, ZENHEADBUTT, 36, COSMICPOWER, 39, IRONHEAD, 42, MAGNETRISE, 45, SCRAMBLEMIND, 48, METEORMASH, 52, HAMMERARM, 56, MANICOVERLOAD, 60, DOUBLEIRONBASH, | Z50: =VLOOKUP($A50,'Moves Species'!$A:$E,4,FALSE) -> ANTIMATTER, ASTEROIDBELT, AURASPHERE, BALLLIGHTNING, BEJEWELED, BODYPRESS, BODYSLAM, BOMBARDMENT, BRICKBREAK, BULKUP, BULLDOZE, CALMMIND, CHARGEBEAM, CLEANSE, CLUSTERROCKETS, CONFUSERAY, COSMICPOWER, CRYSTALLINEBEAM, CURSEDTOUCH, DARKPULSE, DAZZLINGGLEAM, DRAINPUNCH, EARTHENLANCE, EARTHPOWER, EARTHQUAKE, ELECTRICTERRAIN, ELECTRONCRUSH, ENDERSHOCK, ENERGYSURGE, FIREPUNCH, FLAMECHARGE, FLAREBLITZ, FLUXWAVE, GAMMARAY, GOLDENBULLET, GYROBALL, HEAVENSKNUCKLE, HEXBOLT, HIDDENPOWER, ICEBEAM, ICEHAMMER, ICEPUNCH, IRONDEFENSE, IRONHEAD, IRONIMPACT, IRONTEMPEST, KNOCKOFF, LASHOUT, LIGHTSCREEN, MAGICROOM, MAGNETRISE, METEORBEAM, METEORDRIVE, METEORMASH, METRONOME, MINDMELD, MIRRORSHOT, MISSILESHOT, MIXEDWAVES, MUDSLIDE, MYSTICPULSE, NASTYPLOT, NEBULASTRIKE, OVERCLOCK, PARABOLICCHARGE, PROTECT, RADIANTLANCE, REFLECT, REFURBISH, REST, RETURN, ROCKBLAST, ROCKSLIDE, ROCKTOMB, SATELLITERAY, SHADOWBALL, SHADOWPUNCH, SLEEPTALK, SOULRIP, STEELROLLER, STELLARRUSH, SUPERPOWER, SWIFT, TERRAINPULSE, THUNDERBOLT, THUNDERPUNCH, TOXIC, VOLTSWITCH, WILDCHARGE, WONDERROOM, WORKUP, ZENHEADBUTT, | AA50: =VLOOKUP($A50,'Moves Species'!$A:$E,5,FALSE) -> 0
A51: =A50+1 -> 50 | B51: [MORELULL] | C51: Morelull | D51: ='BST Extract'!J51 -> GHOST | E51: ='BST Extract'!K51 -> GRASS | F51: =D51&","&E51 -> GHOST,GRASS | G51: ='BST Extract'!C51 -> 60 | H51: ='BST Extract'!D51 -> 45 | I51: ='BST Extract'!E51 -> 55 | J51: ='BST Extract'!F51 -> 30 | K51: ='BST Extract'!G51 -> 60 | L51: ='BST Extract'!H51 -> 80 | M51: ='BST Extract'!I51 -> 330 | N51: SPECIAL_DEFENSE | O51: 1 | T51: =N51&","&O51&","&P51&","&Q51&","&R51&","&S51 -> SPECIAL_DEFENSE,1,,,, | U51: ='Ability Extract'!C51 -> BADDREAMS | V51: ='Ability Extract'!D51 -> TORMENTED | W51: ='Ability Extract'!E51 -> CURIOUSMEDICINE | X51: ='Ability Extract'!F51 -> BADDREAMS,TORMENTED,CURIOUSMEDICINE | Y51: =VLOOKUP($A51,'Moves Species'!$A:$E,3,FALSE) -> 1, HEALBLOCK, 1, CONFUSERAY, 1, GOOSEBUMP, 4, MEGADRAIN, 7, STUNSPORE, 7, POISONPOWDER, 11, SHIVER, 14, SLEEPPOWDER, 17, MAGICALLEAF, 20, GASTROACID, 23, HEX, 26, VEXINGVINES, 29, GIGADRAIN, 32, SHADOWBALL, 35, SPORE, 35, DREAMEATER, 35, NIGHTMARE, 38, SLUDGEBOMB, 41, ENERGYBALL, 44, MOONLIGHT, 47, ECTOPLASM, 50, STRENGTHSAP, 53, LEAFSTORM, 56, UMBRALWAVE, 60, DEATHWALTZ, | Z51: =VLOOKUP($A51,'Moves Species'!$A:$E,4,FALSE) -> ACIDRAIN, ALLERGY, AROMATHERAPY, ATTRACT, BONECHILL, BULLETSEED, CAUSTICACID, CHILLINGTOUCH, CLEARSMOG, CONCOCTION, CONFUSERAY, CORROSIVEGAS, CURSEDTOUCH, DARKPULSE, DAZZLINGGLEAM, ECLIPSENOVA, ENERGYBALL, ESSENCEBLOOM, FLUXWAVE, GASTROACID, GHASTLYFLOOD, GIGADRAIN, GOSSIP, GRASSYTERRAIN, GUNKSHOT, HAZE, HEX, HIDDENPOWER, LEAFBLADE, MACABREDANCE, MAGICALLEAF, MAGICROOM, MIASMA, MIXEDWAVES, NASTYPLOT, NECTARTAP, PETALTEMPEST, PHANTOMFORCE, PHOBIA, PIXIEDUST, POISONJAB, POLLENPUFF, POLTERGEIST, POSSESSION, PROTECT, PSYCHIC, PSYCHICTERRAIN, RAINDANCE, REST, RETURN, SCENTEDSHIELD, SEISMICCHANT, SHADOWBALL, SLEEPTALK, SLUDGEBOMB, SLUDGEWAVE, SOLARBEAM, SOULRIP, SOULSHIELD, SUNNYDAY, SYNTHESIS, TERRAINPULSE, TOXIC, TOXICSPIKES, UMBRALWAVE, VENOMDRAIN, VITALITYDRAIN, WAIL, WILLOWISP, WONDERROOM, | AA51: =VLOOKUP($A51,'Moves Species'!$A:$E,5,FALSE) -> DARKPULSE, GROWTH, LEECHSEED, INGRAIN, RAGEPOWDER, GRASSYTERRAIN, VITALITYDRAIN, ALLERGY, INFECTION, IMPRISON, DARKVOID, DIRGE, AUTUMNBLAST, | AB51: SHIINOTIC | AC51: Item | AD51: MOONSTONE
A52: =A51+1 -> 51 | B52: [SHIINOTIC] | C52: Shiinotic | D52: ='BST Extract'!J52 -> GHOST | E52: ='BST Extract'!K52 -> GRASS | F52: =D52&","&E52 -> GHOST,GRASS | G52: ='BST Extract'!C52 -> 90 | H52: ='BST Extract'!D52 -> 50 | I52: ='BST Extract'!E52 -> 75 | J52: ='BST Extract'!F52 -> 60 | K52: ='BST Extract'!G52 -> 90 | L52: ='BST Extract'!H52 -> 110 | M52: ='BST Extract'!I52 -> 475 | N52: SPECIAL_DEFENSE | O52: 2 | T52: =N52&","&O52&","&P52&","&Q52&","&R52&","&S52 -> SPECIAL_DEFENSE,2,,,, | U52: ='Ability Extract'!C52 -> BADDREAMS | V52: ='Ability Extract'!D52 -> TORMENTED | W52: ='Ability Extract'!E52 -> CURIOUSMEDICINE | X52: ='Ability Extract'!F52 -> BADDREAMS,TORMENTED,CURIOUSMEDICINE | Y52: =VLOOKUP($A52,'Moves Species'!$A:$E,3,FALSE) -> 1, HEALBLOCK, 1, CONFUSERAY, 1, GOOSEBUMP, 4, MEGADRAIN, 7, STUNSPORE, 7, POISONPOWDER, 11, SHIVER, 14, SLEEPPOWDER, 17, MAGICALLEAF, 20, GASTROACID, 23, HEX, 26, VEXINGVINES, 29, GIGADRAIN, 32, SHADOWBALL, 35, SPORE, 35, DREAMEATER, 35, NIGHTMARE, 38, SLUDGEBOMB, 41, ENERGYBALL, 44, MOONLIGHT, 47, ECTOPLASM, 50, STRENGTHSAP, 53, LEAFSTORM, 56, UMBRALWAVE, 60, DEATHWALTZ, | Z52: =VLOOKUP($A52,'Moves Species'!$A:$E,4,FALSE) -> ACIDRAIN, ALLERGY, AROMATHERAPY, ATTRACT, BONECHILL, BULLETSEED, CAUSTICACID, CHILLINGTOUCH, CLEARSMOG, CONCOCTION, CONFUSERAY, CORROSIVEGAS, CURSEDTOUCH, DARKPULSE, DAZZLINGGLEAM, ECLIPSENOVA, ENERGYBALL, ESSENCEBLOOM, FLUXWAVE, GASTROACID, GHASTLYFLOOD, GIGADRAIN, GOSSIP, GRASSYTERRAIN, GUNKSHOT, HAZE, HEX, HIDDENPOWER, LEAFBLADE, MACABREDANCE, MAGICALLEAF, MAGICROOM, MIASMA, MIXEDWAVES, NASTYPLOT, NECTARTAP, PETALTEMPEST, PHANTOMFORCE, PHOBIA, PIXIEDUST, POISONJAB, POLLENPUFF, POLTERGEIST, POSSESSION, PROTECT, PSYCHIC, PSYCHICTERRAIN, RAINDANCE, REST, RETURN, SCENTEDSHIELD, SEISMICCHANT, SHADOWBALL, SLEEPTALK, SLUDGEBOMB, SLUDGEWAVE, SOLARBEAM, SOULRIP, SOULSHIELD, SUNNYDAY, SYNTHESIS, TERRAINPULSE, TOXIC, TOXICSPIKES, UMBRALWAVE, VENOMDRAIN, VITALITYDRAIN, WAIL, WILLOWISP, WONDERROOM, | AA52: =VLOOKUP($A52,'Moves Species'!$A:$E,5,FALSE) -> 0
A53: =A52+1 -> 52 | B53: [LARVESTA] | C53: Larvesta | D53: ='BST Extract'!J53 -> BUG | E53: ='BST Extract'!K53 -> ELECTRIC | F53: =D53&","&E53 -> BUG,ELECTRIC | G53: ='BST Extract'!C53 -> 55 | H53: ='BST Extract'!D53 -> 85 | I53: ='BST Extract'!E53 -> 55 | J53: ='BST Extract'!F53 -> 60 | K53: ='BST Extract'!G53 -> 50 | L53: ='BST Extract'!H53 -> 55 | M53: ='BST Extract'!I53 -> 360 | N53: ATTACK | O53: 1 | T53: =N53&","&O53&","&P53&","&Q53&","&R53&","&S53 -> ATTACK,1,,,, | U53: ='Ability Extract'!C53 -> STATIC | V53: ='Ability Extract'!D53 -> TINTEDLENS | W53: ='Ability Extract'!E53 -> SWARM | X53: ='Ability Extract'!F53 -> STATIC,TINTEDLENS,SWARM | Y53: =VLOOKUP($A53,'Moves Species'!$A:$E,3,FALSE) -> 1, BUGSTING, 1, STATICSHOCK, 4, STRINGSHOT, 6, FIRSTIMPRESSION, 9, SUCKBLOOD, 12, SPARK, 15, BUGBITE, 18, PURGE, 21, ARCINGBLOW, 24, SKITTERSMACK, 27, AGILITY, 30, FANATICISM, 33, BALLLIGHTNING, 36, LEECHLIFE, 39, WILDCHARGE, 42, ATTACKORDER, 45, SWARMATTACK, 48, ENERGYSURGE, 51, RADIANTLANCE, 54, VOLTTACKLE, 57, SWARMOVERLOAD, 60, BOLTSTRIKE, | Z53: =VLOOKUP($A53,'Moves Species'!$A:$E,4,FALSE) -> AERIALACE, AERIALPULSE, ATTRACT, BALLLIGHTNING, BOLTCRASH, BUGBITE, BUGBUZZ, BULLETSEED, BUTTERFLYKISS, CALMMIND, CHARGEBEAM, CLEANSE, COUPDEGRACE, COVET, DAZZLINGGLEAM, DEFENDORDER, DIVINEPUNISHMENT, DUALWINGBEAT, DUNEBLAST, EARTHPOWER, ELECTRICTERRAIN, ELECTRONCRUSH, ENERGYBALL, ENERGYSURGE, FLUTTER, FLUXWAVE, GENESIS, GIGADRAIN, GRASSYTERRAIN, HIDDENPOWER, HIVEMIND, HURRICANE, LEECHLIFE, LIGHTSCREEN, MAGICALLEAF, NECTARTAP, PARABOLICCHARGE, PIXIEDUST, POLLENPUFF, PROTECT, PURGE, RADIANTLANCE, RAINBOWSCALES, RAYOFLIGHT, REFLECT, REST, RETURN, SACREDSTRIKE, SAFEGUARD, SANDSTORM, SCORCHINGSANDS, SIGNALBEAM, SLEEPTALK, SOLARBEAM, SONICBLAST, STRUGGLEBUG, SUBSTITUTE, SWARMATTACK, SWARMOVERLOAD, SYNTHESIS, TAILGLOW, TAILWIND, TEMPESTFLARE, THUNDER, THUNDERBOLT, THUNDERWAVE, TOXIC, UTURN, VENOMDRAIN, VOLTSWITCH, WILDCHARGE, WORKUP, | AA53: =VLOOKUP($A53,'Moves Species'!$A:$E,5,FALSE) -> ENDURE, FORESIGHT, HARDEN, EXTRASENSORY, MORNINGSUN, ZENHEADBUTT, QUIVERDANCE, THUNDERFANG, BOLTCRASH, PROTONCRASH, | AB53: VOLCARONA | AC53: Level | AD53: 50
A54: =A53+1 -> 53 | B54: [VOLCARONA] | C54: Volcarona | D54: ='BST Extract'!J54 -> BUG | E54: ='BST Extract'!K54 -> ELECTRIC | F54: =D54&","&E54 -> BUG,ELECTRIC | G54: ='BST Extract'!C54 -> 85 | H54: ='BST Extract'!D54 -> 135 | I54: ='BST Extract'!E54 -> 105 | J54: ='BST Extract'!F54 -> 85 | K54: ='BST Extract'!G54 -> 75 | L54: ='BST Extract'!H54 -> 65 | M54: ='BST Extract'!I54 -> 550 | N54: SPECIAL_ATTACK | O54: 3 | T54: =N54&","&O54&","&P54&","&Q54&","&R54&","&S54 -> SPECIAL_ATTACK,3,,,, | U54: ='Ability Extract'!C54 -> STATIC | V54: ='Ability Extract'!D54 -> TINTEDLENS | W54: ='Ability Extract'!E54 -> SWARM | X54: ='Ability Extract'!F54 -> STATIC,TINTEDLENS,SWARM | Y54: =VLOOKUP($A54,'Moves Species'!$A:$E,3,FALSE) -> 0, STORMSHIELD, 1, STORMSHIELD, 1, BUGSTING, 1, STATICSHOCK, 4, STRINGSHOT, 6, FIRSTIMPRESSION, 9, SUCKBLOOD, 12, SPARK, 15, BUGBITE, 18, PURGE, 21, ARCINGBLOW, 24, SKITTERSMACK, 27, AGILITY, 30, FANATICISM, 33, BALLLIGHTNING, 36, LEECHLIFE, 39, WILDCHARGE, 42, ATTACKORDER, 45, SWARMATTACK, 48, ENERGYSURGE, 51, RADIANTLANCE, 54, VOLTTACKLE, 57, SWARMOVERLOAD, 60, BOLTSTRIKE, | Z54: =VLOOKUP($A54,'Moves Species'!$A:$E,4,FALSE) -> AERIALACE, AERIALPULSE, ATTRACT, BALLLIGHTNING, BOLTCRASH, BUGBITE, BUGBUZZ, BULLETSEED, BUTTERFLYKISS, CALMMIND, CHARGEBEAM, CLEANSE, COUPDEGRACE, COVET, DAZZLINGGLEAM, DEFENDORDER, DIVINEPUNISHMENT, DUALWINGBEAT, DUNEBLAST, EARTHPOWER, ELECTRICTERRAIN, ELECTRONCRUSH, ENERGYBALL, ENERGYSURGE, FLUTTER, FLUXWAVE, GENESIS, GIGADRAIN, GRASSYTERRAIN, HIDDENPOWER, HIVEMIND, HURRICANE, LEECHLIFE, LIGHTSCREEN, MAGICALLEAF, NECTARTAP, PARABOLICCHARGE, PIXIEDUST, POLLENPUFF, PROTECT, PURGE, RADIANTLANCE, RAINBOWSCALES, RAYOFLIGHT, REFLECT, REST, RETURN, SACREDSTRIKE, SAFEGUARD, SANDSTORM, SCORCHINGSANDS, SIGNALBEAM, SLEEPTALK, SOLARBEAM, SONICBLAST, STRUGGLEBUG, SUBSTITUTE, SWARMATTACK, SWARMOVERLOAD, SYNTHESIS, TAILGLOW, TAILWIND, TEMPESTFLARE, THUNDER, THUNDERBOLT, THUNDERWAVE, TOXIC, UTURN, VENOMDRAIN, VOLTSWITCH, WILDCHARGE, WORKUP, | AA54: =VLOOKUP($A54,'Moves Species'!$A:$E,5,FALSE) -> 0
A55: =A54+1 -> 54 | B55: [STANTLER] | C55: Stantler | D55: ='BST Extract'!J55 -> ICE | E55: ='BST Extract'!K55 -> GRASS | F55: =D55&","&E55 -> ICE,GRASS | G55: ='BST Extract'!C55 -> 73 | H55: ='BST Extract'!D55 -> 90 | I55: ='BST Extract'!E55 -> 62 | J55: ='BST Extract'!F55 -> 85 | K55: ='BST Extract'!G55 -> 90 | L55: ='BST Extract'!H55 -> 65 | M55: ='BST Extract'!I55 -> 465 | N55: ATTACK | O55: 1 | T55: =N55&","&O55&","&P55&","&Q55&","&R55&","&S55 -> ATTACK,1,,,, | U55: ='Ability Extract'!C55 -> SERENEGRACE | V55: ='Ability Extract'!D55 -> HARVEST | W55: ='Ability Extract'!E55 -> PROTEAN | X55: ='Ability Extract'!F55 -> SERENEGRACE,HARVEST,PROTEAN | Y55: =VLOOKUP($A55,'Moves Species'!$A:$E,3,FALSE) -> 1, TACKLE, 1, LEER, 1, POWDERSNOW, 4, ESSENCEARROW, 7, RAZORLEAF, 7, ICICLESTRIKE, 9, STOMP, 12, CHILLINGBLAST, 15, AROMATHERAPY, 18, LEAFTORNADO, 21, LOWKICK, 24, ICEFANG, 27, FREEZEDRY, 30, HORNLEECH, 33, FABLEDRUSH, 36, ZENHEADBUTT, 36, ICICLECRASH, 39, AUTUMNBLAST, 42, ROCKCLIMB, 45, PETALBLIZZARD, 48, PRIMORDIALBEAM, 51, BLIZZARD, 54, MEGAHORN, 58, LEAFSTORM, 62, WINTERSHOWL, | Z55: =VLOOKUP($A55,'Moves Species'!$A:$E,4,FALSE) -> AROMATHERAPY, ATTRACT, BLIZZARD, BODYSLAM, BOUNCE, BULLDOZE, BULLETSEED, CALMMIND, CHILLINGTOUCH, COVET, ENERGYBALL, ESSENCEBLOOM, FAIRYTALE, GENESIS, GIGADRAIN, GRASSYTERRAIN, HAIL, HEALBELL, HIDDENPOWER, HIGHHORSEPOWER, HYPOTHERMIA, ICEBEAM, ICEFANG, ICEHAMMER, ICICLESPEAR, ICICLESTRIKE, ICYWIND, IRONHEAD, KNOCKOFF, LEAFBLADE, MAGICALLEAF, MIST, MISTYTERRAIN, NATURESWRATH, NUMBINGWIND, PETALTEMPEST, PIXIEDUST, PLAYROUGH, PROTECT, REST, RETURN, SAFEGUARD, SCENTEDSHIELD, SEISMICCHANT, SIGNALBEAM, SLEEPTALK, SOLARBEAM, SUBSTITUTE, SYNTHESIS, TAUNT, TERRAINPULSE, TOXIC, TRIPLEAXEL, VALKYRIECHARIOT, VOLTSWITCH, WEATHERBALL, WILDCHARGE, WISH, WORKUP, ZENHEADBUTT, | AA55: =VLOOKUP($A55,'Moves Species'!$A:$E,5,FALSE) -> BITE, EXTRASENSORY, GIGADRAIN, ICICLESPEAR, HAIL, THRASH, FORESTLEAP, MAGICALLEAF, STAMPEDE, ENTRAINMENT, DOUBLEKICK, FROSTNIP, WOODHAMMER, | AB55: WYRDEER | AC55: Item | AD55: ICESTONE
A56: =A55+1 -> 55 | B56: [MAGIKARP] | C56: Magikarp | D56: ='BST Extract'!J56 -> ELECTRIC | E56: ='BST Extract'!K56 -> DARK | F56: =D56&","&E56 -> ELECTRIC,DARK | G56: ='BST Extract'!C56 -> 20 | H56: ='BST Extract'!D56 -> 10 | I56: ='BST Extract'!E56 -> 55 | J56: ='BST Extract'!F56 -> 80 | K56: ='BST Extract'!G56 -> 15 | L56: ='BST Extract'!H56 -> 20 | M56: ='BST Extract'!I56 -> 200 | N56: SPEED | O56: 1 | T56: =N56&","&O56&","&P56&","&Q56&","&R56&","&S56 -> SPEED,1,,,, | U56: ='Ability Extract'!C56 -> SWIFTSWIM | V56: ='Ability Extract'!D56 -> BLACKLIGHT | W56: ='Ability Extract'!E56 -> RATTLED | X56: ='Ability Extract'!F56 -> SWIFTSWIM,BLACKLIGHT,RATTLED | Y56: =VLOOKUP($A56,'Moves Species'!$A:$E,3,FALSE) -> 1, MAIM, 1, SPARKLE, 5, BACKSTABBING, 10, SPARK, 15, FLAIL, | Z56: =VLOOKUP($A56,'Moves Species'!$A:$E,4,FALSE) -> AMBUSH, ANCIENTGLARE, ATTRACT, BALLLIGHTNING, BODYSLAM, BOLTCRASH, CHARGEBEAM, CLEANSE, COUPDEGRACE, CRUNCH, DARKPULSE, DAZZLINGGLEAM, DEAFEN, DRACARYS, DRACOMETEOR, DRAGONBREATH, DRAGONDANCE, DRAGONHAMMER, ECHOEDVOICE, ELECTRICTERRAIN, ELECTRONCRUSH, ENDERSHOCK, ENERGYSURGE, FIREFANG, FLUXWAVE, FROSTBITE, GAMMARAY, GASTROACID, HIDDENPOWER, ICEFANG, IRONHEAD, KNOCKOFF, LIGHTSCREEN, METEORDRIVE, NAGASKIN, NASTYPLOT, NOBLEROAR, OUTRAGE, OVERFLOW, PARABOLICCHARGE, PHOBIA, POISONFANG, POISONJAB, PROTECT, PSYCHICFANGS, PURGE, RADIANTLANCE, REFLECT, REST, RETURN, RISINGVOLTAGE, SCALD, SCALESHOT, SLEEPTALK, SNARL, SWITCHEROO, TAUNT, TERRAINPULSE, THUNDER, THUNDERBOLT, THUNDERFANG, THUNDERWAVE, TIDALWAVE, TOXIC, UMBRALWAVE, VENDETTA, VITALITYDRAIN, WAIL, WATERPRESSURE, WATERPULSE, WILDCHARGE, WORKUP, | AA56: =VLOOKUP($A56,'Moves Species'!$A:$E,5,FALSE) -> SKULLBASH, THRASH, TAKEDOWN, RADIANTBURST, FINALSTAND, HYPERFANG, | AB56: GYARADOS | AC56: ItemDeprecated | AD56: ROYALSTONE
A57: =A56+1 -> 56 | B57: [GYARADOS] | C57: Gyarados | D57: ='BST Extract'!J57 -> ELECTRIC | E57: ='BST Extract'!K57 -> DARK | F57: =D57&","&E57 -> ELECTRIC,DARK | G57: ='BST Extract'!C57 -> 95 | H57: ='BST Extract'!D57 -> 125 | I57: ='BST Extract'!E57 -> 110 | J57: ='BST Extract'!F57 -> 71 | K57: ='BST Extract'!G57 -> 55 | L57: ='BST Extract'!H57 -> 84 | M57: ='BST Extract'!I57 -> 540 | N57: ATTACK | O57: 2 | T57: =N57&","&O57&","&P57&","&Q57&","&R57&","&S57 -> ATTACK,2,,,, | U57: ='Ability Extract'!C57 -> ANGERPOINT | V57: ='Ability Extract'!D57 -> ILLUMINATE | W57: ='Ability Extract'!E57 -> LEECHINGFANGS | X57: ='Ability Extract'!F57 -> ANGERPOINT,ILLUMINATE,LEECHINGFANGS | Y57: =VLOOKUP($A57,'Moves Species'!$A:$E,3,FALSE) -> 0, THUNDERFANG, 0, ICEFANG, 0, FIREFANG, 1, THUNDERFANG, 1, ICEFANG, 1, FIREFANG, 1, MAIM, 1, SPARKLE, 5, BACKSTABBING, 10, SPARK, 15, FLAIL, 18, CHIPAWAY, 21, BITE, 24, SWAGGER, 27, VENDETTA, 30, PROTONCRASH, 30, IONDELUGE, 33, BODYSLAM, 36, CRUNCH, 39, SAVAGERY, 42, QUASH, 45, DRAGONDANCE, 48, ELECTRONCRUSH, 51, FRENZY, 54, FISHIOUSREND, 57, VOLTTACKLE, 60, DOUBLEEDGE, | Z57: =VLOOKUP($A57,'Moves Species'!$A:$E,4,FALSE) -> AMBUSH, ANCIENTGLARE, ATTRACT, BALLLIGHTNING, BODYSLAM, BOLTCRASH, CHARGEBEAM, CLEANSE, COUPDEGRACE, CRUNCH, DARKPULSE, DAZZLINGGLEAM, DEAFEN, DRACARYS, DRACOMETEOR, DRAGONBREATH, DRAGONDANCE, DRAGONHAMMER, ECHOEDVOICE, ELECTRICTERRAIN, ELECTRONCRUSH, ENDERSHOCK, ENERGYSURGE, FIREFANG, FLUXWAVE, FROSTBITE, GAMMARAY, GASTROACID, HIDDENPOWER, ICEFANG, IRONHEAD, KNOCKOFF, LIGHTSCREEN, METEORDRIVE, NAGASKIN, NASTYPLOT, NOBLEROAR, OUTRAGE, OVERFLOW, PARABOLICCHARGE, PHOBIA, POISONFANG, POISONJAB, PROTECT, PSYCHICFANGS, PURGE, RADIANTLANCE, REFLECT, REST, RETURN, RISINGVOLTAGE, SCALD, SCALESHOT, SLEEPTALK, SNARL, SWITCHEROO, TAUNT, TERRAINPULSE, THUNDER, THUNDERBOLT, THUNDERFANG, THUNDERWAVE, TIDALWAVE, TOXIC, UMBRALWAVE, VENDETTA, VITALITYDRAIN, WAIL, WATERPRESSURE, WATERPULSE, WILDCHARGE, WORKUP, | AA57: =VLOOKUP($A57,'Moves Species'!$A:$E,5,FALSE) -> 0
A58: =A57+1 -> 57 | B58: [BERGMITE] | C58: Bergmite | D58: ='BST Extract'!J58 -> ROCK | E58: ='BST Extract'!K58 -> 0 | F58: =D58&","&E58 -> ROCK,0 | G58: ='BST Extract'!C58 -> 55 | H58: ='BST Extract'!D58 -> 69 | I58: ='BST Extract'!E58 -> 85 | J58: ='BST Extract'!F58 -> 28 | K58: ='BST Extract'!G58 -> 32 | L58: ='BST Extract'!H58 -> 35 | M58: ='BST Extract'!I58 -> 304 | N58: DEFENSE | O58: 1 | T58: =N58&","&O58&","&P58&","&Q58&","&R58&","&S58 -> DEFENSE,1,,,, | U58: ='Ability Extract'!C58 -> IMPENETRABLE | V58: ='Ability Extract'!D58 -> PRESSURE | W58: ='Ability Extract'!E58 -> SOLIDROCK | X58: ='Ability Extract'!F58 -> IMPENETRABLE,PRESSURE,SOLIDROCK | Y58: =VLOOKUP($A58,'Moves Species'!$A:$E,3,FALSE) -> 1, ROCKTHROW, 1, FORTIFY, 1, MUDSPORT, 4, ACCELEROCK, 7, STEAMROLLER, 10, SANDSTORM, 13, BOULDERHURL, 16, BITE, 19, STEALTHROCK, 22, BULLDOZE, 25, ROCKPOLISH, 28, RECOVER, 31, ROCKSLIDE, 34, CRUNCH, 37, IRONDEFENSE, 40, LANDSWRATH, 43, CATAPULT, 46, SPIKYSHIELD, 49, EARTHQUAKE, 52, STONEEDGE, 55, SUPERPOWER, 58, CATACLYSM, 62, HEADSMASH, | Z58: =VLOOKUP($A58,'Moves Species'!$A:$E,4,FALSE) -> AMBUSH, ANCIENTGLARE, ASTEROIDBELT, ATTRACT, BODYPRESS, BODYSLAM, BOMBARDMENT, BOULDERCRUSH, BREAKINGSWIPE, BRICKBREAK, BULKUP, BULLDOZE, CATAPULT, CLOSECOMBAT, CRUNCH, CRYSTALSHOWER, CURSE, DRAGONBREATH, DRAGONHAMMER, DUNEBLAST, DUSTDEVILS, EARTHENLANCE, EARTHPOWER, EARTHQUAKE, ENDERSHOCK, FLAMECHARGE, FLAMEVOLLEY, FLAREBLITZ, FOCUSBLAST, GAIAPULSE, GEOMANCY, GOLDRUSH, HIDDENPOWER, HIGHHORSEPOWER, IRONDEFENSE, IRONHEAD, IRONIMPACT, IRONTEMPEST, MAGNETICCANNON, MAGNETRISE, METEORBEAM, METEORDRIVE, MINERALWAVE, MOONSTONERAY, MUDSHACKLES, MUDSLIDE, NOBLEROAR, OBSIDIANSHARDS, OUTRAGE, PERCUSSIONBLAST, PLAYROUGH, POWERGEM, PROTECT, QUICKSAND, REFURBISH, REST, RETURN, ROCKBLAST, ROCKSLIDE, ROCKTOMB, SANDSTORM, SANDTOMB, SCORCHINGSANDS, SEISMICCHANT, SLEEPTALK, SNARL, SPIKES, STEALTHROCK, STEELROLLER, STONEEDGE, SUBSTITUTE, SUPERPOWER, TAUNT, TOXIC, VENDETTA, WEAKSPOT, WILDCHARGE, WORKUP, ZENHEADBUTT, | AA58: =VLOOKUP($A58,'Moves Species'!$A:$E,5,FALSE) -> WIDEGUARD, EXPLOSION, HEAVYSLAM, HEATCRASH, CONTINENTALRIFT, ROCKTOMB, NERVESOFSTEEL, SHIELDBASH, SELFDESTRUCT, DIAMONDBLADE, WEARDOWN, | AB58: AVALUGG | AC58: Level | AD58: 37
A59: =A58+1 -> 58 | B59: [AVALUGG] | C59: Avalugg | D59: ='BST Extract'!J59 -> ROCK | E59: ='BST Extract'!K59 -> 0 | F59: =D59&","&E59 -> ROCK,0 | G59: ='BST Extract'!C59 -> 95 | H59: ='BST Extract'!D59 -> 105 | I59: ='BST Extract'!E59 -> 184 | J59: ='BST Extract'!F59 -> 28 | K59: ='BST Extract'!G59 -> 44 | L59: ='BST Extract'!H59 -> 58 | M59: ='BST Extract'!I59 -> 514 | N59: DEFENSE | O59: 2 | T59: =N59&","&O59&","&P59&","&Q59&","&R59&","&S59 -> DEFENSE,2,,,, | U59: ='Ability Extract'!C59 -> SANDSTREAM | V59: ='Ability Extract'!D59 -> PRESSURE | W59: ='Ability Extract'!E59 -> SOLIDROCK | X59: ='Ability Extract'!F59 -> SANDSTREAM,PRESSURE,SOLIDROCK | Y59: =VLOOKUP($A59,'Moves Species'!$A:$E,3,FALSE) -> 0, BODYPRESS, 1, BODYPRESS, 1, ROCKTHROW, 1, FORTIFY, 1, MUDSPORT, 4, ACCELEROCK, 7, STEAMROLLER, 10, SANDSTORM, 13, BOULDERHURL, 16, BITE, 19, STEALTHROCK, 22, BULLDOZE, 25, ROCKPOLISH, 28, RECOVER, 31, ROCKSLIDE, 34, CRUNCH, 37, IRONDEFENSE, 40, LANDSWRATH, 43, CATAPULT, 46, SPIKYSHIELD, 49, EARTHQUAKE, 52, STONEEDGE, 55, SUPERPOWER, 58, CATACLYSM, 62, HEADSMASH, | Z59: =VLOOKUP($A59,'Moves Species'!$A:$E,4,FALSE) -> AMBUSH, ANCIENTGLARE, ASTEROIDBELT, ATTRACT, BODYPRESS, BODYSLAM, BOMBARDMENT, BOULDERCRUSH, BREAKINGSWIPE, BRICKBREAK, BULKUP, BULLDOZE, CATAPULT, CLOSECOMBAT, CRUNCH, CRYSTALSHOWER, CURSE, DRAGONBREATH, DRAGONHAMMER, DUNEBLAST, DUSTDEVILS, EARTHENLANCE, EARTHPOWER, EARTHQUAKE, ENDERSHOCK, FLAMECHARGE, FLAMEVOLLEY, FLAREBLITZ, FOCUSBLAST, GAIAPULSE, GEOMANCY, GOLDRUSH, HIDDENPOWER, HIGHHORSEPOWER, IRONDEFENSE, IRONHEAD, IRONIMPACT, IRONTEMPEST, MAGNETICCANNON, MAGNETRISE, METEORBEAM, METEORDRIVE, MINERALWAVE, MOONSTONERAY, MUDSHACKLES, MUDSLIDE, NOBLEROAR, OBSIDIANSHARDS, OUTRAGE, PERCUSSIONBLAST, PLAYROUGH, POWERGEM, PROTECT, QUICKSAND, REFURBISH, REST, RETURN, ROCKBLAST, ROCKSLIDE, ROCKTOMB, SANDSTORM, SANDTOMB, SCORCHINGSANDS, SEISMICCHANT, SLEEPTALK, SNARL, SPIKES, STEALTHROCK, STEELROLLER, STONEEDGE, SUBSTITUTE, SUPERPOWER, TAUNT, TOXIC, VENDETTA, WEAKSPOT, WILDCHARGE, WORKUP, ZENHEADBUTT, | AA59: =VLOOKUP($A59,'Moves Species'!$A:$E,5,FALSE) -> 0
A60: =A59+1 -> 59 | B60: [LEDYBA] | C60: Ledyba | D60: ='BST Extract'!J60 -> BUG | E60: ='BST Extract'!K60 -> STEEL | F60: =D60&","&E60 -> BUG,STEEL | G60: ='BST Extract'!C60 -> 40 | H60: ='BST Extract'!D60 -> 40 | I60: ='BST Extract'!E60 -> 50 | J60: ='BST Extract'!F60 -> 65 | K60: ='BST Extract'!G60 -> 70 | L60: ='BST Extract'!H60 -> 55 | M60: ='BST Extract'!I60 -> 320 | N60: SPECIAL_ATTACK | O60: 1 | T60: =N60&","&O60&","&P60&","&Q60&","&R60&","&S60 -> SPECIAL_ATTACK,1,,,, | U60: ='Ability Extract'!C60 -> FORCEFIELD | V60: ='Ability Extract'!D60 -> TINTEDLENS | W60: ='Ability Extract'!E60 -> HEATPROOF | X60: ='Ability Extract'!F60 -> FORCEFIELD,TINTEDLENS,HEATPROOF | Y60: =VLOOKUP($A60,'Moves Species'!$A:$E,3,FALSE) -> 1, SUPERSONIC, 1, INFESTATION, 4, MISSILESHOT, 8, DETECT, 11, AUTOTOMIZE, 14, SILVERWIND, 17, IRONSPARKS, 20, METALSOUND, 20, SCREECH, 23, MIRRORSHOT, 26, RAINBOWSCALES, 29, SATELLITERAY, 32, LIGHTSCREEN, 32, REFLECT, 35, COBALTRAY, 38, BUGBUZZ, 41, MAGNETFORCE, 44, MAGNETICCANNON, 47, QUIVERDANCE, 50, SIGNALOVERLOAD, 53, PHOTONGEYSER, 56, STOREDPOWER, 60, CHROMERAY, | Z60: =VLOOKUP($A60,'Moves Species'!$A:$E,4,FALSE) -> ACROBATICS, AERIALACE, AERIALPULSE, AIRSLASH, ASTRALWIND, ATTRACT, BALLLIGHTNING, BOMBARDMENT, BRICKBREAK, BUGBITE, BUGBUZZ, BULLETSEED, CATAPULT, CLEANSE, CLUSTERROCKETS, CONFUSERAY, COVET, CRYSTALLINEBEAM, DAZZLINGGLEAM, DEAFEN, DEFENDORDER, DUALWINGBEAT, ECHOEDVOICE, ELECTRICTERRAIN, ELECTRONCRUSH, ENDERSHOCK, ENERGYBALL, ENERGYSURGE, FLAMECHARGE, FLUXWAVE, FOCUSBLAST, GAMMARAY, GIGADRAIN, GOLDENBULLET, GOSSIP, GYROBALL, HIDDENPOWER, IRONDEFENSE, IRONHEAD, IRONIMPACT, IRONTEMPEST, KAMEHAMEHA, LIGHTSCREEN, MAGNETICCANNON, MAGNETRISE, METEORBEAM, METEORDRIVE, METEORMASH, MIRRORSHOT, MISSILESHOT, NECTARTAP, OVERCLOCK, PARABOLICCHARGE, PINMISSILE, PIXIEDUST, PLAYROUGH, POWERGEM, PROTECT, QUICKGUARD, RAINBOWSCALES, RAYOFLIGHT, REFLECT, REFURBISH, REST, RETURN, RISINGVOLTAGE, ROCKBLAST, SAFEGUARD, SATELLITERAY, SIGNALBEAM, SLEEPTALK, SONICBLAST, SOUNDBARRIER, STRUGGLEBUG, SUBSTITUTE, SWARMATTACK, SWIFT, SWITCHEROO, TAILGLOW, TAILWIND, THUNDERBOLT, THUNDERPUNCH, TOXIC, TRIATTACK, UTURN, WILDCHARGE, WORKUP, | AA60: =VLOOKUP($A60,'Moves Species'!$A:$E,5,FALSE) -> DISCHARGE, METALBURST, AIRCUTTER, STICKYWEB, CHARGEBEAM, POLLENBLAST, CLACKACLACK, REFURBISH, HELPINGHAND, | AB60: LEDIAN | AC60: Level | AD60: 23
A61: =A60+1 -> 60 | B61: [LEDIAN] | C61: Ledian | D61: ='BST Extract'!J61 -> BUG | E61: ='BST Extract'!K61 -> STEEL | F61: =D61&","&E61 -> BUG,STEEL | G61: ='BST Extract'!C61 -> 60 | H61: ='BST Extract'!D61 -> 45 | I61: ='BST Extract'!E61 -> 75 | J61: ='BST Extract'!F61 -> 85 | K61: ='BST Extract'!G61 -> 95 | L61: ='BST Extract'!H61 -> 80 | M61: ='BST Extract'!I61 -> 440 | N61: SPECIAL_ATTACK | O61: 2 | T61: =N61&","&O61&","&P61&","&Q61&","&R61&","&S61 -> SPECIAL_ATTACK,2,,,, | U61: ='Ability Extract'!C61 -> FORCEFIELD | V61: ='Ability Extract'!D61 -> TINTEDLENS | W61: ='Ability Extract'!E61 -> HEATPROOF | X61: ='Ability Extract'!F61 -> FORCEFIELD,TINTEDLENS,HEATPROOF | Y61: =VLOOKUP($A61,'Moves Species'!$A:$E,3,FALSE) -> 1, SUPERSONIC, 1, INFESTATION, 4, MISSILESHOT, 8, DETECT, 11, AUTOTOMIZE, 14, SILVERWIND, 17, IRONSPARKS, 20, METALSOUND, 20, SCREECH, 23, MIRRORSHOT, 26, RAINBOWSCALES, 29, SATELLITERAY, 32, LIGHTSCREEN, 32, REFLECT, 35, COBALTRAY, 38, BUGBUZZ, 41, MAGNETFORCE, 44, MAGNETICCANNON, 47, QUIVERDANCE, 50, SIGNALOVERLOAD, 53, PHOTONGEYSER, 56, STOREDPOWER, 60, CHROMERAY, | Z61: =VLOOKUP($A61,'Moves Species'!$A:$E,4,FALSE) -> ACROBATICS, AERIALACE, AERIALPULSE, AIRSLASH, ASTRALWIND, ATTRACT, BALLLIGHTNING, BOMBARDMENT, BRICKBREAK, BUGBITE, BUGBUZZ, BULLETSEED, CATAPULT, CLEANSE, CLUSTERROCKETS, CONFUSERAY, COVET, CRYSTALLINEBEAM, DAZZLINGGLEAM, DEAFEN, DEFENDORDER, DUALWINGBEAT, ECHOEDVOICE, ELECTRICTERRAIN, ELECTRONCRUSH, ENDERSHOCK, ENERGYBALL, ENERGYSURGE, FLAMECHARGE, FLUXWAVE, FOCUSBLAST, GAMMARAY, GIGADRAIN, GOLDENBULLET, GOSSIP, GYROBALL, HIDDENPOWER, IRONDEFENSE, IRONHEAD, IRONIMPACT, IRONTEMPEST, KAMEHAMEHA, LIGHTSCREEN, MAGNETICCANNON, MAGNETRISE, METEORBEAM, METEORDRIVE, METEORMASH, MIRRORSHOT, MISSILESHOT, NECTARTAP, OVERCLOCK, PARABOLICCHARGE, PINMISSILE, PIXIEDUST, PLAYROUGH, POWERGEM, PROTECT, QUICKGUARD, RAINBOWSCALES, RAYOFLIGHT, REFLECT, REFURBISH, REST, RETURN, RISINGVOLTAGE, ROCKBLAST, SAFEGUARD, SATELLITERAY, SIGNALBEAM, SLEEPTALK, SONICBLAST, SOUNDBARRIER, STRUGGLEBUG, SUBSTITUTE, SWARMATTACK, SWIFT, SWITCHEROO, TAILGLOW, TAILWIND, THUNDERBOLT, THUNDERPUNCH, TOXIC, TRIATTACK, UTURN, WILDCHARGE, WORKUP, | AA61: =VLOOKUP($A61,'Moves Species'!$A:$E,5,FALSE) -> 0
A62: =A61+1 -> 61 | B62: [PONYTA] | C62: Ponyta | D62: ='BST Extract'!J62 -> GHOST | E62: ='BST Extract'!K62 -> FIRE | F62: =D62&","&E62 -> GHOST,FIRE | G62: ='BST Extract'!C62 -> 60 | H62: ='BST Extract'!D62 -> 75 | I62: ='BST Extract'!E62 -> 65 | J62: ='BST Extract'!F62 -> 90 | K62: ='BST Extract'!G62 -> 55 | L62: ='BST Extract'!H62 -> 65 | M62: ='BST Extract'!I62 -> 410 | N62: SPEED | O62: 1 | T62: =N62&","&O62&","&P62&","&Q62&","&R62&","&S62 -> SPEED,1,,,, | U62: ='Ability Extract'!C62 -> INFILTRATOR | V62: ='Ability Extract'!D62 -> AFTERMATH | W62: ='Ability Extract'!E62 -> RECKLESS | X62: ='Ability Extract'!F62 -> INFILTRATOR,AFTERMATH,RECKLESS | Y62: =VLOOKUP($A62,'Moves Species'!$A:$E,3,FALSE) -> 1, ASTONISH, 1, TAILWHIP, 1, SIZZLE, 4, SCORCH, 7, SHADOWSNEAK, 10, CONFUSERAY, 13, FLAMECHARGE, 16, SPECTRALLASH, 19, CRIMSONGATE, 22, FLAMEPILLAR, 25, TAKEDOWN, 28, AGILITY, 31, SPIRITSHACKLE, 34, HELLBRAND, 37, FABLEDRUSH, 40, DOUBLEKICK, 43, SPECTRALTHIEF, 46, BLAZEKICK, 49, PLAYROUGH, 52, HEADCHARGE, 56, POSSESSION, 60, FLAREBLITZ, | Z62: =VLOOKUP($A62,'Moves Species'!$A:$E,4,FALSE) -> AMBUSH, ATTRACT, BLOODRITUAL, BODYSLAM, BOUNCE, BURNINGJEALOUSY, BURNINGOFUDA, CLOSECOMBAT, CONFUSERAY, COUPDEGRACE, COVET, CRIMSONGATE, CURSE, CURSEDTOUCH, DARKPULSE, EARTHPOWER, ECLIPSENOVA, FIREBLAST, FIREFANG, FLAMECHARGE, FLAMETHROWER, FLAMEVOLLEY, FLAREBLITZ, GHASTLYFLOOD, GOLDRUSH, HAZE, HEATWAVE, HEX, HIDDENPOWER, HIGHHORSEPOWER, INCINERATE, KNOCKOFF, LASHOUT, LOVEBURST, MELTINGHORN, MEMENTO, METEORDRIVE, MIASMA, MYSTICALFIRE, NASTYPLOT, PHANTOMFORCE, POLTERGEIST, POSSESSION, PROTECT, REST, RETURN, SHADOWBALL, SLEEPTALK, SOULRIP, STELLARRUSH, SUNNYDAY, TAUNT, TERRAINPULSE, TOXIC, UMBRALWAVE, VENDETTA, VITALITYDRAIN, VOLTSWITCH, WILDCHARGE, WILDFIRE, WORKUP, ZENHEADBUTT, | AA62: =VLOOKUP($A62,'Moves Species'!$A:$E,5,FALSE) -> VALKYRIECHARIOT, GOLDENBULLET, DOUBLEEDGE, MACABREDANCE, PHANTOMFORCE, LASHOUT, FLAMEVOLLEY, WILDFIRE, DISTURB, SOULFLAY, FIREWALL, HEATSIPHON, SHADOWBONE, | AB62: RAPIDASH | AC62: Level | AD62: 38
A63: =A62+1 -> 62 | B63: [RAPIDASH] | C63: Rapidash | D63: ='BST Extract'!J63 -> GHOST | E63: ='BST Extract'!K63 -> FIRE | F63: =D63&","&E63 -> GHOST,FIRE | G63: ='BST Extract'!C63 -> 65 | H63: ='BST Extract'!D63 -> 105 | I63: ='BST Extract'!E63 -> 75 | J63: ='BST Extract'!F63 -> 110 | K63: ='BST Extract'!G63 -> 70 | L63: ='BST Extract'!H63 -> 85 | M63: ='BST Extract'!I63 -> 510 | N63: SPEED | O63: 2 | T63: =N63&","&O63&","&P63&","&Q63&","&R63&","&S63 -> SPEED,2,,,, | U63: ='Ability Extract'!C63 -> INFILTRATOR | V63: ='Ability Extract'!D63 -> AFTERMATH | W63: ='Ability Extract'!E63 -> RECKLESS | X63: ='Ability Extract'!F63 -> INFILTRATOR,AFTERMATH,RECKLESS | Y63: =VLOOKUP($A63,'Moves Species'!$A:$E,3,FALSE) -> 0, MELTINGHORN, 1, MELTINGHORN, 1, ASTONISH, 1, TAILWHIP, 1, SIZZLE, 4, SCORCH, 7, SHADOWSNEAK, 10, CONFUSERAY, 13, FLAMECHARGE, 16, SPECTRALLASH, 19, CRIMSONGATE, 22, FLAMEPILLAR, 25, TAKEDOWN, 28, AGILITY, 31, SPIRITSHACKLE, 34, HELLBRAND, 37, FABLEDRUSH, 40, DOUBLEKICK, 43, SPECTRALTHIEF, 46, BLAZEKICK, 49, PLAYROUGH, 52, HEADCHARGE, 56, POSSESSION, 60, FLAREBLITZ, | Z63: =VLOOKUP($A63,'Moves Species'!$A:$E,4,FALSE) -> AMBUSH, ATTRACT, BLOODRITUAL, BODYSLAM, BOUNCE, BURNINGJEALOUSY, BURNINGOFUDA, CLOSECOMBAT, CONFUSERAY, COUPDEGRACE, COVET, CRIMSONGATE, CURSE, CURSEDTOUCH, DARKPULSE, EARTHPOWER, ECLIPSENOVA, FIREBLAST, FIREFANG, FLAMECHARGE, FLAMETHROWER, FLAMEVOLLEY, FLAREBLITZ, GHASTLYFLOOD, GOLDRUSH, HAZE, HEATWAVE, HEX, HIDDENPOWER, HIGHHORSEPOWER, INCINERATE, KNOCKOFF, LASHOUT, LOVEBURST, MELTINGHORN, MEMENTO, METEORDRIVE, MIASMA, MYSTICALFIRE, NASTYPLOT, PHANTOMFORCE, POLTERGEIST, POSSESSION, PROTECT, REST, RETURN, SHADOWBALL, SLEEPTALK, SOULRIP, STELLARRUSH, SUNNYDAY, TAUNT, TERRAINPULSE, TOXIC, UMBRALWAVE, VENDETTA, VITALITYDRAIN, VOLTSWITCH, WILDCHARGE, WILDFIRE, WORKUP, ZENHEADBUTT, | AA63: =VLOOKUP($A63,'Moves Species'!$A:$E,5,FALSE) -> 0
A64: =A63+1 -> 63 | B64: [AMAURA] | C64: Amaura | D64: ='BST Extract'!J64 -> FAIRY | E64: ='BST Extract'!K64 -> DRAGON | F64: =D64&","&E64 -> FAIRY,DRAGON | G64: ='BST Extract'!C64 -> 82 | H64: ='BST Extract'!D64 -> 49 | I64: ='BST Extract'!E64 -> 45 | J64: ='BST Extract'!F64 -> 36 | K64: ='BST Extract'!G64 -> 77 | L64: ='BST Extract'!H64 -> 73 | M64: ='BST Extract'!I64 -> 362 | N64: HP | O64: 1 | T64: =N64&","&O64&","&P64&","&Q64&","&R64&","&S64 -> HP,1,,,, | U64: ='Ability Extract'!C64 -> FRIENDGUARD | V64: ='Ability Extract'!D64 -> ATTUNEMENT | W64: ='Ability Extract'!E64 -> MULTISCALE | X64: ='Ability Extract'!F64 -> FRIENDGUARD,ATTUNEMENT,MULTISCALE | Y64: =VLOOKUP($A64,'Moves Species'!$A:$E,3,FALSE) -> 1, FAIRYWIND, 1, TWISTER, 1, CRYSTALDUST, 4, FAIRYRING, 7, AROMATICMIST, 11, ENDERSHOCK, 14, DRAININGKISS, 17, DRACONICMIGHT, 20, DRACONICMAJESTY, 23, ANCIENTROAR, 26, MISTBALL, 29, CALMMIND, 32, MYSTICPULSE, 35, DAZZLINGGLEAM, 38, DRAGONPULSE, 41, HYPERVOICE, 44, APHRODITESMIRROR, 47, DRAGONGALE, 50, FAESBLESSING, 53, MOONLIGHT, 56, TITANIASLAW, 60, DRACOMETEOR, | Z64: =VLOOKUP($A64,'Moves Species'!$A:$E,4,FALSE) -> ANCIENTGLARE, ARCANEENERGY, AROMATHERAPY, ASTRALWIND, ATTRACT, AURASPHERE, BLIZZARD, BODYSLAM, BREAKINGSWIPE, CHARGEBEAM, CLEANSE, COSMICPOWER, COVET, CRYSTALLINEBEAM, DAZZLINGGLEAM, DEFOG, DIVINEPUNISHMENT, DRACARYS, DRACOMETEOR, DRACONICWAVE, DRAGONBREATH, DRAGONGALE, DRAGONMAGIC, EARTHPOWER, ECHOEDVOICE, ENDERSHOCK, ENERGYBALL, EXPANDINGFORCE, FABLEDRUSH, FAIRYTALE, FANTASYSEAL, FLUXWAVE, GENESIS, GENTLECHIMES, GEOMANCY, GLISTEN, HAIL, HEALBELL, HEXBOLT, HIDDENPOWER, HIGHHORSEPOWER, HOLYNOVA, HYPERVOICE, ICEBEAM, ICYWIND, LIGHTSCREEN, LOVEBURST, MAGICROOM, METEORBEAM, MINDMELD, MIRRORSHOT, MIST, MISTYTERRAIN, MIXEDWAVES, MOONBLAST, MOONSTONERAY, MYSTICPULSE, NAGASKIN, NASTYPLOT, NEBULASTRIKE, NOBLEROAR, OUTRAGE, PIXIEDUST, PLAYROUGH, POWERGEM, PROTECT, PSYCHIC, PSYCHICTERRAIN, RADIANTLANCE, RAYOFLIGHT, REFLECT, REST, RETURN, SACREDSTRIKE, SAFEGUARD, SIGNALBEAM, SIRENSSONG, SLEEPTALK, STARDUSTREVERIE, STRANGESTEAM, SWIFT, TERRAINPULSE, TITANIASLAW, TOXIC, VOLTSWITCH, WILDCHARGE, WONDERROOM, WORKUP, ZENHEADBUTT, | AA64: =VLOOKUP($A64,'Moves Species'!$A:$E,5,FALSE) -> REST, LIGHTSCREEN, BARRIER, AURORAVEIL, PEEKABOO, DRAGONMAGIC, CHARM, CAPTIVATE, ANCIENTGLARE, WYRMBEAM, HELPINGHAND, | AB64: AURORUS | AC64: LevelNight | AD64: 37
A65: =A64+1 -> 64 | B65: [AURORUS] | C65: Aurorus | D65: ='BST Extract'!J65 -> FAIRY | E65: ='BST Extract'!K65 -> DRAGON | F65: =D65&","&E65 -> FAIRY,DRAGON | G65: ='BST Extract'!C65 -> 123 | H65: ='BST Extract'!D65 -> 67 | I65: ='BST Extract'!E65 -> 72 | J65: ='BST Extract'!F65 -> 48 | K65: ='BST Extract'!G65 -> 109 | L65: ='BST Extract'!H65 -> 102 | M65: ='BST Extract'!I65 -> 521 | N65: HP | O65: 2 | T65: =N65&","&O65&","&P65&","&Q65&","&R65&","&S65 -> HP,2,,,, | U65: ='Ability Extract'!C65 -> FRIENDGUARD | V65: ='Ability Extract'!D65 -> ATTUNEMENT | W65: ='Ability Extract'!E65 -> MULTISCALE | X65: ='Ability Extract'!F65 -> FRIENDGUARD,ATTUNEMENT,MULTISCALE | Y65: =VLOOKUP($A65,'Moves Species'!$A:$E,3,FALSE) -> 0, MISTYTERRAIN, 1, MISTYTERRAIN, 1, FAIRYWIND, 1, TWISTER, 1, CRYSTALDUST, 4, FAIRYRING, 7, AROMATICMIST, 11, ENDERSHOCK, 14, DRAININGKISS, 17, DRACONICMIGHT, 20, DRACONICMAJESTY, 23, ANCIENTROAR, 26, MISTBALL, 29, CALMMIND, 32, MYSTICPULSE, 35, DAZZLINGGLEAM, 38, DRAGONPULSE, 41, HYPERVOICE, 44, APHRODITESMIRROR, 47, DRAGONGALE, 50, FAESBLESSING, 53, MOONLIGHT, 56, TITANIASLAW, 60, DRACOMETEOR, | Z65: =VLOOKUP($A65,'Moves Species'!$A:$E,4,FALSE) -> ANCIENTGLARE, ARCANEENERGY, AROMATHERAPY, ASTRALWIND, ATTRACT, AURASPHERE, BLIZZARD, BODYSLAM, BREAKINGSWIPE, CHARGEBEAM, CLEANSE, COSMICPOWER, COVET, CRYSTALLINEBEAM, DAZZLINGGLEAM, DEFOG, DIVINEPUNISHMENT, DRACARYS, DRACOMETEOR, DRACONICWAVE, DRAGONBREATH, DRAGONGALE, DRAGONMAGIC, EARTHPOWER, ECHOEDVOICE, ENDERSHOCK, ENERGYBALL, EXPANDINGFORCE, FABLEDRUSH, FAIRYTALE, FANTASYSEAL, FLUXWAVE, GENESIS, GENTLECHIMES, GEOMANCY, GLISTEN, HAIL, HEALBELL, HEXBOLT, HIDDENPOWER, HIGHHORSEPOWER, HOLYNOVA, HYPERVOICE, ICEBEAM, ICYWIND, LIGHTSCREEN, LOVEBURST, MAGICROOM, METEORBEAM, MINDMELD, MIRRORSHOT, MIST, MISTYTERRAIN, MIXEDWAVES, MOONBLAST, MOONSTONERAY, MYSTICPULSE, NAGASKIN, NASTYPLOT, NEBULASTRIKE, NOBLEROAR, OUTRAGE, PIXIEDUST, PLAYROUGH, POWERGEM, PROTECT, PSYCHIC, PSYCHICTERRAIN, RADIANTLANCE, RAYOFLIGHT, REFLECT, REST, RETURN, SACREDSTRIKE, SAFEGUARD, SIGNALBEAM, SIRENSSONG, SLEEPTALK, STARDUSTREVERIE, STRANGESTEAM, SWIFT, TERRAINPULSE, TITANIASLAW, TOXIC, VOLTSWITCH, WILDCHARGE, WONDERROOM, WORKUP, ZENHEADBUTT, | AA65: =VLOOKUP($A65,'Moves Species'!$A:$E,5,FALSE) -> 0
A66: =A65+1 -> 65 | B66: [GEODUDE] | C66: Geodude | D66: ='BST Extract'!J66 -> ROCK | E66: ='BST Extract'!K66 -> FIRE | F66: =D66&","&E66 -> ROCK,FIRE | G66: ='BST Extract'!C66 -> 60 | H66: ='BST Extract'!D66 -> 70 | I66: ='BST Extract'!E66 -> 70 | J66: ='BST Extract'!F66 -> 15 | K66: ='BST Extract'!G66 -> 25 | L66: ='BST Extract'!H66 -> 60 | M66: ='BST Extract'!I66 -> 300 | N66: DEFENSE | O66: 1 | T66: =N66&","&O66&","&P66&","&Q66&","&R66&","&S66 -> DEFENSE,1,,,, | U66: ='Ability Extract'!C66 -> STEAMENGINE | V66: ='Ability Extract'!D66 -> STURDY | W66: ='Ability Extract'!E66 -> DRYSKIN | X66: ='Ability Extract'!F66 -> STEAMENGINE,STURDY,DRYSKIN | Y66: =VLOOKUP($A66,'Moves Species'!$A:$E,3,FALSE) -> 1, STEALTHROCK, 1, DEFENSECURL, 1, ROLLOUT, 4, FIREBALL, 7, RAPIDSPIN, 10, ROCKPOLISH, 13, BOULDERHURL, 16, FLAMEWHEEL, 19, QUAKESLAM, 22, GEOMANCY, 25, CRIMSONGATE, 28, FIREPUNCH, 31, ROCKSLIDE, 34, SHOREUP, 37, HEATSIPHON, 40, CATAPULT, 43, BODYPRESS, 43, SHIELDBASH, 46, WILDFIRE, 49, STONESURGE, 52, FIREWALL, 56, FLAREBLITZ, 60, HEADSMASH, | Z66: =VLOOKUP($A66,'Moves Species'!$A:$E,4,FALSE) -> ASTEROIDBELT, ATTRACT, BODYPRESS, BODYSLAM, BOMBARDMENT, BOULDERCRUSH, BRICKBREAK, BULKUP, BULLDOZE, BURNINGJEALOUSY, CATAPULT, CLOSECOMBAT, CRIMSONGATE, CRYSTALLINEBEAM, CRYSTALSHOWER, CURSE, DRAINPUNCH, DUNEBLAST, DUSTDEVILS, EARTHENLANCE, EARTHPOWER, EARTHQUAKE, EXECUTION, FIREBLAST, FIREPUNCH, FLAMECHARGE, FLAMETHROWER, FLAMEVOLLEY, FLAREBLITZ, FOCUSBLAST, GAIAPULSE, GOLDRUSH, HEATWAVE, HIDDENPOWER, IRONDEFENSE, IRONHEAD, IRONIMPACT, KNOCKOFF, MINERALWAVE, MOONSTONERAY, MUDSLIDE, MYSTICALFIRE, OBSIDIANSHARDS, PLAYROUGH, POWERGEM, POWERUPPUNCH, PROTECT, REST, RETURN, ROCKBLAST, ROCKSLIDE, ROCKTOMB, SANDSTORM, SANDTOMB, SCALD, SCORCHINGSANDS, SEISMICCHANT, SLEEPTALK, STEALTHROCK, STONEEDGE, SUNNYDAY, SUPERPOWER, TAUNT, TERRAINPULSE, TOXIC, VENDETTA, WEAKSPOT, WILDCHARGE, WILDFIRE, WORKUP, ZENHEADBUTT, | AA66: =VLOOKUP($A66,'Moves Species'!$A:$E,5,FALSE) -> STONEEDGE, WIDEGUARD, IRONDEFENSE, ACCELEROCK, HEAVYSLAM, SANDTOMB, CONTINENTALRIFT, FLARESWEEP, ROCKWRECKER, OBSIDIANSHARDS, | AB66: GRAVELER | AC66: Level | AD66: 25
A67: =A66+1 -> 66 | B67: [GRAVELER] | C67: Graveler | D67: ='BST Extract'!J67 -> ROCK | E67: ='BST Extract'!K67 -> FIRE | F67: =D67&","&E67 -> ROCK,FIRE | G67: ='BST Extract'!C67 -> 70 | H67: ='BST Extract'!D67 -> 85 | I67: ='BST Extract'!E67 -> 95 | J67: ='BST Extract'!F67 -> 25 | K67: ='BST Extract'!G67 -> 35 | L67: ='BST Extract'!H67 -> 80 | M67: ='BST Extract'!I67 -> 390 | N67: DEFENSE | O67: 2 | T67: =N67&","&O67&","&P67&","&Q67&","&R67&","&S67 -> DEFENSE,2,,,, | U67: ='Ability Extract'!C67 -> STEAMENGINE | V67: ='Ability Extract'!D67 -> STURDY | W67: ='Ability Extract'!E67 -> DRYSKIN | X67: ='Ability Extract'!F67 -> STEAMENGINE,STURDY,DRYSKIN | Y67: =VLOOKUP($A67,'Moves Species'!$A:$E,3,FALSE) -> 0, TARSHOT, 1, TARSHOT, 1, STEALTHROCK, 1, DEFENSECURL, 1, ROLLOUT, 4, FIREBALL, 7, RAPIDSPIN, 10, ROCKPOLISH, 13, BOULDERHURL, 16, FLAMEWHEEL, 19, QUAKESLAM, 22, GEOMANCY, 25, CRIMSONGATE, 28, FIREPUNCH, 31, ROCKSLIDE, 34, SHOREUP, 37, HEATSIPHON, 40, CATAPULT, 43, BODYPRESS, 43, SHIELDBASH, 46, WILDFIRE, 49, STONESURGE, 52, FIREWALL, 56, FLAREBLITZ, 60, HEADSMASH, | Z67: =VLOOKUP($A67,'Moves Species'!$A:$E,4,FALSE) -> ASTEROIDBELT, ATTRACT, BODYPRESS, BODYSLAM, BOMBARDMENT, BOULDERCRUSH, BRICKBREAK, BULKUP, BULLDOZE, BURNINGJEALOUSY, CATAPULT, CLOSECOMBAT, CRIMSONGATE, CRYSTALLINEBEAM, CRYSTALSHOWER, CURSE, DRAINPUNCH, DUNEBLAST, DUSTDEVILS, EARTHENLANCE, EARTHPOWER, EARTHQUAKE, EXECUTION, FIREBLAST, FIREPUNCH, FLAMECHARGE, FLAMETHROWER, FLAMEVOLLEY, FLAREBLITZ, FOCUSBLAST, GAIAPULSE, GOLDRUSH, HEATWAVE, HIDDENPOWER, IRONDEFENSE, IRONHEAD, IRONIMPACT, KNOCKOFF, MINERALWAVE, MOONSTONERAY, MUDSLIDE, MYSTICALFIRE, OBSIDIANSHARDS, PLAYROUGH, POWERGEM, POWERUPPUNCH, PROTECT, REST, RETURN, ROCKBLAST, ROCKSLIDE, ROCKTOMB, SANDSTORM, SANDTOMB, SCALD, SCORCHINGSANDS, SEISMICCHANT, SLEEPTALK, STEALTHROCK, STONEEDGE, SUNNYDAY, SUPERPOWER, TAUNT, TERRAINPULSE, TOXIC, VENDETTA, WEAKSPOT, WILDCHARGE, WILDFIRE, WORKUP, ZENHEADBUTT, | AA67: =VLOOKUP($A67,'Moves Species'!$A:$E,5,FALSE) -> 0 | AB67: GOLEM | AC67: Item | AD67: FIRESTONE
A68: =A67+1 -> 67 | B68: [GOLEM] | C68: Golem | D68: ='BST Extract'!J68 -> ROCK | E68: ='BST Extract'!K68 -> FIRE | F68: =D68&","&E68 -> ROCK,FIRE | G68: ='BST Extract'!C68 -> 90 | H68: ='BST Extract'!D68 -> 110 | I68: ='BST Extract'!E68 -> 130 | J68: ='BST Extract'!F68 -> 35 | K68: ='BST Extract'!G68 -> 40 | L68: ='BST Extract'!H68 -> 90 | M68: ='BST Extract'!I68 -> 495 | N68: DEFENSE | O68: 3 | T68: =N68&","&O68&","&P68&","&Q68&","&R68&","&S68 -> DEFENSE,3,,,, | U68: ='Ability Extract'!C68 -> STEAMENGINE | V68: ='Ability Extract'!D68 -> STURDY | W68: ='Ability Extract'!E68 -> DRYSKIN | X68: ='Ability Extract'!F68 -> STEAMENGINE,STURDY,DRYSKIN | Y68: =VLOOKUP($A68,'Moves Species'!$A:$E,3,FALSE) -> 0, HEATCRASH, 1, HEATCRASH, 1, TARSHOT, 1, STEALTHROCK, 1, DEFENSECURL, 1, ROLLOUT, 4, FIREBALL, 7, RAPIDSPIN, 10, ROCKPOLISH, 13, BOULDERHURL, 16, FLAMEWHEEL, 19, QUAKESLAM, 22, GEOMANCY, 25, CRIMSONGATE, 28, FIREPUNCH, 31, ROCKSLIDE, 34, SHOREUP, 37, HEATSIPHON, 40, CATAPULT, 43, BODYPRESS, 43, SHIELDBASH, 46, WILDFIRE, 49, STONESURGE, 52, FIREWALL, 56, FLAREBLITZ, 60, HEADSMASH, | Z68: =VLOOKUP($A68,'Moves Species'!$A:$E,4,FALSE) -> ASTEROIDBELT, ATTRACT, BODYPRESS, BODYSLAM, BOMBARDMENT, BOULDERCRUSH, BRICKBREAK, BULKUP, BULLDOZE, BURNINGJEALOUSY, CATAPULT, CLOSECOMBAT, CRIMSONGATE, CRYSTALLINEBEAM, CRYSTALSHOWER, CURSE, DRAINPUNCH, DUNEBLAST, DUSTDEVILS, EARTHENLANCE, EARTHPOWER, EARTHQUAKE, EXECUTION, FIREBLAST, FIREPUNCH, FLAMECHARGE, FLAMETHROWER, FLAMEVOLLEY, FLAREBLITZ, FOCUSBLAST, GAIAPULSE, GOLDRUSH, HEATWAVE, HIDDENPOWER, IRONDEFENSE, IRONHEAD, IRONIMPACT, KNOCKOFF, MINERALWAVE, MOONSTONERAY, MUDSLIDE, MYSTICALFIRE, OBSIDIANSHARDS, PLAYROUGH, POWERGEM, POWERUPPUNCH, PROTECT, REST, RETURN, ROCKBLAST, ROCKSLIDE, ROCKTOMB, SANDSTORM, SANDTOMB, SCALD, SCORCHINGSANDS, SEISMICCHANT, SLEEPTALK, STEALTHROCK, STONEEDGE, SUNNYDAY, SUPERPOWER, TAUNT, TERRAINPULSE, TOXIC, VENDETTA, WEAKSPOT, WILDCHARGE, WILDFIRE, WORKUP, ZENHEADBUTT, | AA68: =VLOOKUP($A68,'Moves Species'!$A:$E,5,FALSE) -> 0
A69: =A68+1 -> 68 | B69: [SKRELP] | C69: Skrelp | D69: ='BST Extract'!J69 -> GRASS | E69: ='BST Extract'!K69 -> WATER | F69: =D69&","&E69 -> GRASS,WATER | G69: ='BST Extract'!C69 -> 60 | H69: ='BST Extract'!D69 -> 30 | I69: ='BST Extract'!E69 -> 50 | J69: ='BST Extract'!F69 -> 70 | K69: ='BST Extract'!G69 -> 60 | L69: ='BST Extract'!H69 -> 60 | M69: ='BST Extract'!I69 -> 330 | N69: SPECIAL_DEFENSE | O69: 1 | T69: =N69&","&O69&","&P69&","&Q69&","&R69&","&S69 -> SPECIAL_DEFENSE,1,,,, | U69: ='Ability Extract'!C69 -> REGROWTH | V69: ='Ability Extract'!D69 -> TORRENT | W69: ='Ability Extract'!E69 -> PROTEAN | X69: ='Ability Extract'!F69 -> REGROWTH,TORRENT,PROTEAN | Y69: =VLOOKUP($A69,'Moves Species'!$A:$E,3,FALSE) -> 1, ABSORB, 1, SMOKESCREEN, 1, TWISTER, 4, BUBBLE, 6, MEGADRAIN, 8, ACIDSPRAY, 11, RAINDANCE, 11, HAZE, 14, WATERPULSE, 17, LEAFTORNADO, 17, GROWTH, 20, MUDBOMB, 23, BRINE, 23, AQUARING, 26, MISTBALL, 29, GIGADRAIN, 32, OCEANBLAST, 35, AUTUMNBLAST, 35, EDENFRUIT, 38, MUDBLAST, 41, TIDALWAVE, 44, SYNTHESIS, 47, PRIMORDIALBEAM, 50, MUDDYWATER, 53, TIDALSHIFT, 56, LEAFSTORM, 60, HYDROPUMP, | Z69: =VLOOKUP($A69,'Moves Species'!$A:$E,4,FALSE) -> ATTRACT, BRINE, BULLETSEED, CASCADE, CLEARSMOG, DRAGONBREATH, DRAGONGALE, ENDERSHOCK, ENERGYBALL, ESSENCEBLOOM, FLIPTURN, FLUXWAVE, GENESIS, GIGADRAIN, GRASSYTERRAIN, HAZE, HEALBELL, HIDDENPOWER, ICEBEAM, ICYWIND, LEAFBLADE, LIQUIDATION, MAGICALLEAF, MIASMA, MIST, MUDSHACKLES, MUDSLIDE, MYSTICPULSE, NAGASKIN, NASTYPLOT, NATURESWRATH, NUMBINGWIND, OCEANWRATH, OUTRAGE, OVERFLOW, PETALTEMPEST, PIXIEDUST, POWERWHIP, PROTECT, RAINDANCE, REST, RETURN, SCALD, SCENTEDSHIELD, SIRENSSONG, SLEEPTALK, SLUDGEBOMB, SOAK, SOLARBEAM, SPIKES, SUBMERGE, SYNTHESIS, TERRAINPULSE, TIDALWAVE, TOXIC, WATERPRESSURE, WATERPULSE, WEATHERBALL, | AA69: =VLOOKUP($A69,'Moves Species'!$A:$E,5,FALSE) -> ACIDARMOR, WATERSPOUT, GRASSYTERRAIN, ICYWIND, AQUAJET, SLUDGEWAVE, BUBBLEBEAM, HYPERTORRENT, ESSENCEARROW, DRENCH, DRAGONPULSE, | AB69: DRAGALGE | AC69: Level | AD69: 42
A70: =A69+1 -> 69 | B70: [DRAGALGE] | C70: Dragalge | D70: ='BST Extract'!J70 -> GRASS | E70: ='BST Extract'!K70 -> WATER | F70: =D70&","&E70 -> GRASS,WATER | G70: ='BST Extract'!C70 -> 75 | H70: ='BST Extract'!D70 -> 45 | I70: ='BST Extract'!E70 -> 74 | J70: ='BST Extract'!F70 -> 80 | K70: ='BST Extract'!G70 -> 107 | L70: ='BST Extract'!H70 -> 123 | M70: ='BST Extract'!I70 -> 504 | N70: SPECIAL_DEFENSE | O70: 2 | T70: =N70&","&O70&","&P70&","&Q70&","&R70&","&S70 -> SPECIAL_DEFENSE,2,,,, | U70: ='Ability Extract'!C70 -> REGROWTH | V70: ='Ability Extract'!D70 -> TORRENT | W70: ='Ability Extract'!E70 -> PROTEAN | X70: ='Ability Extract'!F70 -> REGROWTH,TORRENT,PROTEAN | Y70: =VLOOKUP($A70,'Moves Species'!$A:$E,3,FALSE) -> 1, ABSORB, 1, SMOKESCREEN, 1, TWISTER, 4, BUBBLE, 6, MEGADRAIN, 8, ACIDSPRAY, 11, RAINDANCE, 11, HAZE, 14, WATERPULSE, 17, LEAFTORNADO, 17, GROWTH, 20, MUDBOMB, 23, BRINE, 23, AQUARING, 26, MISTBALL, 29, GIGADRAIN, 32, OCEANBLAST, 35, AUTUMNBLAST, 35, EDENFRUIT, 38, MUDBLAST, 41, TIDALWAVE, 44, SYNTHESIS, 47, PRIMORDIALBEAM, 50, MUDDYWATER, 53, TIDALSHIFT, 56, LEAFSTORM, 60, HYDROPUMP, | Z70: =VLOOKUP($A70,'Moves Species'!$A:$E,4,FALSE) -> ATTRACT, BRINE, BULLETSEED, CASCADE, CLEARSMOG, DRAGONBREATH, DRAGONGALE, ENDERSHOCK, ENERGYBALL, ESSENCEBLOOM, FLIPTURN, FLUXWAVE, GENESIS, GIGADRAIN, GRASSYTERRAIN, HAZE, HEALBELL, HIDDENPOWER, ICEBEAM, ICYWIND, LEAFBLADE, LIQUIDATION, MAGICALLEAF, MIASMA, MIST, MUDSHACKLES, MUDSLIDE, MYSTICPULSE, NAGASKIN, NASTYPLOT, NATURESWRATH, NUMBINGWIND, OCEANWRATH, OUTRAGE, OVERFLOW, PETALTEMPEST, PIXIEDUST, POWERWHIP, PROTECT, RAINDANCE, REST, RETURN, SCALD, SCENTEDSHIELD, SIRENSSONG, SLEEPTALK, SLUDGEBOMB, SOAK, SOLARBEAM, SPIKES, SUBMERGE, SYNTHESIS, TERRAINPULSE, TIDALWAVE, TOXIC, WATERPRESSURE, WATERPULSE, WEATHERBALL, | AA70: =VLOOKUP($A70,'Moves Species'!$A:$E,5,FALSE) -> 0
